Workbook

Sheet Bonds
A1: Date | B1: US TREASURY CS CPN. STRIP 15/05/38 - SPREAD | C1: US TREASURY BOND 1996 6% 15/02/26 - SPREAD | D1: US TREASURY BOND 1997 6 3/8% 15/08/27 - SPREAD | E1: US TREASURY BOND 1998 5 1/4% 15/11/28 - SPREAD | F1: US TREASURY CS CPN. STRIP 15/05/38 - MOD. DURATION | G1: US TREASURY BOND 1996 6% 15/02/26 - MOD. DURATION | H1: US TREASURY BOND 1997 6 3/8% 15/08/27 - MOD. DURATION | I1: US TREASURY BOND 1998 5 1/4% 15/11/28 - MOD. DURATION | J1: US TREASURY CS CPN. STRIP 15/05/38 - PRICE | K1: US TREASURY BOND 1996 6% 15/02/26 - PRICE | L1: US TREASURY BOND 1997 6 3/8% 15/08/27 - PRICE | M1: US TREASURY BOND 1998 5 1/4% 15/11/28 - PRICE | N1: US TREASURY CS CPN. STRIP 15/05/38 - RED. YIELD | O1: US TREASURY BOND 1996 6% 15/02/26 - RED. YIELD | P1: US TREASURY BOND 1997 6 3/8% 15/08/27 - RED. YIELD | Q1: US TREASURY BOND 1998 5 1/4% 15/11/28 - RED. YIELD | T1: Source: Datastream data provided with the assignment text. Ascending chronological order (oldest date on top).
A2: 42262 | B2: 38.6 | C2: 64.1 | D2: 10.5 | E2: 10.3 | F2: 12.1083 | G2: 0.4087 | H2: 1.7914 | I2: 2.8631 | J2: 56.871 | K2: 100.5664 | L2: 104.9844 | M2: 104.8438 | N2: 4.508 | O2: 4.5417 | P2: 3.653 | Q2: 3.6122
A3: 42263 | B3: 39.6 | C3: 68.9 | D3: 11.6 | E3: 10.9 | F3: 12.1071 | G3: 0.4112 | H3: 1.7938 | I3: 2.8652 | J3: 56.639 | K3: 100.543 | L3: 104.9336 | M3: 104.75 | N3: 4.5399 | O3: 4.6075 | P3: 3.6834 | Q3: 3.6442
A4: 42264 | B4: 39.9 | C4: 69.7 | D4: 10.5 | E4: 10 | F4: 12.1195 | G4: 0.4191 | H4: 1.8022 | I4: 2.874 | J4: 56.886 | K4: 100.5547 | L4: 105.0156 | M4: 104.8828 | N4: 4.5019 | O4: 4.6068 | P4: 3.651 | Q4: 3.6045
A5: 42265 | B5: 40.1 | C5: 44.1 | D5: 10.7 | E5: 8.5 | F5: 12.1186 | G5: 0.4222 | H5: 1.8048 | I5: 2.877 | J5: 56.671 | K5: 100.6641 | L5: 105.0078 | M5: 104.9375 | N5: 4.5315 | O5: 4.3591 | P5: 3.6587 | Q5: 3.5879
A6: 42268 | B6: 40.2 | C6: 43.3 | D6: 11.7 | E6: 8.4 | F6: 12.1169 | G6: 0.4249 | H6: 1.8073 | I6: 2.8795 | J6: 56.408 | K6: 100.6719 | L6: 104.9844 | M6: 104.9063 | N6: 4.5679 | O6: 4.3513 | P6: 3.6745 | Q6: 3.5993
A7: 42269 | B7: 40.2 | C7: 61.1 | D7: 9.2 | E7: 9 | F7: 12.1237 | G7: 0.4272 | H7: 1.8108 | I7: 2.8829 | J7: 56.65 | K7: 100.6016 | L7: 105.1406 | M7: 105.0313 | N7: 4.5324 | O7: 4.5245 | P7: 3.5963 | Q7: 3.5599
A8: 42270 | B8: 40.1 | C8: 56.3 | D8: 9.4 | E8: 8.3 | F8: 12.1203 | G8: 0.4299 | H8: 1.8132 | I8: 2.8852 | J8: 56.286 | K8: 100.625 | L8: 105.0898 | M8: 104.9609 | N8: 4.5834 | O8: 4.4798 | P8: 3.6265 | Q8: 3.5841
A9: 42271 | B9: 42.2 | C9: 46.6 | D9: 10.3 | E9: 11.1 | F9: 12.1167 | G9: 0.4379 | H9: 1.8205 | I9: 2.8917 | J9: 55.592 | K9: 100.6484 | L9: 104.9688 | M9: 104.7188 | N9: 4.6804 | O9: 4.4551 | P9: 3.7004 | Q9: 3.6665
A10: 42272 | B10: 41.9 | C10: 61.8 | D10: 11.1 | E10: 9 | F10: 12.113 | G10: 0.4402 | H10: 1.8228 | I10: 2.894 | J10: 55.221 | K10: 100.5742 | L10: 104.8984 | M10: 104.6563 | N10: 4.7335 | O10: 4.6316 | P10: 3.7406 | Q10: 3.688
A11: 42275 | B11: 43 | C11: 62.2 | D11: 10.5 | E11: 9.6 | F11: 12.1085 | G11: 0.4428 | H11: 1.8254 | I11: 2.8961 | J11: 54.805 | K11: 100.5703 | L11: 104.875 | M11: 104.5625 | N11: 4.7934 | O11: 4.6487 | P11: 3.7562 | Q11: 3.7197
A12: 42276 | B12: 44 | C12: 64.8 | D12: 10.7 | E12: 11.2 | F12: 12.1154 | G12: 0.4453 | H12: 1.8283 | I12: 2.8991 | J12: 55.046 | K12: 100.5664 | L12: 104.9258 | M12: 104.625 | N12: 4.7569 | O12: 4.6657 | P12: 3.7333 | Q12: 3.7005
A13: 42277 | B13: 43.9 | C13: 65.8 | D13: 11.1 | E13: 11.3 | F13: 12.1182 | G13: 0.448 | H13: 1.8309 | I13: 2.9018 | J13: 55.046 | K13: 100.5664 | L13: 104.9258 | M13: 104.625 | N13: 4.756 | O13: 4.6739 | P13: 3.7367 | Q13: 3.7017
... A2611: 45915 | B2611: 35.4 | C2611: -1.4 | D2611: 3.3 | E2611: 9 | F2611: 21.9653 | G2611: 8.164 | H2611: 8.9788 | I2611: 9.9069 | J2611: 49.368 | K2611: 134.1406 | L2611: 140.9844 | M2611: 130.6094 | N2611: 3.1393 | O2611: 2.2941 | P2611: 2.3992 | Q2611: 2.5051

Sheet Stocks
A1: Date | B1: WARNER BROS DISCOVERY SERIES A | C1: VISA 'A' | D1: MICROCHIP TECH. | E1: CONOCOPHILLIPS
A2: 42297 | B2: 29.18 | C2: 76.28 | D2: 23.7 | E2: 53.54
A3: 42298 | B3: 28.81 | C3: 75.46 | D3: 23.58 | E3: 52.97
A4: 42299 | B4: 29.45 | C4: 76.42 | D4: 24.43 | E4: 54.58
A5: 42300 | B5: 29.77 | C5: 77.07 | D5: 24.555 | E5: 54.61
A6: 42303 | B6: 29.29 | C6: 78.18 | D6: 24.255 | E6: 52.95
A7: 42304 | B7: 28.78 | C7: 77.52 | D7: 23.965 | E7: 51.69
A8: 42305 | B8: 29.53 | C8: 78.87 | D8: 24.28 | E8: 53.34
A9: 42306 | B9: 29.37 | C9: 78.51 | D9: 23.695 | E9: 53.62
A10: 42307 | B10: 29.44 | C10: 77.58 | D10: 24.145 | E10: 53.35
A11: 42310 | B11: 30.06 | C11: 75.22 | D11: 24.445 | E11: 54.94
A12: 42311 | B12: 31.08 | C12: 77.9 | D12: 24.41 | E12: 56.73
A13: 42312 | B13: 30.3 | C13: 78.35 | D13: 24.495 | E13: 56.34
... A2611: 45950 | B2611: 18.32 | C2611: 344.4099 | D2611: 67.07 | E2611: 87.06

Sheet Stocks Returns
A1: Date | B1: WARNER BROS DISCOVERY SERIES A | C1: VISA 'A' | D1: MICROCHIP TECH. | E1: CONOCOPHILLIPS
A2: =Stocks!A3 -> 42298 | B2: =Stocks!B3/Stocks!B2-1 -> -0.012679918 | C2: =Stocks!C3/Stocks!C2-1 -> -0.010749869 | D2: =Stocks!D3/Stocks!D2-1 -> -0.0050632911 | E2: =Stocks!E3/Stocks!E2-1 -> -0.010646246
A3: =Stocks!A4 -> 42299 | B3: =Stocks!B4/Stocks!B3-1 -> 0.022214509 | C3: =Stocks!C4/Stocks!C3-1 -> 0.012721972 | D3: =Stocks!D4/Stocks!D3-1 -> 0.036047498 | E3: =Stocks!E4/Stocks!E3-1 -> 0.030394563
A4: =Stocks!A5 -> 42300 | B4: =Stocks!B5/Stocks!B4-1 -> 0.010865874 | C4: =Stocks!C5/Stocks!C4-1 -> 0.0085056268 | D4: =Stocks!D5/Stocks!D4-1 -> 0.0051166598 | E4: =Stocks!E5/Stocks!E4-1 -> 0.00054965189
A5: =Stocks!A6 -> 42303 | B5: =Stocks!B6/Stocks!B5-1 -> -0.016123614 | C5: =Stocks!C6/Stocks!C5-1 -> 0.014402491 | D5: =Stocks!D6/Stocks!D5-1 -> -0.012217471 | E5: =Stocks!E6/Stocks!E5-1 -> -0.030397363
A6: =Stocks!A7 -> 42304 | B6: =Stocks!B7/Stocks!B6-1 -> -0.017412086 | C6: =Stocks!C7/Stocks!C6-1 -> -0.0084420568 | D6: =Stocks!D7/Stocks!D6-1 -> -0.011956298 | E6: =Stocks!E7/Stocks!E6-1 -> -0.023796034
A7: =Stocks!A8 -> 42305 | B7: =Stocks!B8/Stocks!B7-1 -> 0.026059764 | C7: =Stocks!C8/Stocks!C7-1 -> 0.017414861 | D7: =Stocks!D8/Stocks!D7-1 -> 0.013144169 | E7: =Stocks!E8/Stocks!E7-1 -> 0.031921068
A8: =Stocks!A9 -> 42306 | B8: =Stocks!B9/Stocks!B8-1 -> -0.0054182188 | C8: =Stocks!C9/Stocks!C8-1 -> -0.0045644732 | D8: =Stocks!D9/Stocks!D8-1 -> -0.024093904 | E8: =Stocks!E9/Stocks!E8-1 -> 0.0052493438
A9: =Stocks!A10 -> 42307 | B9: =Stocks!B10/Stocks!B9-1 -> 0.0023833844 | C9: =Stocks!C10/Stocks!C9-1 -> -0.011845625 | D9: =Stocks!D10/Stocks!D9-1 -> 0.018991348 | E9: =Stocks!E10/Stocks!E9-1 -> -0.0050354345
A10: =Stocks!A11 -> 42310 | B10: =Stocks!B11/Stocks!B10-1 -> 0.021059783 | C10: =Stocks!C11/Stocks!C10-1 -> -0.030420211 | D10: =Stocks!D11/Stocks!D10-1 -> 0.012424933 | E10: =Stocks!E11/Stocks!E10-1 -> 0.029803187
A11: =Stocks!A12 -> 42311 | B11: =Stocks!B12/Stocks!B11-1 -> 0.033932136 | C11: =Stocks!C12/Stocks!C11-1 -> 0.035628822 | D11: =Stocks!D12/Stocks!D11-1 -> -0.0014317856 | E11: =Stocks!E12/Stocks!E11-1 -> 0.032580997
A12: =Stocks!A13 -> 42312 | B12: =Stocks!B13/Stocks!B12-1 -> -0.025096525 | C12: =Stocks!C13/Stocks!C12-1 -> 0.0057766367 | D12: =Stocks!D13/Stocks!D12-1 -> 0.0034821794 | E12: =Stocks!E13/Stocks!E12-1 -> -0.0068746695
A13: =Stocks!A14 -> 42313 | B13: =Stocks!B14/Stocks!B13-1 -> -0.026072607 | C13: =Stocks!C14/Stocks!C13-1 -> 0.01161455 | D13: =Stocks!D14/Stocks!D13-1 -> -0.022045315 | E13: =Stocks!E14/Stocks!E13-1 -> -0.0010649627
... A2610: =Stocks!A2611 -> 45950 | B2610: =Stocks!B2611/Stocks!B2610-1 -> 0.0071467839 | C2610: =Stocks!C2611/Stocks!C2610-1 -> 0.0073707939 | D2610: =Stocks!D2611/Stocks!D2610-1 -> 0.029707531 | E2610: =Stocks!E2611/Stocks!E2610-1 -> 0.006706753

Sheet 1_Bonds
B2: POINT 1 - Immunized bond portfolio
B6: Rebalancing 1 | C6: 45792 | D6: row in Bonds: | E6: =MATCH($C$6,Bonds!$A:$A,0) -> 2524 | G6: Initial wealth of the block | H6: 100000
B7: Security | C7: Spread (bp) | D7: Mod. duration | E7: Price | F7: YTM (%) | G7: YTM (decimal) | H7: Weight w | I7: Capital invested | J7: No. of bonds | K7: w x duration | L7: w x spread | M7: Future wealth
B8: T-STRIP 15/05/38 | C8: =INDEX(Bonds!B:B,$E$6) -> 35.5 | D8: =INDEX(Bonds!F:F,$E$6) -> 21.6904 | E8: =INDEX(Bonds!J:J,$E$6) -> 52.088 | F8: =INDEX(Bonds!N:N,$E$6) -> 2.9421 | G8: =F8/100 -> 0.029421 | H8: 0.21 | I8: =$H$6*H8 -> 21000 | J8: =I8/E8 -> 403.16388 | K8: =H8*D8 -> 4.554984 | L8: =H8*C8 -> 7.455 | M8: =I8*(1+G8) -> 21617.841
B9: T-BOND 6% 15/02/26 | C9: =INDEX(Bonds!C:C,$E$6) -> -0.6 | D9: =INDEX(Bonds!G:G,$E$6) -> 7.8644 | E9: =INDEX(Bonds!K:K,$E$6) -> 135.3281 | F9: =INDEX(Bonds!O:O,$E$6) -> 2.0949 | G9: =F9/100 -> 0.020949 | H9: 0 | I9: =$H$6*H9 -> 0 | J9: =I9/E9 -> 0 | K9: =H9*D9 -> 0 | L9: =H9*C9 -> 0 | M9: =I9*(1+G9) -> 0
B10: T-BOND 6 3/8% 15/08/27 | C10: =INDEX(Bonds!D:D,$E$6) -> 2.4 | D10: =INDEX(Bonds!H:H,$E$6) -> 8.6914 | E10: =INDEX(Bonds!L:L,$E$6) -> 142.6875 | F10: =INDEX(Bonds!P:P,$E$6) -> 2.1849 | G10: =F10/100 -> 0.021849 | H10: 0.4 | I10: =$H$6*H10 -> 40000 | J10: =I10/E10 -> 280.3329 | K10: =H10*D10 -> 3.47656 | L10: =H10*C10 -> 0.96 | M10: =I10*(1+G10) -> 40873.96
B11: T-BOND 5 1/4% 15/11/28 | C11: =INDEX(Bonds!E:E,$E$6) -> 6.5 | D11: =INDEX(Bonds!I:I,$E$6) -> 9.8272 | E11: =INDEX(Bonds!M:M,$E$6) -> 132.9219 | F11: =INDEX(Bonds!Q:Q,$E$6) -> 2.276 | G11: =F11/100 -> 0.02276 | H11: 0.39 | I11: =$H$6*H11 -> 39000 | J11: =I11/E11 -> 293.40538 | K11: =H11*D11 -> 3.832608 | L11: =H11*C11 -> 2.535 | M11: =I11*(1+G11) -> 39887.64
B12: TOTAL | H12: =SUM(H8:H11) -> 1 | I12: =SUM(I8:I11) -> 100000 | K12: =SUM(K8:K11) -> 11.864152 | L12: =SUM(L8:L11) -> 10.95 | M12: =SUM(M8:M11) -> 102379.44
B14: CONSTRAINT CHECK
B15: Empirical average duration of the 4 bonds | E15: =AVERAGE(D8:D11) -> 12.01835
B16: Portfolio duration | E16: =K12 -> 11.864152
B17: Duration constraint (ptf <= average) | E17: =IF(K12<=AVERAGE(D8:D11)+0.0000001,"RESPECTED","VIOLATED") -> RESPECTED
B18: Empirical average spread of the 4 bonds | E18: =AVERAGE(C8:C11) -> 10.95
B19: Portfolio spread | E19: =L12 -> 10.95
B20: Spread constraint (ptf <= average) | E20: =IF(L12<=AVERAGE(C8:C11)+0.0000001,"RESPECTED","VIOLATED") -> RESPECTED
B21: Maximum weight on a single bond | E21: =MAX(H8:H11) -> 0.4
B22: 40% constraint per bond | E22: =IF(MAX(H8:H11)<=0.4000001,"RESPECTED","VIOLATED") -> RESPECTED
B23: Sum of weights | E23: =H12 -> 1
B25: RESULTS
B26: 1-year future wealth | E26: =M12 -> 102379.44
B27: Annual IRR of the bond portfolio (= risk-free rate) | E27: =M12/$H$6-1 -> 0.02379441
B28: Daily risk-free rate (252 days) | E28: =(1+E27)^(1/252)-1 -> 9.3320763e-05
B31: Rebalancing 2 | C31: 45824 | D31: row in Bonds: | E31: =MATCH($C$31,Bonds!$A:$A,0) -> 2546 | G31: Initial wealth of the block | H31: ='4_ExPost_Wealth'!M27 -> 98240.583
B32: Security | C32: Spread (bp) | D32: Mod. duration | E32: Price | F32: YTM (%) | G32: YTM (decimal) | H32: Weight w | I32: Capital invested | J32: No. of bonds | K32: w x duration | L32: w x spread | M32: Future wealth
B33: T-STRIP 15/05/38 | C33: =INDEX(Bonds!B:B,$E$31) -> 30 | D33: =INDEX(Bonds!F:F,$E$31) -> 21.75 | E33: =INDEX(Bonds!J:J,$E$31) -> 51.126 | F33: =INDEX(Bonds!N:N,$E$31) -> 3.0159 | G33: =F33/100 -> 0.030159 | H33: 0.2503324 | I33: =$H$31*H33 -> 24592.801 | J33: =I33/E33 -> 481.02338 | K33: =H33*D33 -> 5.4447298 | L33: =H33*C33 -> 7.5099721 | M33: =I33*(1+G33) -> 25334.495
B34: T-BOND 6% 15/02/26 | C34: =INDEX(Bonds!C:C,$E$31) -> -0.8 | D34: =INDEX(Bonds!G:G,$E$31) -> 7.922 | E34: =INDEX(Bonds!K:K,$E$31) -> 133.75 | F34: =INDEX(Bonds!O:O,$E$31) -> 2.2638 | G34: =F34/100 -> 0.022638 | H34: 0.16503266 | I34: =$H$31*H34 -> 16212.905 | J34: =I34/E34 -> 121.21798 | K34: =H34*D34 -> 1.3073888 | L34: =H34*C34 -> -0.13202613 | M34: =I34*(1+G34) -> 16579.933
B35: T-BOND 6 3/8% 15/08/27 | C35: =INDEX(Bonds!D:D,$E$31) -> 2.4 | D35: =INDEX(Bonds!H:H,$E$31) -> 8.7418 | E35: =INDEX(Bonds!L:L,$E$31) -> 140.8594 | F35: =INDEX(Bonds!P:P,$E$31) -> 2.3505 | G35: =F35/100 -> 0.023505 | H35: 0.4 | I35: =$H$31*H35 -> 39296.233 | J35: =I35/E35 -> 278.97487 | K35: =H35*D35 -> 3.49672 | L35: =H35*C35 -> 0.96 | M35: =I35*(1+G35) -> 40219.891
B36: T-BOND 5 1/4% 15/11/28 | C36: =INDEX(Bonds!E:E,$E$31) -> 6.7 | D36: =INDEX(Bonds!I:I,$E$31) -> 9.8736 | E36: =INDEX(Bonds!M:M,$E$31) -> 130.9688 | F36: =INDEX(Bonds!Q:Q,$E$31) -> 2.4391 | G36: =F36/100 -> 0.024391 | H36: 0.18463493 | I36: =$H$31*H36 -> 18138.643 | J36: =I36/E36 -> 138.49591 | K36: =H36*D36 -> 1.8230115 | L36: =H36*C36 -> 1.237054 | M36: =I36*(1+G36) -> 18581.063
B37: TOTAL | H37: =SUM(H33:H36) -> 1 | I37: =SUM(I33:I36) -> 98240.583 | K37: =SUM(K33:K36) -> 12.07185 | L37: =SUM(L33:L36) -> 9.575 | M37: =SUM(M33:M36) -> 100715.38
B39: CONSTRAINT CHECK
B40: Empirical average duration of the 4 bonds | E40: =AVERAGE(D33:D36) -> 12.07185
B41: Portfolio duration | E41: =K37 -> 12.07185
B42: Duration constraint (ptf <= average) | E42: =IF(K37<=AVERAGE(D33:D36)+0.0000001,"RESPECTED","VIOLATED") -> RESPECTED
B43: Empirical average spread of the 4 bonds | E43: =AVERAGE(C33:C36) -> 9.575
B44: Portfolio spread | E44: =L37 -> 9.575
B45: Spread constraint (ptf <= average) | E45: =IF(L37<=AVERAGE(C33:C36)+0.0000001,"RESPECTED","VIOLATED") -> RESPECTED
B46: Maximum weight on a single bond | E46: =MAX(H33:H36) -> 0.4
B47: 40% constraint per bond | E47: =IF(MAX(H33:H36)<=0.4000001,"RESPECTED","VIOLATED") -> RESPECTED
B48: Sum of weights | E48: =H37 -> 1
B50: RESULTS
B51: 1-year future wealth | E51: =M37 -> 100715.38
B52: Annual IRR of the bond portfolio (= risk-free rate) | E52: =M37/$H$31-1 -> 0.025191215
B53: Daily risk-free rate (252 days) | E53: =(1+E52)^(1/252)-1 -> 9.8731645e-05
B56: Rebalancing 3 | C56: 45853 | D56: row in Bonds: | E56: =MATCH($C$56,Bonds!$A:$A,0) -> 2567 | G56: Initial wealth of the block | H56: ='4_ExPost_Wealth'!M48 -> 97663.032
B57: Security | C57: Spread (bp) | D57: Mod. duration | E57: Price | F57: YTM (%) | G57: YTM (decimal) | H57: Weight w | I57: Capital invested | J57: No. of bonds | K57: w x duration | L57: w x spread | M57: Future wealth
B58: T-STRIP 15/05/38 | C58: =INDEX(Bonds!B:B,$E$56) -> 35.5 | D58: =INDEX(Bonds!F:F,$E$56) -> 21.8046 | E58: =INDEX(Bonds!J:J,$E$56) -> 49.832 | F58: =INDEX(Bonds!N:N,$E$56) -> 3.121 | G58: =F58/100 -> 0.03121 | H58: 0.2497243 | I58: =$H$56*H58 -> 24388.832 | J58: =I58/E58 -> 489.4211 | K58: =H58*D58 -> 5.4451385 | L58: =H58*C58 -> 8.8652127 | M58: =I58*(1+G58) -> 25150.008
B59: T-BOND 6% 15/02/26 | C59: =INDEX(Bonds!C:C,$E$56) -> -0.4 | D59: =INDEX(Bonds!G:G,$E$56) -> 7.9986 | E59: =INDEX(Bonds!K:K,$E$56) -> 133.8438 | F59: =INDEX(Bonds!O:O,$E$56) -> 2.2764 | G59: =F59/100 -> 0.022764 | H59: 0.16134324 | I59: =$H$56*H59 -> 15757.27 | J59: =I59/E59 -> 117.7288 | K59: =H59*D59 -> 1.29052 | L59: =H59*C59 -> -0.064537295 | M59: =I59*(1+G59) -> 16115.968
B60: T-BOND 6 3/8% 15/08/27 | C60: =INDEX(Bonds!D:D,$E$56) -> 3.9 | D60: =INDEX(Bonds!H:H,$E$56) -> 8.8148 | E60: =INDEX(Bonds!L:L,$E$56) -> 140.7344 | F60: =INDEX(Bonds!P:P,$E$56) -> 2.3793 | G60: =F60/100 -> 0.023793 | H60: 0.4 | I60: =$H$56*H60 -> 39065.213 | J60: =I60/E60 -> 277.58112 | K60: =H60*D60 -> 3.52592 | L60: =H60*C60 -> 1.56 | M60: =I60*(1+G60) -> 39994.692
B61: T-BOND 5 1/4% 15/11/28 | C61: =INDEX(Bonds!E:E,$E$56) -> 10 | D61: =INDEX(Bonds!I:I,$E$56) -> 9.9411 | E61: =INDEX(Bonds!M:M,$E$56) -> 130.4688 | F61: =INDEX(Bonds!Q:Q,$E$56) -> 2.4902 | G61: =F61/100 -> 0.024902 | H61: 0.18893246 | I61: =$H$56*H61 -> 18451.717 | J61: =I61/E61 -> 141.42628 | K61: =H61*D61 -> 1.8781965 | L61: =H61*C61 -> 1.8893246 | M61: =I61*(1+G61) -> 18911.202
B62: TOTAL | H62: =SUM(H58:H61) -> 1 | I62: =SUM(I58:I61) -> 97663.032 | K62: =SUM(K58:K61) -> 12.139775 | L62: =SUM(L58:L61) -> 12.25 | M62: =SUM(M58:M61) -> 100171.87
B64: CONSTRAINT CHECK
B65: Empirical average duration of the 4 bonds | E65: =AVERAGE(D58:D61) -> 12.139775
B66: Portfolio duration | E66: =K62 -> 12.139775
B67: Duration constraint (ptf <= average) | E67: =IF(K62<=AVERAGE(D58:D61)+0.0000001,"RESPECTED","VIOLATED") -> RESPECTED
B68: Empirical average spread of the 4 bonds | E68: =AVERAGE(C58:C61) -> 12.25
B69: Portfolio spread | E69: =L62 -> 12.25
B70: Spread constraint (ptf <= average) | E70: =IF(L62<=AVERAGE(C58:C61)+0.0000001,"RESPECTED","VIOLATED") -> RESPECTED
B71: Maximum weight on a single bond | E71: =MAX(H58:H61) -> 0.4
B72: 40% constraint per bond | E72: =IF(MAX(H58:H61)<=0.4000001,"RESPECTED","VIOLATED") -> RESPECTED
B73: Sum of weights | E73: =H62 -> 1
B75: RESULTS
B76: 1-year future wealth | E76: =M62 -> 100171.87
B77: Annual IRR of the bond portfolio (= risk-free rate) | E77: =M62/$H$56-1 -> 0.025688709
B78: Daily risk-free rate (252 days) | E78: =(1+E77)^(1/252)-1 -> 0.00010065704

Sheet 2_CVaR_t1
A2: POINT 2 - Mean-CVaR 3% frontier and investor's optimal portfolio - rebalancing 1 (15/05/2025)
G3: Valuation date | H3: 45792 | M3: MEAN-CVaR 3% EFFICIENT FRONTIER (no short selling)
G4: Sample rows in the Stocks Returns sheet | H4: 2 : 2498
A5: Date | B5: R risky ptf | C5: Loss L = -R | D5: X = final wealth | E5: u(X) | G5: Number of observations T | H5: =COUNT($B$6:$B$2502) -> 2497 | M5: Average return | N5: CVaR 3% | O5: w1 | P5: w2 | Q5: w3 | R5: w4 | S5: STARR
A6: ='Stocks Returns'!A2 -> 42298 | B6: =SUMPRODUCT('Stocks Returns'!B2:E2,$H$10:$K$10) -> -0.010418992 | C6: =-B6 -> 0.010418992 | D6: =1+$H$13+$H$19*(B6-$H$13) -> 0.99279778 | E6: =$H$22*D6-$H$23*D6^2-LN(1+$H$24*EXP(1-D6^3)) -> 1.5872294 | G6: Tail level alpha | H6: 0.03 | M6: 0.00064734709 | N6: 0.041445084 | O6: 0.080881658 | P6: 0.78778015 | Q6: 0 | R6: 0.13133819 | S6: =(M6-$H$13)/N6 -> 0.013367721
A7: ='Stocks Returns'!A3 -> 42299 | B7: =SUMPRODUCT('Stocks Returns'!B3:E3,$H$10:$K$10) -> 0.014112553 | C7: =-B7 -> -0.014112553 | D7: =1+$H$13+$H$19*(B7-$H$13) -> 1.0098227 | E7: =$H$22*D7-$H$23*D7^2-LN(1+$H$24*EXP(1-D7^3)) -> 1.6041633 | G7: k = ROUNDUP(T*alpha) - tail observations | H7: =ROUNDUP(H5*H6,0) -> 75 | M7: 0.00065045656 | N7: 0.041633287 | O7: 0.077588342 | P7: 0.79334893 | Q7: 0 | R7: 0.12906273 | S7: =(M7-$H$13)/N7 -> 0.013381979
A8: ='Stocks Returns'!A4 -> 42300 | B8: =SUMPRODUCT('Stocks Returns'!B4:E4,$H$10:$K$10) -> 0.0082931637 | C8: =-B8 -> -0.0082931637 | D8: =1+$H$13+$H$19*(B8-$H$13) -> 1.005784 | E8: =$H$22*D8-$H$23*D8^2-LN(1+$H$24*EXP(1-D8^3)) -> 1.6002517 | M8: 0.00065356602 | N8: 0.041457692 | O8: 0.074311457 | P8: 0.79895911 | Q8: 0 | R8: 0.12672944 | S8: =(M8-$H$13)/N8 -> 0.013513662
A9: ='Stocks Returns'!A5 -> 42303 | B9: =SUMPRODUCT('Stocks Returns'!B5:E5,$H$10:$K$10) -> 0.012767851 | C9: =-B9 -> -0.012767851 | D9: =1+$H$13+$H$19*(B9-$H$13) -> 1.0088894 | E9: =$H$22*D9-$H$23*D9^2-LN(1+$H$24*EXP(1-D9^3)) -> 1.6032654 | G9: Risky portfolio weights w* (Solver variable cells) | H9: WARNER BROS DISCOVERY | I9: VISA 'A' | J9: MICROCHIP TECH. | K9: CONOCOPHILLIPS | M9: 0.00065667548 | N9: 0.041650864 | O9: 0.069953459 | P9: 0.80184465 | Q9: 0 | R9: 0.12820189 | S9: =(M9-$H$13)/N9 -> 0.013525643
A10: ='Stocks Returns'!A6 -> 42304 | B10: =SUMPRODUCT('Stocks Returns'!B6:E6,$H$10:$K$10) -> -0.0086761187 | C10: =-B10 -> 0.0086761187 | D10: =1+$H$13+$H$19*(B10-$H$13) -> 0.99400733 | E10: =$H$22*D10-$H$23*D10^2-LN(1+$H$24*EXP(1-D10^3)) -> 1.5884707 | H10: 0 | I10: 0.93991483 | J10: 0.058150325 | K10: 0.0019348481 | M10: 0.00065978495 | N10: 0.041473334 | O10: 0.066254493 | P10: 0.8063911 | Q10: 0 | R10: 0.12735441 | S10: =(M10-$H$13)/N10 -> 0.013658516
A11: ='Stocks Returns'!A7 -> 42305 | B11: =SUMPRODUCT('Stocks Returns'!B7:E7,$H$10:$K$10) -> 0.017194586 | C11: =-B11 -> -0.017194586 | D11: =1+$H$13+$H$19*(B11-$H$13) -> 1.0119616 | E11: =$H$22*D11-$H$23*D11^2-LN(1+$H$24*EXP(1-D11^3)) -> 1.606208 | G11: Sum of weights (constraint = 1, no short selling) | H11: =SUM(H10:K10) -> 1 | M11: 0.00066289441 | N11: 0.041671054 | O11: 0.062555527 | P11: 0.81093754 | Q11: 0 | R11: 0.12650693 | S11: =(M11-$H$13)/N11 -> 0.013668328
A12: ='Stocks Returns'!A8 -> 42306 | B12: =SUMPRODUCT('Stocks Returns'!B8:E8,$H$10:$K$10) -> -0.0056811277 | C12: =-B12 -> 0.0056811277 | D12: =1+$H$13+$H$19*(B12-$H$13) -> 0.99608585 | E12: =$H$22*D12-$H$23*D12^2-LN(1+$H$24*EXP(1-D12^3)) -> 1.5905902 | G12: Annual IRR of the bond portfolio | H12: ='1_Bonds'!E27 -> 0.02379441 | M12: 0.00066600387 | N12: 0.041494336 | O12: 0.059456999 | P12: 0.81699722 | Q12: 0 | R12: 0.12354578 | S12: =(M12-$H$13)/N12 -> 0.013801477
A13: ='Stocks Returns'!A9 -> 42307 | B13: =SUMPRODUCT('Stocks Returns'!B9:E9,$H$10:$K$10) -> -0.010039268 | C13: =-B13 -> 0.010039268 | D13: =1+$H$13+$H$19*(B13-$H$13) -> 0.9930613 | E13: =$H$22*D13-$H$23*D13^2-LN(1+$H$24*EXP(1-D13^3)) -> 1.5875003 | G13: Daily risk-free rate rf | H13: =(1+H12)^(1/252)-1 -> 9.3320763e-05 | M13: 0.00066911334 | N13: 0.041692493 | O13: 0.056348755 | P13: 0.82303241 | Q13: 0 | R13: 0.12061883 | S13: =(M13-$H$13)/N13 -> 0.013810462
A14: ='Stocks Returns'!A10 -> 42310 | B14: =SUMPRODUCT('Stocks Returns'!B10:E10,$H$10:$K$10) -> -0.027812229 | C14: =-B14 -> 0.027812229 | D14: =1+$H$13+$H$19*(B14-$H$13) -> 0.98072687 | E14: =$H$22*D14-$H$23*D14^2-LN(1+$H$24*EXP(1-D14^3)) -> 1.5745283 | G14: Average daily return of the risky portfolio | H14: =AVERAGE($B$6:$B$2502) -> 0.00073752153 | M14: 0.0006722228 | N14: 0.041521844 | O14: 0.053394524 | P14: 0.82945575 | Q14: 0 | R14: 0.11714973 | S14: =(M14-$H$13)/N14 -> 0.013942108
A15: ='Stocks Returns'!A11 -> 42311 | B15: =SUMPRODUCT('Stocks Returns'!B11:E11,$H$10:$K$10) -> 0.033467839 | C15: =-B15 -> -0.033467839 | D15: =1+$H$13+$H$19*(B15-$H$13) -> 1.0232552 | E15: =$H$22*D15-$H$23*D15^2-LN(1+$H$24*EXP(1-D15^3)) -> 1.6166916 | G15: VaR 3% daily (loss, positive sign) | H15: =-SMALL($B$6:$B$2502,H7) -> 0.028802031 | M15: 0.00067533226 | N15: 0.04172372 | O15: 0.050417381 | P15: 0.83582134 | Q15: 0 | R15: 0.11376128 | S15: =(M15-$H$13)/N15 -> 0.013949176
A16: ='Stocks Returns'!A12 -> 42312 | B16: =SUMPRODUCT('Stocks Returns'!B12:E12,$H$10:$K$10) -> 0.0056187349 | C16: =-B16 -> -0.0056187349 | D16: =1+$H$13+$H$19*(B16-$H$13) -> 1.003928 | E16: =$H$22*D16-$H$23*D16^2-LN(1+$H$24*EXP(1-D16^3)) -> 1.5984319 | G16: CVaR 3% daily = average of the k worst returns (loss, positive sign) | H16: =-(SUMIF($B$6:$B$2502,"<"&-H15)+(-H15)*(H7-COUNTIF($B$6:$B$2502,"<"&-H15)))/H7 -> 0.042674545 | M16: 0.00067844173 | N16: 0.041742357 | O16: 0.047404175 | P16: 0.84209605 | Q16: 0 | R16: 0.11049977 | S16: =(M16-$H$13)/N16 -> 0.01401744
A17: ='Stocks Returns'!A13 -> 42313 | B17: =SUMPRODUCT('Stocks Returns'!B13:E13,$H$10:$K$10) -> 0.0096326851 | C17: =-B17 -> -0.0096326851 | D17: =1+$H$13+$H$19*(B17-$H$13) -> 1.0067136 | E17: =$H$22*D17-$H$23*D17^2-LN(1+$H$24*EXP(1-D17^3)) -> 1.601158 | G17: STARR = (mu - rf) / CVaR 3% | H17: =(H14-H13)/H16 -> 0.015095668 | M17: 0.00068155119 | N17: 0.041761225 | O17: 0.044390969 | P17: 0.84837076 | Q17: 0 | R17: 0.10723827 | S17: =(M17-$H$13)/N17 -> 0.014085565
A18: ='Stocks Returns'!A14 -> 42314 | B18: =SUMPRODUCT('Stocks Returns'!B14:E14,$H$10:$K$10) -> -0.0061382578 | C18: =-B18 -> 0.0061382578 | D18: =1+$H$13+$H$19*(B18-$H$13) -> 0.99576861 | E18: =$H$22*D18-$H$23*D18^2-LN(1+$H$24*EXP(1-D18^3)) -> 1.5902678 | M18: 0.00068466065 | N18: 0.041779985 | O18: 0.040892851 | P18: 0.85342338 | Q18: 0 | R18: 0.10568376 | S18: =(M18-$H$13)/N18 -> 0.014153664
A19: ='Stocks Returns'!A15 -> 42317 | B19: =SUMPRODUCT('Stocks Returns'!B15:E15,$H$10:$K$10) -> -0.0085558904 | C19: =-B19 -> 0.0085558904 | D19: =1+$H$13+$H$19*(B19-$H$13) -> 0.99409077 | E19: =$H$22*D19-$H$23*D19^2-LN(1+$H$24*EXP(1-D19^3)) -> 1.5885561 | G19: lambda = share invested in the risky portfolio | H19: 0.694 | M19: 0.00068777012 | N19: 0.041804898 | O19: 0.038017061 | P19: 0.86004441 | Q19: 0 | R19: 0.10193853 | S19: =(M19-$H$13)/N19 -> 0.01421961
A20: ='Stocks Returns'!A16 -> 42318 | B20: =SUMPRODUCT('Stocks Returns'!B16:E16,$H$10:$K$10) -> 0.016547154 | C20: =-B20 -> -0.016547154 | D20: =1+$H$13+$H$19*(B20-$H$13) -> 1.0115123 | E20: =$H$22*D20-$H$23*D20^2-LN(1+$H$24*EXP(1-D20^3)) -> 1.6057801 | G20: 1 - lambda = share in the risk-free asset | H20: =1-H19 -> 0.306 | M20: 0.00069087958 | N20: 0.041832838 | O20: 0.034362489 | P20: 0.86470274 | Q20: 0 | R20: 0.10093478 | S20: =(M20-$H$13)/N20 -> 0.014284443
A21: ='Stocks Returns'!A17 -> 42319 | B21: =SUMPRODUCT('Stocks Returns'!B17:E17,$H$10:$K$10) -> -0.0036645628 | C21: =-B21 -> 0.0036645628 | D21: =1+$H$13+$H$19*(B21-$H$13) -> 0.99748535 | E21: =$H$22*D21-$H$23*D21^2-LN(1+$H$24*EXP(1-D21^3)) -> 1.5920076 | M21: 0.00069398904 | N21: 0.041860779 | O21: 0.030707916 | P21: 0.86936106 | Q21: 0 | R21: 0.099931021 | S21: =(M21-$H$13)/N21 -> 0.01434919
A22: ='Stocks Returns'!A18 -> 42320 | B22: =SUMPRODUCT('Stocks Returns'!B18:E18,$H$10:$K$10) -> -0.011281921 | C22: =-B22 -> 0.011281921 | D22: =1+$H$13+$H$19*(B22-$H$13) -> 0.9921989 | E22: =$H$22*D22-$H$23*D22^2-LN(1+$H$24*EXP(1-D22^3)) -> 1.5866127 | G22: Parameter a (utility) | H22: 4 | M22: 0.0006970985 | N22: 0.041888719 | O22: 0.027053344 | P22: 0.87401939 | Q22: 0 | R22: 0.098927266 | S22: =(M22-$H$13)/N22 -> 0.014413851
A23: ='Stocks Returns'!A19 -> 42321 | B23: =SUMPRODUCT('Stocks Returns'!B19:E19,$H$10:$K$10) -> -0.0033211667 | C23: =-B23 -> 0.0033211667 | D23: =1+$H$13+$H$19*(B23-$H$13) -> 0.99772367 | E23: =$H$22*D23-$H$23*D23^2-LN(1+$H$24*EXP(1-D23^3)) -> 1.5922482 | G23: Parameter b (utility) | H23: 2 | M23: 0.00070020797 | N23: 0.041736515 | O23: 0.023156669 | P23: 0.87806757 | Q23: 0 | R23: 0.098775761 | S23: =(M23-$H$13)/N23 -> 0.014540917
A24: ='Stocks Returns'!A20 -> 42324 | B24: =SUMPRODUCT('Stocks Returns'!B20:E20,$H$10:$K$10) -> 0.0099960375 | C24: =-B24 -> -0.0099960375 | D24: =1+$H$13+$H$19*(B24-$H$13) -> 1.0069658 | E24: =$H$22*D24-$H$23*D24^2-LN(1+$H$24*EXP(1-D24^3)) -> 1.6014032 | G24: Parameter c (utility) | H24: 0.5 | M24: 0.00070331743 | N24: 0.041953002 | O24: 0.019225834 | P24: 0.88202966 | Q24: 0 | R24: 0.098744509 | S24: =(M24-$H$13)/N24 -> 0.014540001
A25: ='Stocks Returns'!A21 -> 42325 | B25: =SUMPRODUCT('Stocks Returns'!B21:E21,$H$10:$K$10) -> -0.00068610053 | C25: =-B25 -> 0.00068610053 | D25: =1+$H$13+$H$19*(B25-$H$13) -> 0.9995524 | E25: =$H$22*D25-$H$23*D25^2-LN(1+$H$24*EXP(1-D25^3)) -> 1.5940869 | G25: u(x) = a*x - b*x^2 - LN(1 + c*e^(1-x^3)) | M25: 0.00070642689 | N25: 0.041985683 | O25: 0.015294999 | P25: 0.88599174 | Q25: 0 | R25: 0.098713257 | S25: =(M25-$H$13)/N25 -> 0.014602743
A26: ='Stocks Returns'!A22 -> 42326 | B26: =SUMPRODUCT('Stocks Returns'!B22:E22,$H$10:$K$10) -> 0.02059157 | C26: =-B26 -> -0.02059157 | D26: =1+$H$13+$H$19*(B26-$H$13) -> 1.0143191 | E26: =$H$22*D26-$H$23*D26^2-LN(1+$H$24*EXP(1-D26^3)) -> 1.60844 | M26: 0.00070953636 | N26: 0.042018364 | O26: 0.011364165 | P26: 0.88995383 | Q26: 0 | R26: 0.098682005 | S26: =(M26-$H$13)/N26 -> 0.014665388
A27: ='Stocks Returns'!A23 -> 42327 | B27: =SUMPRODUCT('Stocks Returns'!B23:E23,$H$10:$K$10) -> -0.0034064673 | C27: =-B27 -> 0.0034064673 | D27: =1+$H$13+$H$19*(B27-$H$13) -> 0.99766447 | E27: =$H$22*D27-$H$23*D27^2-LN(1+$H$24*EXP(1-D27^3)) -> 1.5921885 | G27: E[u(X)] (Solver objective function on w* and lambda) | H27: =AVERAGE($E$6:$E$2502) -> 1.5948523 | M27: 0.00071264582 | N27: 0.042053616 | O27: 0.0082425113 | P27: 0.89595523 | Q27: 0 | R27: 0.09580226 | S27: =(M27-$H$13)/N27 -> 0.014727035
A28: ='Stocks Returns'!A24 -> 42328 | B28: =SUMPRODUCT('Stocks Returns'!B24:E24,$H$10:$K$10) -> 0.00069282336 | C28: =-B28 -> -0.00069282336 | D28: =1+$H$13+$H$19*(B28-$H$13) -> 1.0005094 | E28: =$H$22*D28-$H$23*D28^2-LN(1+$H$24*EXP(1-D28^3)) -> 1.5950437 | G28: E[X] | H28: =AVERAGE($D$6:$D$2502) -> 1.0005404 | M28: 0.00071575528 | N28: 0.042089182 | O28: 0.0051259082 | P28: 0.90196935 | Q28: 0 | R28: 0.092904739 | S28: =(M28-$H$13)/N28 -> 0.014788468
A29: ='Stocks Returns'!A25 -> 42331 | B29: =SUMPRODUCT('Stocks Returns'!B25:E25,$H$10:$K$10) -> -0.0018822016 | C29: =-B29 -> 0.0018822016 | D29: =1+$H$13+$H$19*(B29-$H$13) -> 0.99872231 | E29: =$H$22*D29-$H$23*D29^2-LN(1+$H$24*EXP(1-D29^3)) -> 1.5932539 | G29: Certainty equivalent CE (goal seek on H30 = 0) | H29: 1.0003176 | M29: 0.00071886475 | N29: 0.042126342 | O29: 0.00096558006 | P29: 0.90535307 | Q29: 0 | R29: 0.093681352 | S29: =(M29-$H$13)/N29 -> 0.014849236
A30: ='Stocks Returns'!A26 -> 42332 | B30: =SUMPRODUCT('Stocks Returns'!B26:E26,$H$10:$K$10) -> -0.0028942624 | C30: =-B30 -> 0.0028942624 | D30: =1+$H$13+$H$19*(B30-$H$13) -> 0.99801994 | E30: =$H$22*D30-$H$23*D30^2-LN(1+$H$24*EXP(1-D30^3)) -> 1.592547 | G30: Check: u(CE) - E[u(X)] (should be 0) | H30: =H22*H29-H23*H29^2-LN(1+H24*EXP(1-H29^3))-H27 -> 1.7297275e-13 | M30: 0.00072197421 | N30: 0.042181043 | O30: 0 | P30: 0.90906952 | Q30: 0.0097117959 | R30: 0.081218688 | S30: =(M30-$H$13)/N30 -> 0.014903696
A31: ='Stocks Returns'!A27 -> 42333 | B31: =SUMPRODUCT('Stocks Returns'!B27:E27,$H$10:$K$10) -> -0.0028407415 | C31: =-B31 -> 0.0028407415 | D31: =1+$H$13+$H$19*(B31-$H$13) -> 0.99805708 | E31: =$H$22*D31-$H$23*D31^2-LN(1+$H$24*EXP(1-D31^3)) -> 1.5925844 | G31: Daily risk premium = E[X] - CE | H31: =H28-H29 -> 0.00022282459 | M31: 0.00072508367 | N31: 0.042258493 | O31: 0 | P31: 0.9148837 | Q31: 0.01984602 | R31: 0.065270284 | S31: =(M31-$H$13)/N31 -> 0.014949963
A32: ='Stocks Returns'!A28 -> 42334 | B32: =SUMPRODUCT('Stocks Returns'!B28:E28,$H$10:$K$10) -> 0 | C32: =-B32 -> 0 | D32: =1+$H$13+$H$19*(B32-$H$13) -> 1.0000286 | E32: =$H$22*D32-$H$23*D32^2-LN(1+$H$24*EXP(1-D32^3)) -> 1.5945634 | G32: Annualized risk premium (x252) | H32: =H31*252 -> 0.056151796 | M32: 0.00072819314 | N32: 0.04235254 | O32: 0 | P32: 0.92014965 | Q32: 0.030670034 | R32: 0.04918032 | S32: =(M32-$H$13)/N32 -> 0.014990184
A33: ='Stocks Returns'!A29 -> 42335 | B33: =SUMPRODUCT('Stocks Returns'!B29:E29,$H$10:$K$10) -> 0.0039418578 | C33: =-B33 -> -0.0039418578 | D33: =1+$H$13+$H$19*(B33-$H$13) -> 1.0027642 | E33: =$H$22*D33-$H$23*D33^2-LN(1+$H$24*EXP(1-D33^3)) -> 1.5972838 | G33: Absolute risk aversion ARA(CE) = -u''/u' | H33: =-( (H22*(H29+0.00001)-H23*(H29+0.00001)^2-LN(1+H24*EXP(1-(H29+0.00001)^3))) -2*(H22*H29-H23*H29^2-LN(1+H24*EXP(1-H29^3))) +(H22*(H29-0.00001)-H23*(H29-0.00001)^2-LN(1+H24*EXP(1-(H29-0.00001)^3))) )/0.00001^2 / ( ((H22*(H29+0.00001)-H23*(H29+0.00001)^2-LN(1+H24*EXP(1-(H29+0.00001)^3))) -(H22*(H29-0.00001)-H23*(H29-0.00001)^2-LN(1+H24*EXP(1-(H29-0.00001)^3))))/(2*0.00001) ) -> 4.007633 | M33: 0.0007313026 | N33: 0.042446808 | O33: 0 | P33: 0.92568971 | Q33: 0.041149153 | R33: 0.033161136 | S33: =(M33-$H$13)/N33 -> 0.015030149
A34: ='Stocks Returns'!A30 -> 42338 | B34: =SUMPRODUCT('Stocks Returns'!B30:E30,$H$10:$K$10) -> -0.0090311261 | C34: =-B34 -> 0.0090311261 | D34: =1+$H$13+$H$19*(B34-$H$13) -> 0.99376095 | E34: =$H$22*D34-$H$23*D34^2-LN(1+$H$24*EXP(1-D34^3)) -> 1.5882183 | M34: 0.00073441206 | N34: 0.042544308 | O34: 0 | P34: 0.93244013 | Q34: 0.05010539 | R34: 0.017454482 | S34: =(M34-$H$13)/N34 -> 0.015068791
A35: ='Stocks Returns'!A31 -> 42339 | B35: =SUMPRODUCT('Stocks Returns'!B31:E31,$H$10:$K$10) -> 0.010979514 | C35: =-B35 -> -0.010979514 | D35: =1+$H$13+$H$19*(B35-$H$13) -> 1.0076483 | E35: =$H$22*D35-$H$23*D35^2-LN(1+$H$24*EXP(1-D35^3)) -> 1.6020656 | M35: 0.00073752153 | N35: 0.042674545 | O35: 0 | P35: 0.93991483 | Q35: 0.058150325 | R35: 0.0019348481 | S35: =(M35-$H$13)/N35 -> 0.015095668
A36: ='Stocks Returns'!A32 -> 42340 | B36: =SUMPRODUCT('Stocks Returns'!B32:E32,$H$10:$K$10) -> -0.012500651 | C36: =-B36 -> 0.012500651 | D36: =1+$H$13+$H$19*(B36-$H$13) -> 0.9913531 | E36: =$H$22*D36-$H$23*D36^2-LN(1+$H$24*EXP(1-D36^3)) -> 1.5857393 | M36: 0.00074063099 | N36: 0.042945575 | O36: 0 | P36: 1 | Q36: 0 | R36: 0 | S36: =(M36-$H$13)/N36 -> 0.015072804
A37: ='Stocks Returns'!A33 -> 42341 | B37: =SUMPRODUCT('Stocks Returns'!B33:E33,$H$10:$K$10) -> -0.0092399752 | C37: =-B37 -> 0.0092399752 | D37: =1+$H$13+$H$19*(B37-$H$13) -> 0.99361601 | E37: =$H$22*D37-$H$23*D37^2-LN(1+$H$24*EXP(1-D37^3)) -> 1.5880697
A38: ='Stocks Returns'!A34 -> 42342 | B38: =SUMPRODUCT('Stocks Returns'!B34:E34,$H$10:$K$10) -> 0.026493258 | C38: =-B38 -> -0.026493258 | D38: =1+$H$13+$H$19*(B38-$H$13) -> 1.0184149 | E38: =$H$22*D38-$H$23*D38^2-LN(1+$H$24*EXP(1-D38^3)) -> 1.6122632
A39: ='Stocks Returns'!A35 -> 42345 | B39: =SUMPRODUCT('Stocks Returns'!B35:E35,$H$10:$K$10) -> -0.010867093 | C39: =-B39 -> 0.010867093 | D39: =1+$H$13+$H$19*(B39-$H$13) -> 0.99248679 | E39: =$H$22*D39-$H$23*D39^2-LN(1+$H$24*EXP(1-D39^3)) -> 1.5869094
A40: ='Stocks Returns'!A36 -> 42346 | B40: =SUMPRODUCT('Stocks Returns'!B36:E36,$H$10:$K$10) -> -0.0062841315 | C40: =-B40 -> 0.0062841315 | D40: =1+$H$13+$H$19*(B40-$H$13) -> 0.99566737 | E40: =$H$22*D40-$H$23*D40^2-LN(1+$H$24*EXP(1-D40^3)) -> 1.5901648
A41: ='Stocks Returns'!A37 -> 42347 | B41: =SUMPRODUCT('Stocks Returns'!B37:E37,$H$10:$K$10) -> -0.015019741 | C41: =-B41 -> 0.015019741 | D41: =1+$H$13+$H$19*(B41-$H$13) -> 0.98960486 | E41: =$H$22*D41-$H$23*D41^2-LN(1+$H$24*EXP(1-D41^3)) -> 1.5839251
A42: ='Stocks Returns'!A38 -> 42348 | B42: =SUMPRODUCT('Stocks Returns'!B38:E38,$H$10:$K$10) -> 0.0027220009 | C42: =-B42 -> -0.0027220009 | D42: =1+$H$13+$H$19*(B42-$H$13) -> 1.0019176 | E42: =$H$22*D42-$H$23*D42^2-LN(1+$H$24*EXP(1-D42^3)) -> 1.5964452
A43: ='Stocks Returns'!A39 -> 42349 | B43: =SUMPRODUCT('Stocks Returns'!B39:E39,$H$10:$K$10) -> -0.025136927 | C43: =-B43 -> 0.025136927 | D43: =1+$H$13+$H$19*(B43-$H$13) -> 0.98258353 | E43: =$H$22*D43-$H$23*D43^2-LN(1+$H$24*EXP(1-D43^3)) -> 1.5765188
A44: ='Stocks Returns'!A40 -> 42352 | B44: =SUMPRODUCT('Stocks Returns'!B40:E40,$H$10:$K$10) -> 0.009402765 | C44: =-B44 -> -0.009402765 | D44: =1+$H$13+$H$19*(B44-$H$13) -> 1.0065541 | E44: =$H$22*D44-$H$23*D44^2-LN(1+$H$24*EXP(1-D44^3)) -> 1.6010027
A45: ='Stocks Returns'!A41 -> 42353 | B45: =SUMPRODUCT('Stocks Returns'!B41:E41,$H$10:$K$10) -> 0.023341212 | C45: =-B45 -> -0.023341212 | D45: =1+$H$13+$H$19*(B45-$H$13) -> 1.0162274 | E45: =$H$22*D45-$H$23*D45^2-LN(1+$H$24*EXP(1-D45^3)) -> 1.6102299
A46: ='Stocks Returns'!A42 -> 42354 | B46: =SUMPRODUCT('Stocks Returns'!B42:E42,$H$10:$K$10) -> 0.016090801 | C46: =-B46 -> -0.016090801 | D46: =1+$H$13+$H$19*(B46-$H$13) -> 1.0111956 | E46: =$H$22*D46-$H$23*D46^2-LN(1+$H$24*EXP(1-D46^3)) -> 1.6054779
A47: ='Stocks Returns'!A43 -> 42355 | B47: =SUMPRODUCT('Stocks Returns'!B43:E43,$H$10:$K$10) -> -0.014678526 | C47: =-B47 -> 0.014678526 | D47: =1+$H$13+$H$19*(B47-$H$13) -> 0.98984166 | E47: =$H$22*D47-$H$23*D47^2-LN(1+$H$24*EXP(1-D47^3)) -> 1.5841716
A48: ='Stocks Returns'!A44 -> 42356 | B48: =SUMPRODUCT('Stocks Returns'!B44:E44,$H$10:$K$10) -> -0.028802031 | C48: =-B48 -> 0.028802031 | D48: =1+$H$13+$H$19*(B48-$H$13) -> 0.98003995 | E48: =$H$22*D48-$H$23*D48^2-LN(1+$H$24*EXP(1-D48^3)) -> 1.5737886
... A2502: ='Stocks Returns'!A2498 -> 45792 | B2502: =SUMPRODUCT('Stocks Returns'!B2498:E2498,$H$10:$K$10) -> 0.015550899 | C2502: =-B2502 -> -0.015550899 | D2502: =1+$H$13+$H$19*(B2502-$H$13) -> 1.0108209 | E2502: =$H$22*D2502-$H$23*D2502^2-LN(1+$H$24*EXP(1-D2502^3)) -> 1.6051199

Sheet 2_CVaR_t2
A2: POINT 2 - Mean-CVaR 3% frontier and investor's optimal portfolio - rebalancing 2 (16/06/2025)
G3: Valuation date | H3: 45824 | M3: MEAN-CVaR 3% EFFICIENT FRONTIER (no short selling)
G4: Sample rows in the Stocks Returns sheet | H4: 2 : 2520
A5: Date | B5: R risky ptf | C5: Loss L = -R | D5: X = final wealth | E5: u(X) | G5: Number of observations T | H5: =COUNT($B$6:$B$2524) -> 2519 | M5: Average return | N5: CVaR 3% | O5: w1 | P5: w2 | Q5: w3 | R5: w4 | S5: STARR
A6: ='Stocks Returns'!A2 -> 42298 | B6: =SUMPRODUCT('Stocks Returns'!B2:E2,$H$10:$K$10) -> -0.010315385 | C6: =-B6 -> 0.010315385 | D6: =1+$H$13+$H$19*(B6-$H$13) -> 0.99301713 | E6: =$H$22*D6-$H$23*D6^2-LN(1+$H$24*EXP(1-D6^3)) -> 1.587455 | G6: Tail level alpha | H6: 0.03 | M6: 0.00064060391 | N6: 0.041388884 | O6: 0.082538734 | P6: 0.77877316 | Q6: 0 | R6: 0.13868811 | S6: =(M6-$H$13)/N6 -> 0.013092217
A7: ='Stocks Returns'!A3 -> 42299 | B7: =SUMPRODUCT('Stocks Returns'!B3:E3,$H$10:$K$10) -> 0.014562536 | C7: =-B7 -> -0.014562536 | D7: =1+$H$13+$H$19*(B7-$H$13) -> 1.0099341 | E7: =$H$22*D7-$H$23*D7^2-LN(1+$H$24*EXP(1-D7^3)) -> 1.6042703 | G7: k = ROUNDUP(T*alpha) - tail observations | H7: =ROUNDUP(H5*H6,0) -> 76 | M7: 0.00064382268 | N7: 0.041572984 | O7: 0.080236723 | P7: 0.78881477 | Q7: 0 | R7: 0.1309485 | S7: =(M7-$H$13)/N7 -> 0.013111665
A8: ='Stocks Returns'!A4 -> 42300 | B8: =SUMPRODUCT('Stocks Returns'!B4:E4,$H$10:$K$10) -> 0.0082199748 | C8: =-B8 -> -0.0082199748 | D8: =1+$H$13+$H$19*(B8-$H$13) -> 1.0056212 | E8: =$H$22*D8-$H$23*D8^2-LN(1+$H$24*EXP(1-D8^3)) -> 1.6000926 | M8: 0.00064704146 | N8: 0.041581075 | O8: 0.075255022 | P8: 0.79232559 | Q8: 0 | R8: 0.13241939 | S8: =(M8-$H$13)/N8 -> 0.013186523
A9: ='Stocks Returns'!A5 -> 42303 | B9: =SUMPRODUCT('Stocks Returns'!B5:E5,$H$10:$K$10) -> 0.012218608 | C9: =-B9 -> -0.012218608 | D9: =1+$H$13+$H$19*(B9-$H$13) -> 1.0083402 | E9: =$H$22*D9-$H$23*D9^2-LN(1+$H$24*EXP(1-D9^3)) -> 1.6027352 | G9: Risky portfolio weights w* (Solver variable cells) | H9: WARNER BROS DISCOVERY | I9: VISA 'A' | J9: MICROCHIP TECH. | K9: CONOCOPHILLIPS | M9: 0.00065026023 | N9: 0.041595028 | O9: 0.071586778 | P9: 0.79903749 | Q9: 0 | R9: 0.12937573 | S9: =(M9-$H$13)/N9 -> 0.013259483
A10: ='Stocks Returns'!A6 -> 42304 | B10: =SUMPRODUCT('Stocks Returns'!B6:E6,$H$10:$K$10) -> -0.0087623104 | C10: =-B10 -> 0.0087623104 | D10: =1+$H$13+$H$19*(B10-$H$13) -> 0.99407322 | E10: =$H$22*D10-$H$23*D10^2-LN(1+$H$24*EXP(1-D10^3)) -> 1.5885381 | H10: 0 | I10: 0.92027206 | J10: 0.076343536 | K10: 0.0033844055 | M10: 0.000653479 | N10: 0.041609352 | O10: 0.067535692 | P10: 0.80481636 | Q10: 0 | R10: 0.12764795 | S10: =(M10-$H$13)/N10 -> 0.013332276
A11: ='Stocks Returns'!A7 -> 42305 | B11: =SUMPRODUCT('Stocks Returns'!B7:E7,$H$10:$K$10) -> 0.017137916 | C11: =-B11 -> -0.017137916 | D11: =1+$H$13+$H$19*(B11-$H$13) -> 1.0116854 | E11: =$H$22*D11-$H$23*D11^2-LN(1+$H$24*EXP(1-D11^3)) -> 1.605945 | G11: Sum of weights (constraint = 1, no short selling) | H11: =SUM(H10:K10) -> 1 | M11: 0.00065669778 | N11: 0.041623888 | O11: 0.063266503 | P11: 0.81006367 | Q11: 0 | R11: 0.12666983 | S11: =(M11-$H$13)/N11 -> 0.01340495
A12: ='Stocks Returns'!A8 -> 42306 | B12: =SUMPRODUCT('Stocks Returns'!B8:E8,$H$10:$K$10) -> -0.0060222051 | C12: =-B12 -> 0.0060222051 | D12: =1+$H$13+$H$19*(B12-$H$13) -> 0.99593649 | E12: =$H$22*D12-$H$23*D12^2-LN(1+$H$24*EXP(1-D12^3)) -> 1.5904385 | G12: Annual IRR of the bond portfolio | H12: ='1_Bonds'!E52 -> 0.025191215 | M12: 0.00065991655 | N12: 0.041638937 | O12: 0.058469047 | P12: 0.81402352 | Q12: 0 | R12: 0.12750743 | S12: =(M12-$H$13)/N12 -> 0.013477407
A13: ='Stocks Returns'!A9 -> 42307 | B13: =SUMPRODUCT('Stocks Returns'!B9:E9,$H$10:$K$10) -> -0.0094683728 | C13: =-B13 -> 0.0094683728 | D13: =1+$H$13+$H$19*(B13-$H$13) -> 0.9935931 | E13: =$H$22*D13-$H$23*D13^2-LN(1+$H$24*EXP(1-D13^3)) -> 1.5880462 | G13: Daily risk-free rate rf | H13: =(1+H12)^(1/252)-1 -> 9.8731645e-05 | M13: 0.00066313533 | N13: 0.041471379 | O13: 0.054597319 | P13: 0.8202395 | Q13: 0 | R13: 0.12516318 | S13: =(M13-$H$13)/N13 -> 0.013609475
A14: ='Stocks Returns'!A10 -> 42310 | B14: =SUMPRODUCT('Stocks Returns'!B10:E10,$H$10:$K$10) -> -0.026945441 | C14: =-B14 -> 0.026945441 | D14: =1+$H$13+$H$19*(B14-$H$13) -> 0.98170869 | E14: =$H$22*D14-$H$23*D14^2-LN(1+$H$24*EXP(1-D14^3)) -> 1.5755826 | G14: Average daily return of the risky portfolio | H14: =AVERAGE($B$6:$B$2524) -> 0.0007275108 | M14: 0.0006663541 | N14: 0.041677955 | O14: 0.049733954 | P14: 0.82403872 | Q14: 0 | R14: 0.12622732 | S14: =(M14-$H$13)/N14 -> 0.013619249
A15: ='Stocks Returns'!A11 -> 42311 | B15: =SUMPRODUCT('Stocks Returns'!B11:E11,$H$10:$K$10) -> 0.032789169 | C15: =-B15 -> -0.032789169 | D15: =1+$H$13+$H$19*(B15-$H$13) -> 1.0223282 | E15: =$H$22*D15-$H$23*D15^2-LN(1+$H$24*EXP(1-D15^3)) -> 1.6158511 | G15: VaR 3% daily (loss, positive sign) | H15: =-SMALL($B$6:$B$2524,H7) -> 0.029215281 | M15: 0.00066957287 | N15: 0.041701263 | O15: 0.044419523 | P15: 0.82673862 | Q15: 0 | R15: 0.12884185 | S15: =(M15-$H$13)/N15 -> 0.013688823
A16: ='Stocks Returns'!A12 -> 42312 | B16: =SUMPRODUCT('Stocks Returns'!B12:E12,$H$10:$K$10) -> 0.0055586526 | C16: =-B16 -> -0.0055586526 | D16: =1+$H$13+$H$19*(B16-$H$13) -> 1.0038115 | E16: =$H$22*D16-$H$23*D16^2-LN(1+$H$24*EXP(1-D16^3)) -> 1.5983172 | G16: CVaR 3% daily = average of the k worst returns (loss, positive sign) | H16: =-(SUMIF($B$6:$B$2524,"<"&-H15)+(-H15)*(H7-COUNTIF($B$6:$B$2524,"<"&-H15)))/H7 -> 0.042734434 | M16: 0.00067279165 | N16: 0.041725983 | O16: 0.040723972 | P16: 0.83338398 | Q16: 0 | R16: 0.12589205 | S16: =(M16-$H$13)/N16 -> 0.013757854
A17: ='Stocks Returns'!A13 -> 42313 | B17: =SUMPRODUCT('Stocks Returns'!B13:E13,$H$10:$K$10) -> 0.0090019243 | C17: =-B17 -> -0.0090019243 | D17: =1+$H$13+$H$19*(B17-$H$13) -> 1.0061529 | E17: =$H$22*D17-$H$23*D17^2-LN(1+$H$24*EXP(1-D17^3)) -> 1.6006118 | G17: STARR = (mu - rf) / CVaR 3% | H17: =(H14-H13)/H16 -> 0.014713642 | M17: 0.00067601042 | N17: 0.041755465 | O17: 0.040784231 | P17: 0.8491828 | Q17: 0 | R17: 0.11003297 | S17: =(M17-$H$13)/N17 -> 0.013825227
A18: ='Stocks Returns'!A14 -> 42314 | B18: =SUMPRODUCT('Stocks Returns'!B14:E14,$H$10:$K$10) -> -0.0060477859 | C18: =-B18 -> 0.0060477859 | D18: =1+$H$13+$H$19*(B18-$H$13) -> 0.9959191 | E18: =$H$22*D18-$H$23*D18^2-LN(1+$H$24*EXP(1-D18^3)) -> 1.5904208 | M18: 0.00067922919 | N18: 0.041784747 | O18: 0.034240761 | P18: 0.84888735 | Q18: 0 | R18: 0.11687189 | S18: =(M18-$H$13)/N18 -> 0.013892571
A19: ='Stocks Returns'!A15 -> 42317 | B19: =SUMPRODUCT('Stocks Returns'!B15:E15,$H$10:$K$10) -> -0.0084214718 | C19: =-B19 -> 0.0084214718 | D19: =1+$H$13+$H$19*(B19-$H$13) -> 0.99430499 | E19: =$H$22*D19-$H$23*D19^2-LN(1+$H$24*EXP(1-D19^3)) -> 1.5887753 | G19: lambda = share invested in the risky portfolio | H19: 0.68 | M19: 0.00068244797 | N19: 0.041818631 | O19: 0.029092405 | P19: 0.85199201 | Q19: 0 | R19: 0.11891559 | S19: =(M19-$H$13)/N19 -> 0.013958284
A20: ='Stocks Returns'!A16 -> 42318 | B20: =SUMPRODUCT('Stocks Returns'!B16:E16,$H$10:$K$10) -> 0.015935747 | C20: =-B20 -> -0.015935747 | D20: =1+$H$13+$H$19*(B20-$H$13) -> 1.0108679 | E20: =$H$22*D20-$H$23*D20^2-LN(1+$H$24*EXP(1-D20^3)) -> 1.6051649 | G20: 1 - lambda = share in the risk-free asset | H20: =1-H19 -> 0.32 | M20: 0.00068566674 | N20: 0.041854938 | O20: 0.025962047 | P20: 0.86001482 | Q20: 0 | R20: 0.11402314 | S20: =(M20-$H$13)/N20 -> 0.014023079
A21: ='Stocks Returns'!A17 -> 42319 | B21: =SUMPRODUCT('Stocks Returns'!B17:E17,$H$10:$K$10) -> -0.0036456616 | C21: =-B21 -> 0.0036456616 | D21: =1+$H$13+$H$19*(B21-$H$13) -> 0.99755254 | E21: =$H$22*D21-$H$23*D21^2-LN(1+$H$24*EXP(1-D21^3)) -> 1.5920755 | M21: 0.00068888552 | N21: 0.041890855 | O21: 0.022507049 | P21: 0.86724644 | Q21: 0 | R21: 0.11024652 | S21: =(M21-$H$13)/N21 -> 0.014087893
A22: ='Stocks Returns'!A18 -> 42320 | B22: =SUMPRODUCT('Stocks Returns'!B18:E18,$H$10:$K$10) -> -0.011387943 | C22: =-B22 -> 0.011387943 | D22: =1+$H$13+$H$19*(B22-$H$13) -> 0.99228779 | E22: =$H$22*D22-$H$23*D22^2-LN(1+$H$24*EXP(1-D22^3)) -> 1.5867043 | G22: Parameter a (utility) | H22: 4 | M22: 0.00069210429 | N22: 0.041928486 | O22: 0.018488291 | P22: 0.87310409 | Q22: 0 | R22: 0.10840762 | S22: =(M22-$H$13)/N22 -> 0.014152017
A23: ='Stocks Returns'!A19 -> 42321 | B23: =SUMPRODUCT('Stocks Returns'!B19:E19,$H$10:$K$10) -> -0.0035613195 | C23: =-B23 -> 0.0035613195 | D23: =1+$H$13+$H$19*(B23-$H$13) -> 0.9976099 | E23: =$H$22*D23-$H$23*D23^2-LN(1+$H$24*EXP(1-D23^3)) -> 1.5921334 | G23: Parameter b (utility) | H23: 2 | M23: 0.00069532306 | N23: 0.041969147 | O23: 0.014453213 | P23: 0.87892196 | Q23: 0 | R23: 0.10662482 | S23: =(M23-$H$13)/N23 -> 0.014215
A24: ='Stocks Returns'!A20 -> 42324 | B24: =SUMPRODUCT('Stocks Returns'!B20:E20,$H$10:$K$10) -> 0.0099919828 | C24: =-B24 -> -0.0099919828 | D24: =1+$H$13+$H$19*(B24-$H$13) -> 1.0068261 | E24: =$H$22*D24-$H$23*D24^2-LN(1+$H$24*EXP(1-D24^3)) -> 1.6012674 | G24: Parameter c (utility) | H24: 0.5 | M24: 0.00069854184 | N24: 0.041822444 | O24: 0.010418136 | P24: 0.88473984 | Q24: 0 | R24: 0.10484202 | S24: =(M24-$H$13)/N24 -> 0.014341826
A25: ='Stocks Returns'!A21 -> 42325 | B25: =SUMPRODUCT('Stocks Returns'!B21:E21,$H$10:$K$10) -> -0.0006297326 | C25: =-B25 -> 0.0006297326 | D25: =1+$H$13+$H$19*(B25-$H$13) -> 0.99960338 | E25: =$H$22*D25-$H$23*D25^2-LN(1+$H$24*EXP(1-D25^3)) -> 1.594138 | G25: u(x) = a*x - b*x^2 - LN(1 + c*e^(1-x^3)) | M25: 0.00070176061 | N25: 0.041864759 | O25: 0.0067115404 | P25: 0.89135828 | Q25: 0 | R25: 0.10193018 | S25: =(M25-$H$13)/N25 -> 0.014404214
A26: ='Stocks Returns'!A22 -> 42326 | B26: =SUMPRODUCT('Stocks Returns'!B22:E22,$H$10:$K$10) -> 0.020556343 | C26: =-B26 -> -0.020556343 | D26: =1+$H$13+$H$19*(B26-$H$13) -> 1.0140099 | E26: =$H$22*D26-$H$23*D26^2-LN(1+$H$24*EXP(1-D26^3)) -> 1.6081486 | M26: 0.00070497939 | N26: 0.041910385 | O26: 0.0032560712 | P26: 0.89858875 | Q26: 0 | R26: 0.098155181 | S26: =(M26-$H$13)/N26 -> 0.014465335
A27: ='Stocks Returns'!A23 -> 42327 | B27: =SUMPRODUCT('Stocks Returns'!B23:E23,$H$10:$K$10) -> -0.0032778145 | C27: =-B27 -> 0.0032778145 | D27: =1+$H$13+$H$19*(B27-$H$13) -> 0.99780268 | E27: =$H$22*D27-$H$23*D27^2-LN(1+$H$24*EXP(1-D27^3)) -> 1.5923279 | G27: E[u(X)] (Solver objective function on w* and lambda) | H27: =AVERAGE($E$6:$E$2524) -> 1.5948477 | M27: 0.00070819816 | N27: 0.04196213 | O27: 0.00034988102 | P27: 0.90585841 | Q27: 0.0012409428 | R27: 0.092550767 | S27: =(M27-$H$13)/N27 -> 0.014524203
A28: ='Stocks Returns'!A24 -> 42328 | B28: =SUMPRODUCT('Stocks Returns'!B24:E24,$H$10:$K$10) -> 0.00074309248 | C28: =-B28 -> -0.00074309248 | D28: =1+$H$13+$H$19*(B28-$H$13) -> 1.0005369 | E28: =$H$22*D28-$H$23*D28^2-LN(1+$H$24*EXP(1-D28^3)) -> 1.5950712 | G28: E[X] | H28: =AVERAGE($D$6:$D$2524) -> 1.0005263 | M28: 0.00071141693 | N28: 0.042209894 | O28: 0 | P28: 0.89523436 | Q28: 0.025518972 | R28: 0.079246664 | S28: =(M28-$H$13)/N28 -> 0.014515205
A29: ='Stocks Returns'!A25 -> 42331 | B29: =SUMPRODUCT('Stocks Returns'!B25:E25,$H$10:$K$10) -> -0.0021525285 | C29: =-B29 -> 0.0021525285 | D29: =1+$H$13+$H$19*(B29-$H$13) -> 0.99856787 | E29: =$H$22*D29-$H$23*D29^2-LN(1+$H$24*EXP(1-D29^3)) -> 1.5930987 | G29: Certainty equivalent CE (goal seek on H30 = 0) | H29: 1.0003131 | M29: 0.00071463571 | N29: 0.042114833 | O29: 0 | P29: 0.8842453 | Q29: 0.050959877 | R29: 0.064794823 | S29: =(M29-$H$13)/N29 -> 0.014624398
A30: ='Stocks Returns'!A26 -> 42332 | B30: =SUMPRODUCT('Stocks Returns'!B26:E26,$H$10:$K$10) -> -0.0025143384 | C30: =-B30 -> 0.0025143384 | D30: =1+$H$13+$H$19*(B30-$H$13) -> 0.99832184 | E30: =$H$22*D30-$H$23*D30^2-LN(1+$H$24*EXP(1-D30^3)) -> 1.5928511 | G30: Check: u(CE) - E[u(X)] (should be 0) | H30: =H22*H29-H23*H29^2-LN(1+H24*EXP(1-H29^3))-H27 -> 1.7164048e-13 | M30: 0.00071785448 | N30: 0.042213683 | O30: 0 | P30: 0.89666066 | Q30: 0.054050673 | R30: 0.049288666 | S30: =(M30-$H$13)/N30 -> 0.014666402
A31: ='Stocks Returns'!A27 -> 42333 | B31: =SUMPRODUCT('Stocks Returns'!B27:E27,$H$10:$K$10) -> -0.0028395672 | C31: =-B31 -> 0.0028395672 | D31: =1+$H$13+$H$19*(B31-$H$13) -> 0.99810069 | E31: =$H$22*D31-$H$23*D31^2-LN(1+$H$24*EXP(1-D31^3)) -> 1.5926284 | G31: Daily risk premium = E[X] - CE | H31: =H28-H29 -> 0.00021324739 | M31: 0.00072107326 | N31: 0.042317428 | O31: 0 | P31: 0.90185762 | Q31: 0.064034701 | R31: 0.034107681 | S31: =(M31-$H$13)/N31 -> 0.014706509
A32: ='Stocks Returns'!A28 -> 42334 | B32: =SUMPRODUCT('Stocks Returns'!B28:E28,$H$10:$K$10) -> 0 | C32: =-B32 -> 0 | D32: =1+$H$13+$H$19*(B32-$H$13) -> 1.0000316 | E32: =$H$22*D32-$H$23*D32^2-LN(1+$H$24*EXP(1-D32^3)) -> 1.5945665 | G32: Annualized risk premium (x252) | H32: =H31*252 -> 0.053738342 | M32: 0.00072429203 | N32: 0.042606235 | O32: 0 | P32: 0.9121881 | Q32: 0.069116461 | R32: 0.018695443 | S32: =(M32-$H$13)/N32 -> 0.014682367
A33: ='Stocks Returns'!A29 -> 42335 | B33: =SUMPRODUCT('Stocks Returns'!B29:E29,$H$10:$K$10) -> 0.0040571008 | C33: =-B33 -> -0.0040571008 | D33: =1+$H$13+$H$19*(B33-$H$13) -> 1.0027904 | E33: =$H$22*D33-$H$23*D33^2-LN(1+$H$24*EXP(1-D33^3)) -> 1.5973097 | G33: Absolute risk aversion ARA(CE) = -u''/u' | H33: =-( (H22*(H29+0.00001)-H23*(H29+0.00001)^2-LN(1+H24*EXP(1-(H29+0.00001)^3))) -2*(H22*H29-H23*H29^2-LN(1+H24*EXP(1-H29^3))) +(H22*(H29-0.00001)-H23*(H29-0.00001)^2-LN(1+H24*EXP(1-(H29-0.00001)^3))) )/0.00001^2 / ( ((H22*(H29+0.00001)-H23*(H29+0.00001)^2-LN(1+H24*EXP(1-(H29+0.00001)^3))) -(H22*(H29-0.00001)-H23*(H29-0.00001)^2-LN(1+H24*EXP(1-(H29-0.00001)^3))))/(2*0.00001) ) -> 4.0075271 | M33: 0.0007275108 | N33: 0.042558861 | O33: 0 | P33: 0.92027206 | Q33: 0.076343536 | R33: 0.0033844055 | S33: =(M33-$H$13)/N33 -> 0.014774342
A34: ='Stocks Returns'!A30 -> 42338 | B34: =SUMPRODUCT('Stocks Returns'!B30:E30,$H$10:$K$10) -> -0.0085863958 | C34: =-B34 -> 0.0085863958 | D34: =1+$H$13+$H$19*(B34-$H$13) -> 0.99419285 | E34: =$H$22*D34-$H$23*D34^2-LN(1+$H$24*EXP(1-D34^3)) -> 1.5886606 | M34: 0.00073072958 | N34: 0.044761694 | O34: 0 | P34: 0.66360087 | Q34: 0.33639913 | R34: 0 | S34: =(M34-$H$13)/N34 -> 0.014119169
A35: ='Stocks Returns'!A31 -> 42339 | B35: =SUMPRODUCT('Stocks Returns'!B31:E31,$H$10:$K$10) -> 0.010849916 | C35: =-B35 -> -0.010849916 | D35: =1+$H$13+$H$19*(B35-$H$13) -> 1.0074095 | E35: =$H$22*D35-$H$23*D35^2-LN(1+$H$24*EXP(1-D35^3)) -> 1.6018341 | M35: 0.00073394835 | N35: 0.053876991 | O35: 0 | P35: 0.33180043 | Q35: 0.66819957 | R35: 0 | S35: =(M35-$H$13)/N35 -> 0.01179013
A36: ='Stocks Returns'!A32 -> 42340 | B36: =SUMPRODUCT('Stocks Returns'!B32:E32,$H$10:$K$10) -> -0.013028082 | C36: =-B36 -> 0.013028082 | D36: =1+$H$13+$H$19*(B36-$H$13) -> 0.9911725 | E36: =$H$22*D36-$H$23*D36^2-LN(1+$H$24*EXP(1-D36^3)) -> 1.5855525 | M36: 0.00073716713 | N36: 0.06747821 | O36: 0 | P36: 0 | Q36: 1 | R36: 0 | S36: =(M36-$H$13)/N36 -> 0.0094613577
A37: ='Stocks Returns'!A33 -> 42341 | B37: =SUMPRODUCT('Stocks Returns'!B33:E33,$H$10:$K$10) -> -0.0091691963 | C37: =-B37 -> 0.0091691963 | D37: =1+$H$13+$H$19*(B37-$H$13) -> 0.99379654 | E37: =$H$22*D37-$H$23*D37^2-LN(1+$H$24*EXP(1-D37^3)) -> 1.5882548
A38: ='Stocks Returns'!A34 -> 42342 | B38: =SUMPRODUCT('Stocks Returns'!B34:E34,$H$10:$K$10) -> 0.026320399 | C38: =-B38 -> -0.026320399 | D38: =1+$H$13+$H$19*(B38-$H$13) -> 1.0179295 | E38: =$H$22*D38-$H$23*D38^2-LN(1+$H$24*EXP(1-D38^3)) -> 1.6118137
A39: ='Stocks Returns'!A35 -> 42345 | B39: =SUMPRODUCT('Stocks Returns'!B35:E35,$H$10:$K$10) -> -0.01098673 | C39: =-B39 -> 0.01098673 | D39: =1+$H$13+$H$19*(B39-$H$13) -> 0.99256062 | E39: =$H$22*D39-$H$23*D39^2-LN(1+$H$24*EXP(1-D39^3)) -> 1.5869854
A40: ='Stocks Returns'!A36 -> 42346 | B40: =SUMPRODUCT('Stocks Returns'!B36:E36,$H$10:$K$10) -> -0.0063692038 | C40: =-B40 -> 0.0063692038 | D40: =1+$H$13+$H$19*(B40-$H$13) -> 0.99570054 | E40: =$H$22*D40-$H$23*D40^2-LN(1+$H$24*EXP(1-D40^3)) -> 1.5901986
A41: ='Stocks Returns'!A37 -> 42347 | B41: =SUMPRODUCT('Stocks Returns'!B37:E37,$H$10:$K$10) -> -0.014994612 | C41: =-B41 -> 0.014994612 | D41: =1+$H$13+$H$19*(B41-$H$13) -> 0.98983526 | E41: =$H$22*D41-$H$23*D41^2-LN(1+$H$24*EXP(1-D41^3)) -> 1.5841649
A42: ='Stocks Returns'!A38 -> 42348 | B42: =SUMPRODUCT('Stocks Returns'!B38:E38,$H$10:$K$10) -> 0.0026199361 | C42: =-B42 -> -0.0026199361 | D42: =1+$H$13+$H$19*(B42-$H$13) -> 1.0018132 | E42: =$H$22*D42-$H$23*D42^2-LN(1+$H$24*EXP(1-D42^3)) -> 1.5963415
A43: ='Stocks Returns'!A39 -> 42349 | B43: =SUMPRODUCT('Stocks Returns'!B39:E39,$H$10:$K$10) -> -0.024948459 | C43: =-B43 -> 0.024948459 | D43: =1+$H$13+$H$19*(B43-$H$13) -> 0.98306664 | E43: =$H$22*D43-$H$23*D43^2-LN(1+$H$24*EXP(1-D43^3)) -> 1.5770345
A44: ='Stocks Returns'!A40 -> 42352 | B44: =SUMPRODUCT('Stocks Returns'!B40:E40,$H$10:$K$10) -> 0.0092365592 | C44: =-B44 -> -0.0092365592 | D44: =1+$H$13+$H$19*(B44-$H$13) -> 1.0063125 | E44: =$H$22*D44-$H$23*D44^2-LN(1+$H$24*EXP(1-D44^3)) -> 1.6007673
A45: ='Stocks Returns'!A41 -> 42353 | B45: =SUMPRODUCT('Stocks Returns'!B41:E41,$H$10:$K$10) -> 0.023519604 | C45: =-B45 -> -0.023519604 | D45: =1+$H$13+$H$19*(B45-$H$13) -> 1.0160249 | E45: =$H$22*D45-$H$23*D45^2-LN(1+$H$24*EXP(1-D45^3)) -> 1.6100407
A46: ='Stocks Returns'!A42 -> 42354 | B46: =SUMPRODUCT('Stocks Returns'!B42:E42,$H$10:$K$10) -> 0.016157003 | C46: =-B46 -> -0.016157003 | D46: =1+$H$13+$H$19*(B46-$H$13) -> 1.0110184 | E46: =$H$22*D46-$H$23*D46^2-LN(1+$H$24*EXP(1-D46^3)) -> 1.6053087
A47: ='Stocks Returns'!A43 -> 42355 | B47: =SUMPRODUCT('Stocks Returns'!B43:E43,$H$10:$K$10) -> -0.014710294 | C47: =-B47 -> 0.014710294 | D47: =1+$H$13+$H$19*(B47-$H$13) -> 0.99002859 | E47: =$H$22*D47-$H$23*D47^2-LN(1+$H$24*EXP(1-D47^3)) -> 1.5843659
A48: ='Stocks Returns'!A44 -> 42356 | B48: =SUMPRODUCT('Stocks Returns'!B44:E44,$H$10:$K$10) -> -0.028388932 | C48: =-B48 -> 0.028388932 | D48: =1+$H$13+$H$19*(B48-$H$13) -> 0.98072712 | E48: =$H$22*D48-$H$23*D48^2-LN(1+$H$24*EXP(1-D48^3)) -> 1.5745286
... A2524: ='Stocks Returns'!A2520 -> 45824 | B2524: =SUMPRODUCT('Stocks Returns'!B2520:E2520,$H$10:$K$10) -> 0.0096478761 | C2524: =-B2524 -> -0.0096478761 | D2524: =1+$H$13+$H$19*(B2524-$H$13) -> 1.0065921 | E2524: =$H$22*D2524-$H$23*D2524^2-LN(1+$H$24*EXP(1-D2524^3)) -> 1.6010397

Sheet 2_CVaR_t3
A2: POINT 2 - Mean-CVaR 3% frontier and investor's optimal portfolio - rebalancing 3 (15/07/2025)
G3: Valuation date | H3: 45853 | M3: MEAN-CVaR 3% EFFICIENT FRONTIER (no short selling)
G4: Sample rows in the Stocks Returns sheet | H4: 2 : 2541
A5: Date | B5: R risky ptf | C5: Loss L = -R | D5: X = final wealth | E5: u(X) | G5: Number of observations T | H5: =COUNT($B$6:$B$2545) -> 2540 | M5: Average return | N5: CVaR 3% | O5: w1 | P5: w2 | Q5: w3 | R5: w4 | S5: STARR
A6: ='Stocks Returns'!A2 -> 42298 | B6: =SUMPRODUCT('Stocks Returns'!B2:E2,$H$10:$K$10) -> -0.010013056 | C6: =-B6 -> 0.010013056 | D6: =1+$H$13+$H$19*(B6-$H$13) -> 0.99336492 | E6: =$H$22*D6-$H$23*D6^2-LN(1+$H$24*EXP(1-D6^3)) -> 1.5878122 | G6: Tail level alpha | H6: 0.03 | M6: 0.00062458208 | N6: 0.041555754 | O6: 0.089992058 | P6: 0.76267839 | Q6: 0 | R6: 0.14732955 | S6: =(M6-$H$13)/N6 -> 0.012607762
A7: ='Stocks Returns'!A3 -> 42299 | B7: =SUMPRODUCT('Stocks Returns'!B3:E3,$H$10:$K$10) -> 0.015744271 | C7: =-B7 -> -0.015744271 | D7: =1+$H$13+$H$19*(B7-$H$13) -> 1.0105193 | E7: =$H$22*D7-$H$23*D7^2-LN(1+$H$24*EXP(1-D7^3)) -> 1.6048313 | G7: k = ROUNDUP(T*alpha) - tail observations | H7: =ROUNDUP(H5*H6,0) -> 77 | M7: 0.00062907736 | N7: 0.041557403 | O7: 0.084908967 | P7: 0.77365486 | Q7: 0 | R7: 0.14143617 | S7: =(M7-$H$13)/N7 -> 0.012715432
A8: ='Stocks Returns'!A4 -> 42300 | B8: =SUMPRODUCT('Stocks Returns'!B4:E4,$H$10:$K$10) -> 0.0080665168 | C8: =-B8 -> -0.0080665168 | D8: =1+$H$13+$H$19*(B8-$H$13) -> 1.0054059 | E8: =$H$22*D8-$H$23*D8^2-LN(1+$H$24*EXP(1-D8^3)) -> 1.5998822 | M8: 0.00063357265 | N8: 0.041562506 | O8: 0.080995291 | P8: 0.7871625 | Q8: 0 | R8: 0.13184221 | S8: =(M8-$H$13)/N8 -> 0.012822028
A9: ='Stocks Returns'!A5 -> 42303 | B9: =SUMPRODUCT('Stocks Returns'!B5:E5,$H$10:$K$10) -> 0.01095333 | C9: =-B9 -> -0.01095333 | D9: =1+$H$13+$H$19*(B9-$H$13) -> 1.0073285 | E9: =$H$22*D9-$H$23*D9^2-LN(1+$H$24*EXP(1-D9^3)) -> 1.6017555 | G9: Risky portfolio weights w* (Solver variable cells) | H9: WARNER BROS DISCOVERY | I9: VISA 'A' | J9: MICROCHIP TECH. | K9: CONOCOPHILLIPS | M9: 0.00063806793 | N9: 0.041580129 | O9: 0.073590648 | P9: 0.793114 | Q9: 0 | R9: 0.13329535 | S9: =(M9-$H$13)/N9 -> 0.012924705
A10: ='Stocks Returns'!A6 -> 42304 | B10: =SUMPRODUCT('Stocks Returns'!B6:E6,$H$10:$K$10) -> -0.0088973986 | C10: =-B10 -> 0.0088973986 | D10: =1+$H$13+$H$19*(B10-$H$13) -> 0.99410795 | E10: =$H$22*D10-$H$23*D10^2-LN(1+$H$24*EXP(1-D10^3)) -> 1.5885737 | H10: 0 | I10: 0.87042953 | J10: 0.12957047 | K10: 0 | M10: 0.00064256322 | N10: 0.041607268 | O10: 0.065559968 | P10: 0.79771045 | Q10: 0 | R10: 0.13672958 | S10: =(M10-$H$13)/N10 -> 0.013024315
A11: ='Stocks Returns'!A7 -> 42305 | B11: =SUMPRODUCT('Stocks Returns'!B7:E7,$H$10:$K$10) -> 0.016861505 | C11: =-B11 -> -0.016861505 | D11: =1+$H$13+$H$19*(B11-$H$13) -> 1.0112634 | E11: =$H$22*D11-$H$23*D11^2-LN(1+$H$24*EXP(1-D11^3)) -> 1.6055426 | G11: Sum of weights (constraint = 1, no short selling) | H11: =SUM(H10:K10) -> 1 | M11: 0.0006470585 | N11: 0.041633612 | O11: 0.059171861 | P11: 0.80586223 | Q11: 0 | R11: 0.13496591 | S11: =(M11-$H$13)/N11 -> 0.013124046
A12: ='Stocks Returns'!A8 -> 42306 | B12: =SUMPRODUCT('Stocks Returns'!B8:E8,$H$10:$K$10) -> -0.0070949108 | C12: =-B12 -> 0.0070949108 | D12: =1+$H$13+$H$19*(B12-$H$13) -> 0.99530841 | E12: =$H$22*D12-$H$23*D12^2-LN(1+$H$24*EXP(1-D12^3)) -> 1.5897994 | G12: Annual IRR of the bond portfolio | H12: ='1_Bonds'!E77 -> 0.025688709 | M12: 0.00065155379 | N12: 0.041660856 | O12: 0.053278121 | P12: 0.81508405 | Q12: 0 | R12: 0.13163783 | S12: =(M12-$H$13)/N12 -> 0.013223366
A13: ='Stocks Returns'!A9 -> 42307 | B13: =SUMPRODUCT('Stocks Returns'!B9:E9,$H$10:$K$10) -> -0.0078500636 | C13: =-B13 -> 0.0078500636 | D13: =1+$H$13+$H$19*(B13-$H$13) -> 0.99480548 | E13: =$H$22*D13-$H$23*D13^2-LN(1+$H$24*EXP(1-D13^3)) -> 1.5892866 | G13: Daily risk-free rate rf | H13: =(1+H12)^(1/252)-1 -> 0.00010065704 | M13: 0.00065604907 | N13: 0.041697972 | O13: 0.047253415 | P13: 0.82402241 | Q13: 0 | R13: 0.12872418 | S13: =(M13-$H$13)/N13 -> 0.013319401
A14: ='Stocks Returns'!A10 -> 42310 | B14: =SUMPRODUCT('Stocks Returns'!B10:E10,$H$10:$K$10) -> -0.024868746 | C14: =-B14 -> 0.024868746 | D14: =1+$H$13+$H$19*(B14-$H$13) -> 0.98347103 | E14: =$H$22*D14-$H$23*D14^2-LN(1+$H$24*EXP(1-D14^3)) -> 1.5774655 | G14: Average daily return of the risky portfolio | H14: =AVERAGE($B$6:$B$2545) -> 0.00071898306 | M14: 0.00066054436 | N14: 0.041553377 | O14: 0.039714343 | P14: 0.82968293 | Q14: 0 | R14: 0.13060272 | S14: =(M14-$H$13)/N14 -> 0.01347393
A15: ='Stocks Returns'!A11 -> 42311 | B15: =SUMPRODUCT('Stocks Returns'!B11:E11,$H$10:$K$10) -> 0.030826862 | C15: =-B15 -> -0.030826862 | D15: =1+$H$13+$H$19*(B15-$H$13) -> 1.0205643 | E15: =$H$22*D15-$H$23*D15^2-LN(1+$H$24*EXP(1-D15^3)) -> 1.6142418 | G15: VaR 3% daily (loss, positive sign) | H15: =-SMALL($B$6:$B$2545,H7) -> 0.029377076 | M15: 0.00066503964 | N15: 0.041787444 | O15: 0.037170538 | P15: 0.84615564 | Q15: 0 | R15: 0.11667382 | S15: =(M15-$H$13)/N15 -> 0.013506033
A16: ='Stocks Returns'!A12 -> 42312 | B16: =SUMPRODUCT('Stocks Returns'!B12:E12,$H$10:$K$10) -> 0.0054793428 | C16: =-B16 -> -0.0054793428 | D16: =1+$H$13+$H$19*(B16-$H$13) -> 1.0036829 | E16: =$H$22*D16-$H$23*D16^2-LN(1+$H$24*EXP(1-D16^3)) -> 1.5981906 | G16: CVaR 3% daily = average of the k worst returns (loss, positive sign) | H16: =-(SUMIF($B$6:$B$2545,"<"&-H15)+(-H15)*(H7-COUNTIF($B$6:$B$2545,"<"&-H15)))/H7 -> 0.042857275 | M16: 0.00066953493 | N16: 0.041657209 | O16: 0.034100412 | P16: 0.85076351 | Q16: 0.008739537 | R16: 0.10639654 | S16: =(M16-$H$13)/N16 -> 0.013656169
A17: ='Stocks Returns'!A13 -> 42313 | B17: =SUMPRODUCT('Stocks Returns'!B13:E13,$H$10:$K$10) -> 0.0072532254 | C17: =-B17 -> -0.0072532254 | D17: =1+$H$13+$H$19*(B17-$H$13) -> 1.0048643 | E17: =$H$22*D17-$H$23*D17^2-LN(1+$H$24*EXP(1-D17^3)) -> 1.5993517 | G17: STARR = (mu - rf) / CVaR 3% | H17: =(H14-H13)/H16 -> 0.014427562 | M17: 0.00067403021 | N17: 0.041703807 | O17: 0.028718659 | P17: 0.84915931 | Q17: 0.018463855 | R17: 0.10365817 | S17: =(M17-$H$13)/N17 -> 0.013748701
A18: ='Stocks Returns'!A14 -> 42314 | B18: =SUMPRODUCT('Stocks Returns'!B14:E14,$H$10:$K$10) -> -0.0057630629 | C18: =-B18 -> 0.0057630629 | D18: =1+$H$13+$H$19*(B18-$H$13) -> 0.99619542 | E18: =$H$22*D18-$H$23*D18^2-LN(1+$H$24*EXP(1-D18^3)) -> 1.5907014 | M18: 0.0006785255 | N18: 0.041933111 | O18: 0.023336906 | P18: 0.84755512 | Q18: 0.028188174 | R18: 0.1009198 | S18: =(M18-$H$13)/N18 -> 0.01378072
A19: ='Stocks Returns'!A15 -> 42317 | B19: =SUMPRODUCT('Stocks Returns'!B15:E15,$H$10:$K$10) -> -0.0079424567 | C19: =-B19 -> 0.0079424567 | D19: =1+$H$13+$H$19*(B19-$H$13) -> 0.99474394 | E19: =$H$22*D19-$H$23*D19^2-LN(1+$H$24*EXP(1-D19^3)) -> 1.5892238 | G19: lambda = share invested in the risky portfolio | H19: 0.666 | M19: 0.00068302078 | N19: 0.041988567 | O19: 0.016941673 | P19: 0.84670102 | Q19: 0.035513837 | R19: 0.10084347 | S19: =(M19-$H$13)/N19 -> 0.013869579
A20: ='Stocks Returns'!A16 -> 42318 | B20: =SUMPRODUCT('Stocks Returns'!B16:E16,$H$10:$K$10) -> 0.014286294 | C20: =-B20 -> -0.014286294 | D20: =1+$H$13+$H$19*(B20-$H$13) -> 1.0095483 | E20: =$H$22*D20-$H$23*D20^2-LN(1+$H$24*EXP(1-D20^3)) -> 1.6038997 | G20: 1 - lambda = share in the risk-free asset | H20: =1-H19 -> 0.334 | M20: 0.00068751607 | N20: 0.042048114 | O20: 0.012491496 | P20: 0.84727784 | Q20: 0.045104001 | R20: 0.095126659 | S20: =(M20-$H$13)/N20 -> 0.013956845
A21: ='Stocks Returns'!A17 -> 42319 | B21: =SUMPRODUCT('Stocks Returns'!B17:E17,$H$10:$K$10) -> -0.0034503142 | C21: =-B21 -> 0.0034503142 | D21: =1+$H$13+$H$19*(B21-$H$13) -> 0.99773571 | E21: =$H$22*D21-$H$23*D21^2-LN(1+$H$24*EXP(1-D21^3)) -> 1.5922604 | M21: 0.00069201135 | N21: 0.041937539 | O21: 0.0087465524 | P21: 0.85237424 | Q21: 0.05225531 | R21: 0.086623903 | S21: =(M21-$H$13)/N21 -> 0.014100835
A22: ='Stocks Returns'!A18 -> 42320 | B22: =SUMPRODUCT('Stocks Returns'!B18:E18,$H$10:$K$10) -> -0.011572156 | C22: =-B22 -> 0.011572156 | D22: =1+$H$13+$H$19*(B22-$H$13) -> 0.99232656 | E22: =$H$22*D22-$H$23*D22^2-LN(1+$H$24*EXP(1-D22^3)) -> 1.5867443 | G22: Parameter a (utility) | H22: 4 | M22: 0.00069650664 | N22: 0.042014017 | O22: 0.0049950754 | P22: 0.85749655 | Q22: 0.059373969 | R22: 0.078134402 | S22: =(M22-$H$13)/N22 -> 0.014182162
A23: ='Stocks Returns'!A19 -> 42321 | B23: =SUMPRODUCT('Stocks Returns'!B19:E19,$H$10:$K$10) -> -0.0042628553 | C23: =-B23 -> 0.0042628553 | D23: =1+$H$13+$H$19*(B23-$H$13) -> 0.99719456 | E23: =$H$22*D23-$H$23*D23^2-LN(1+$H$24*EXP(1-D23^3)) -> 1.5917137 | G23: Parameter b (utility) | H23: 2 | M23: 0.00070100192 | N23: 0.04227453 | O23: 0 | P23: 0.86215696 | Q23: 0.064675692 | R23: 0.073167344 | S23: =(M23-$H$13)/N23 -> 0.014201101
A24: ='Stocks Returns'!A20 -> 42324 | B24: =SUMPRODUCT('Stocks Returns'!B20:E20,$H$10:$K$10) -> 0.0096835535 | C24: =-B24 -> -0.0096835535 | D24: =1+$H$13+$H$19*(B24-$H$13) -> 1.0064829 | E24: =$H$22*D24-$H$23*D24^2-LN(1+$H$24*EXP(1-D24^3)) -> 1.6009333 | G24: Parameter c (utility) | H24: 0.5 | M24: 0.00070549721 | N24: 0.042391643 | O24: 0 | P24: 0.86867269 | Q24: 0.077275377 | R24: 0.054051937 | S24: =(M24-$H$13)/N24 -> 0.01426791
A25: ='Stocks Returns'!A21 -> 42325 | B25: =SUMPRODUCT('Stocks Returns'!B21:E21,$H$10:$K$10) -> -0.00040566832 | C25: =-B25 -> 0.00040566832 | D25: =1+$H$13+$H$19*(B25-$H$13) -> 0.99976344 | E25: =$H$22*D25-$H$23*D25^2-LN(1+$H$24*EXP(1-D25^3)) -> 1.5942982 | G25: u(x) = a*x - b*x^2 - LN(1 + c*e^(1-x^3)) | M25: 0.00070999249 | N25: 0.042522672 | O25: 0 | P25: 0.86997974 | Q25: 0.094119222 | R25: 0.035901033 | S25: =(M25-$H$13)/N25 -> 0.01432966
A26: ='Stocks Returns'!A22 -> 42326 | B26: =SUMPRODUCT('Stocks Returns'!B22:E22,$H$10:$K$10) -> 0.020528899 | C26: =-B26 -> -0.020528899 | D26: =1+$H$13+$H$19*(B26-$H$13) -> 1.0137059 | E26: =$H$22*D26-$H$23*D26^2-LN(1+$H$24*EXP(1-D26^3)) -> 1.6078616 | M26: 0.00071448778 | N26: 0.042675363 | O26: 0 | P26: 0.88247925 | Q26: 0.10184315 | R26: 0.015677591 | S26: =(M26-$H$13)/N26 -> 0.014383726
A27: ='Stocks Returns'!A23 -> 42327 | B27: =SUMPRODUCT('Stocks Returns'!B23:E23,$H$10:$K$10) -> -0.0028020326 | C27: =-B27 -> 0.0028020326 | D27: =1+$H$13+$H$19*(B27-$H$13) -> 0.99816747 | E27: =$H$22*D27-$H$23*D27^2-LN(1+$H$24*EXP(1-D27^3)) -> 1.5926956 | G27: E[u(X)] (Solver objective function on w* and lambda) | H27: =AVERAGE($E$6:$E$2545) -> 1.5948414 | M27: 0.00071898306 | N27: 0.042857275 | O27: 0 | P27: 0.87042953 | Q27: 0.12957047 | R27: 0 | S27: =(M27-$H$13)/N27 -> 0.014427562
A28: ='Stocks Returns'!A24 -> 42328 | B28: =SUMPRODUCT('Stocks Returns'!B24:E24,$H$10:$K$10) -> 0.00098366042 | C28: =-B28 -> -0.00098366042 | D28: =1+$H$13+$H$19*(B28-$H$13) -> 1.0006887 | E28: =$H$22*D28-$H$23*D28^2-LN(1+$H$24*EXP(1-D28^3)) -> 1.5952227 | G28: E[X] | H28: =AVERAGE($D$6:$D$2545) -> 1.0005125 | M28: 0.00072347835 | N28: 0.043229024 | O28: 0 | P28: 0.77371514 | Q28: 0.22628486 | R28: 0 | S28: =(M28-$H$13)/N28 -> 0.01440748
A29: ='Stocks Returns'!A25 -> 42331 | B29: =SUMPRODUCT('Stocks Returns'!B25:E25,$H$10:$K$10) -> -0.0030014395 | C29: =-B29 -> 0.0030014395 | D29: =1+$H$13+$H$19*(B29-$H$13) -> 0.99803466 | E29: =$H$22*D29-$H$23*D29^2-LN(1+$H$24*EXP(1-D29^3)) -> 1.5925618 | G29: Certainty equivalent CE (goal seek on H30 = 0) | H29: 1.0003067 | M29: 0.00072797363 | N29: 0.04434194 | O29: 0 | P29: 0.67700074 | Q29: 0.32299926 | R29: 0 | S29: =(M29-$H$13)/N29 -> 0.014147252
A30: ='Stocks Returns'!A26 -> 42332 | B30: =SUMPRODUCT('Stocks Returns'!B26:E26,$H$10:$K$10) -> -0.0017252335 | C30: =-B30 -> 0.0017252335 | D30: =1+$H$13+$H$19*(B30-$H$13) -> 0.99888461 | E30: =$H$22*D30-$H$23*D30^2-LN(1+$H$24*EXP(1-D30^3)) -> 1.593417 | G30: Check: u(CE) - E[u(X)] (should be 0) | H30: =H22*H29-H23*H29^2-LN(1+H24*EXP(1-H29^3))-H27 -> 1.6942003e-13 | M30: 0.00073246891 | N30: 0.046360125 | O30: 0 | P30: 0.58028635 | Q30: 0.41971365 | R30: 0 | S30: =(M30-$H$13)/N30 -> 0.013628347
A31: ='Stocks Returns'!A27 -> 42333 | B31: =SUMPRODUCT('Stocks Returns'!B27:E27,$H$10:$K$10) -> -0.0027285427 | C31: =-B31 -> 0.0027285427 | D31: =1+$H$13+$H$19*(B31-$H$13) -> 0.99821641 | E31: =$H$22*D31-$H$23*D31^2-LN(1+$H$24*EXP(1-D31^3)) -> 1.5927449 | G31: Daily risk premium = E[X] - CE | H31: =H28-H29 -> 0.00020579541 | M31: 0.0007369642 | N31: 0.048826518 | O31: 0 | P31: 0.48357196 | Q31: 0.51642804 | R31: 0 | S31: =(M31-$H$13)/N31 -> 0.013031999
A32: ='Stocks Returns'!A28 -> 42334 | B32: =SUMPRODUCT('Stocks Returns'!B28:E28,$H$10:$K$10) -> 0 | C32: =-B32 -> 0 | D32: =1+$H$13+$H$19*(B32-$H$13) -> 1.0000336 | E32: =$H$22*D32-$H$23*D32^2-LN(1+$H$24*EXP(1-D32^3)) -> 1.5945685 | G32: Annualized risk premium (x252) | H32: =H31*252 -> 0.051860443 | M32: 0.00074145948 | N32: 0.051807602 | O32: 0 | P32: 0.38685757 | Q32: 0.61314243 | R32: 0 | S32: =(M32-$H$13)/N32 -> 0.012368888
A33: ='Stocks Returns'!A29 -> 42335 | B33: =SUMPRODUCT('Stocks Returns'!B29:E29,$H$10:$K$10) -> 0.0045472978 | C33: =-B33 -> -0.0045472978 | D33: =1+$H$13+$H$19*(B33-$H$13) -> 1.0030621 | E33: =$H$22*D33-$H$23*D33^2-LN(1+$H$24*EXP(1-D33^3)) -> 1.5975782 | G33: Absolute risk aversion ARA(CE) = -u''/u' | H33: =-( (H22*(H29+0.00001)-H23*(H29+0.00001)^2-LN(1+H24*EXP(1-(H29+0.00001)^3))) -2*(H22*H29-H23*H29^2-LN(1+H24*EXP(1-H29^3))) +(H22*(H29-0.00001)-H23*(H29-0.00001)^2-LN(1+H24*EXP(1-(H29-0.00001)^3))) )/0.00001^2 / ( ((H22*(H29+0.00001)-H23*(H29+0.00001)^2-LN(1+H24*EXP(1-(H29+0.00001)^3))) -(H22*(H29-0.00001)-H23*(H29-0.00001)^2-LN(1+H24*EXP(1-(H29-0.00001)^3))))/(2*0.00001) ) -> 4.0073734 | M33: 0.00074595477 | N33: 0.055148203 | O33: 0 | P33: 0.29014318 | Q33: 0.70985682 | R33: 0 | S33: =(M33-$H$13)/N33 -> 0.011701156
A34: ='Stocks Returns'!A30 -> 42338 | B34: =SUMPRODUCT('Stocks Returns'!B30:E30,$H$10:$K$10) -> -0.0074458143 | C34: =-B34 -> 0.0074458143 | D34: =1+$H$13+$H$19*(B34-$H$13) -> 0.99507471 | E34: =$H$22*D34-$H$23*D34^2-LN(1+$H$24*EXP(1-D34^3)) -> 1.5895612 | M34: 0.00075045005 | N34: 0.058879633 | O34: 0 | P34: 0.19342878 | Q34: 0.80657122 | R34: 0 | S34: =(M34-$H$13)/N34 -> 0.011035956
A35: ='Stocks Returns'!A31 -> 42339 | B35: =SUMPRODUCT('Stocks Returns'!B31:E31,$H$10:$K$10) -> 0.010478614 | C35: =-B35 -> -0.010478614 | D35: =1+$H$13+$H$19*(B35-$H$13) -> 1.0070124 | E35: =$H$22*D35-$H$23*D35^2-LN(1+$H$24*EXP(1-D35^3)) -> 1.6014485 | M35: 0.00075494534 | N35: 0.062916333 | O35: 0 | P35: 0.096714392 | Q35: 0.90328561 | R35: 0 | S35: =(M35-$H$13)/N35 -> 0.010399339
A36: ='Stocks Returns'!A32 -> 42340 | B36: =SUMPRODUCT('Stocks Returns'!B32:E32,$H$10:$K$10) -> -0.014366538 | C36: =-B36 -> 0.014366538 | D36: =1+$H$13+$H$19*(B36-$H$13) -> 0.9904655 | E36: =$H$22*D36-$H$23*D36^2-LN(1+$H$24*EXP(1-D36^3)) -> 1.5848197 | M36: 0.00075944062 | N36: 0.067175374 | O36: 0 | P36: 0 | Q36: 1 | R36: 0 | S36: =(M36-$H$13)/N36 -> 0.0098069209
A37: ='Stocks Returns'!A33 -> 42341 | B37: =SUMPRODUCT('Stocks Returns'!B33:E33,$H$10:$K$10) -> -0.0088980781 | C37: =-B37 -> 0.0088980781 | D37: =1+$H$13+$H$19*(B37-$H$13) -> 0.9941075 | E37: =$H$22*D37-$H$23*D37^2-LN(1+$H$24*EXP(1-D37^3)) -> 1.5885732
A38: ='Stocks Returns'!A34 -> 42342 | B38: =SUMPRODUCT('Stocks Returns'!B34:E34,$H$10:$K$10) -> 0.026082238 | C38: =-B38 -> -0.026082238 | D38: =1+$H$13+$H$19*(B38-$H$13) -> 1.0174044 | E38: =$H$22*D38-$H$23*D38^2-LN(1+$H$24*EXP(1-D38^3)) -> 1.6113264
A39: ='Stocks Returns'!A35 -> 42345 | B39: =SUMPRODUCT('Stocks Returns'!B35:E35,$H$10:$K$10) -> -0.011089649 | C39: =-B39 -> 0.011089649 | D39: =1+$H$13+$H$19*(B39-$H$13) -> 0.99264791 | E39: =$H$22*D39-$H$23*D39^2-LN(1+$H$24*EXP(1-D39^3)) -> 1.5870752
A40: ='Stocks Returns'!A36 -> 42346 | B40: =SUMPRODUCT('Stocks Returns'!B36:E36,$H$10:$K$10) -> -0.0065567074 | C40: =-B40 -> 0.0065567074 | D40: =1+$H$13+$H$19*(B40-$H$13) -> 0.99566685 | E40: =$H$22*D40-$H$23*D40^2-LN(1+$H$24*EXP(1-D40^3)) -> 1.5901643
A41: ='Stocks Returns'!A37 -> 42347 | B41: =SUMPRODUCT('Stocks Returns'!B37:E37,$H$10:$K$10) -> -0.01506269 | C41: =-B41 -> 0.01506269 | D41: =1+$H$13+$H$19*(B41-$H$13) -> 0.99000187 | E41: =$H$22*D41-$H$23*D41^2-LN(1+$H$24*EXP(1-D41^3)) -> 1.5843382
A42: ='Stocks Returns'!A38 -> 42348 | B42: =SUMPRODUCT('Stocks Returns'!B38:E38,$H$10:$K$10) -> 0.0022268391 | C42: =-B42 -> -0.0022268391 | D42: =1+$H$13+$H$19*(B42-$H$13) -> 1.0015167 | E42: =$H$22*D42-$H$23*D42^2-LN(1+$H$24*EXP(1-D42^3)) -> 1.596047
A43: ='Stocks Returns'!A39 -> 42349 | B43: =SUMPRODUCT('Stocks Returns'!B39:E39,$H$10:$K$10) -> -0.024424401 | C43: =-B43 -> 0.024424401 | D43: =1+$H$13+$H$19*(B43-$H$13) -> 0.98376697 | E43: =$H$22*D43-$H$23*D43^2-LN(1+$H$24*EXP(1-D43^3)) -> 1.5777805
A44: ='Stocks Returns'!A40 -> 42352 | B44: =SUMPRODUCT('Stocks Returns'!B40:E40,$H$10:$K$10) -> 0.0086046382 | C44: =-B44 -> -0.0086046382 | D44: =1+$H$13+$H$19*(B44-$H$13) -> 1.0057643 | E44: =$H$22*D44-$H$23*D44^2-LN(1+$H$24*EXP(1-D44^3)) -> 1.6002325
A45: ='Stocks Returns'!A41 -> 42353 | B45: =SUMPRODUCT('Stocks Returns'!B41:E41,$H$10:$K$10) -> 0.024056539 | C45: =-B45 -> -0.024056539 | D45: =1+$H$13+$H$19*(B45-$H$13) -> 1.0160553 | E45: =$H$22*D45-$H$23*D45^2-LN(1+$H$24*EXP(1-D45^3)) -> 1.6100691
A46: ='Stocks Returns'!A42 -> 42354 | B46: =SUMPRODUCT('Stocks Returns'!B42:E42,$H$10:$K$10) -> 0.016653442 | C46: =-B46 -> -0.016653442 | D46: =1+$H$13+$H$19*(B46-$H$13) -> 1.0111248 | E46: =$H$22*D46-$H$23*D46^2-LN(1+$H$24*EXP(1-D46^3)) -> 1.6054103
A47: ='Stocks Returns'!A43 -> 42355 | B47: =SUMPRODUCT('Stocks Returns'!B43:E43,$H$10:$K$10) -> -0.014595104 | C47: =-B47 -> 0.014595104 | D47: =1+$H$13+$H$19*(B47-$H$13) -> 0.99031328 | E47: =$H$22*D47-$H$23*D47^2-LN(1+$H$24*EXP(1-D47^3)) -> 1.5846617
A48: ='Stocks Returns'!A44 -> 42356 | B48: =SUMPRODUCT('Stocks Returns'!B44:E44,$H$10:$K$10) -> -0.027192279 | C48: =-B48 -> 0.027192279 | D48: =1+$H$13+$H$19*(B48-$H$13) -> 0.98192356 | E48: =$H$22*D48-$H$23*D48^2-LN(1+$H$24*EXP(1-D48^3)) -> 1.5758128
... A2545: ='Stocks Returns'!A2541 -> 45853 | B2545: =SUMPRODUCT('Stocks Returns'!B2541:E2541,$H$10:$K$10) -> -0.010286994 | C2545: =-B2545 -> 0.010286994 | D2545: =1+$H$13+$H$19*(B2545-$H$13) -> 0.99318248 | E2545: =$H$22*D2545-$H$23*D2545^2-LN(1+$H$24*EXP(1-D2545^3)) -> 1.5876248

Sheet 3_SIM_t1
A2: POINT 3 - Single Index Model and Markowitz portfolio - rebalancing 1 (15/05/2025)
A3: Index = optimal portfolio from point 2 (lambda share in the risky portfolio + 1-lambda share in the risk-free asset). Same sample as point 2: no data after the valuation date. | M3: MARKET PARAMETERS
M4: E[Rm] daily | N4: =AVERAGE($B$6:$B$2502) -> 0.00054039609
A5: Date | B5: R index (market) | C5: WARNER BROS DISCOVERY | D5: VISA 'A' | E5: MICROCHIP TECH. | F5: CONOCOPHILLIPS | G5: residual 1 | H5: residual 2 | I5: residual 3 | J5: residual 4 | M5: Var(Rm) (population variance) | N5: =VARP($B$6:$B$2502) -> 0.00011092769
A6: ='2_CVaR_t1'!A6 -> 42298 | B6: ='2_CVaR_t1'!D6-1 -> -0.0072022243 | C6: ='Stocks Returns'!B2 -> -0.012679918 | D6: ='Stocks Returns'!C2 -> -0.010749869 | E6: ='Stocks Returns'!D2 -> -0.0050632911 | F6: ='Stocks Returns'!E2 -> -0.010646246 | G6: =C6-($P$11+$O$11*$B6) -> -0.0054862525 | H6: =D6-($P$12+$O$12*$B6) -> -0.00030397197 | I6: =E6-($P$13+$O$13*$B6) -> 0.0050242329 | J6: =F6-($P$14+$O$14*$B6) -> -0.0033351531 | M6: Daily risk-free rate rf | N6: ='2_CVaR_t1'!H13 -> 9.3320763e-05
A7: ='2_CVaR_t1'!A7 -> 42299 | B7: ='2_CVaR_t1'!D7-1 -> 0.0098226677 | C7: ='Stocks Returns'!B3 -> 0.022214509 | D7: ='Stocks Returns'!C3 -> 0.012721972 | E7: ='Stocks Returns'!D3 -> 0.036047498 | F7: ='Stocks Returns'!E3 -> 0.030394563 | G7: =C7-($P$11+$O$11*$B7) -> 0.013697286 | H7: =D7-($P$12+$O$12*$B7) -> -0.001429673 | I7: =E7-($P$13+$O$13*$B7) -> 0.022426665 | J7: =F7-($P$14+$O$14*$B7) -> 0.020494092 | M7: Target return of the Markowitz portfolio (= daily rf) | N7: =N6 -> 9.3320763e-05
A8: ='2_CVaR_t1'!A8 -> 42300 | B8: ='2_CVaR_t1'!D8-1 -> 0.0057840117 | C8: ='Stocks Returns'!B4 -> 0.010865874 | D8: ='Stocks Returns'!C4 -> 0.0085056268 | E8: ='Stocks Returns'!D4 -> 0.0051166598 | F8: ='Stocks Returns'!E4 -> 0.00054965189 | G8: =C8-($P$11+$O$11*$B8) -> 0.0060755982 | H8: =D8-($P$12+$O$12*$B8) -> 0.00018902675 | I8: =E8-($P$13+$O$13*$B8) -> -0.0028800612 | J8: =F8-($P$14+$O$14*$B8) -> -0.0052678806
A9: ='2_CVaR_t1'!A9 -> 42303 | B9: ='2_CVaR_t1'!D9-1 -> 0.0088894447 | C9: ='Stocks Returns'!B5 -> -0.016123614 | D9: ='Stocks Returns'!C5 -> 0.014402491 | E9: ='Stocks Returns'!D5 -> -0.012217471 | F9: ='Stocks Returns'!E5 -> -0.030397363 | G9: =C9-($P$11+$O$11*$B9) -> -0.023779642 | H9: =D9-($P$12+$O$12*$B9) -> 0.0015991657 | I9: =E9-($P$13+$O$13*$B9) -> -0.024538725 | J9: =F9-($P$14+$O$14*$B9) -> -0.039354378 | M9: OLS ESTIMATES OF THE SINGLE INDEX MODEL: R_i = alpha_i + beta_i * R_m + eps_i
A10: ='2_CVaR_t1'!A10 -> 42304 | B10: ='2_CVaR_t1'!D10-1 -> -0.0059926702 | C10: ='Stocks Returns'!B6 -> -0.017412086 | D10: ='Stocks Returns'!C6 -> -0.0084420568 | E10: ='Stocks Returns'!D6 -> -0.011956298 | F10: ='Stocks Returns'!E6 -> -0.023796034 | G10: =C10-($P$11+$O$11*$B10) -> -0.01133462 | H10: =D10-($P$12+$O$12*$B10) -> 0.00025627788 | I10: =E10-($P$13+$O$13*$B10) -> -0.0035531626 | J10: =F10-($P$14+$O$14*$B10) -> -0.017707758 | N10: Security | O10: beta | P10: alpha | Q10: var(eps_i) | R10: E[R_i] = alpha + beta*E[Rm]
A11: ='2_CVaR_t1'!A11 -> 42305 | B11: ='2_CVaR_t1'!D11-1 -> 0.011961599 | C11: ='Stocks Returns'!B7 -> 0.026059764 | D11: ='Stocks Returns'!C7 -> 0.017414861 | E11: ='Stocks Returns'!D7 -> 0.013144169 | F11: ='Stocks Returns'!E7 -> 0.031921068 | G11: =C11-($P$11+$O$11*$B11) -> 0.015568695 | H11: =D11-($P$12+$O$12*$B11) -> 0.00017289098 | I11: =E11-($P$13+$O$13*$B11) -> -0.003455276 | J11: =F11-($P$14+$O$14*$B11) -> 0.019858214 | N11: WARNER BROS DISCOVERY | O11: =SLOPE(C$6:C$2502,$B$6:$B$2502) -> 0.92281869 | P11: =INTERCEPT(C$6:C$2502,$B$6:$B$2502) -> -0.000547318 | Q11: =VARP(G$6:G$2502) -> 0.00072850654 | R11: =P11+O11*$N$4 -> -4.8630386e-05
A12: ='2_CVaR_t1'!A12 -> 42306 | B12: ='2_CVaR_t1'!D12-1 -> -0.0039141465 | C12: ='Stocks Returns'!B8 -> -0.0054182188 | D12: ='Stocks Returns'!C8 -> -0.0045644732 | E12: ='Stocks Returns'!D8 -> -0.024093904 | F12: ='Stocks Returns'!E8 -> 0.0052493438 | G12: =C12-($P$11+$O$11*$B12) -> -0.0012588532 | H12: =D12-($P$12+$O$12*$B12) -> 0.0011308131 | I12: =E12-($P$13+$O$13*$B12) -> -0.01858526 | J12: =F12-($P$14+$O$14*$B12) -> 0.0092363062 | N12: VISA 'A' | O12: =SLOPE(D$6:D$2502,$B$6:$B$2502) -> 1.4447987 | P12: =INTERCEPT(D$6:D$2502,$B$6:$B$2502) -> -4.0132582e-05 | Q12: =VARP(H$6:H$2502) -> 1.6262808e-06 | R12: =P12+O12*$N$4 -> 0.00074063099
A13: ='2_CVaR_t1'!A13 -> 42307 | B13: ='2_CVaR_t1'!D13-1 -> -0.0069386959 | C13: ='Stocks Returns'!B9 -> 0.0023833844 | D13: ='Stocks Returns'!C9 -> -0.011845625 | E13: ='Stocks Returns'!D9 -> 0.018991348 | F13: ='Stocks Returns'!E9 -> -0.0050354345 | G13: =C13-($P$11+$O$11*$B13) -> 0.0093338606 | H13: =D13-($P$12+$O$12*$B13) -> -0.0017804734 | I13: =E13-($P$13+$O$13*$B13) -> 0.028711891 | J13: =F13-($P$14+$O$14*$B13) -> 0.0020092403 | N13: MICROCHIP TECH. | O13: =SLOPE(E$6:E$2502,$B$6:$B$2502) -> 1.3925702 | P13: =INTERCEPT(E$6:E$2502,$B$6:$B$2502) -> -5.7921205e-05 | Q13: =VARP(I$6:I$2502) -> 0.00041975671 | R13: =P13+O13*$N$4 -> 0.00069461828
A14: ='2_CVaR_t1'!A14 -> 42310 | B14: ='2_CVaR_t1'!D14-1 -> -0.019273131 | C14: ='Stocks Returns'!B10 -> 0.021059783 | D14: ='Stocks Returns'!C10 -> -0.030420211 | E14: ='Stocks Returns'!D10 -> 0.012424933 | F14: ='Stocks Returns'!E10 -> 0.029803187 | G14: =C14-($P$11+$O$11*$B14) -> 0.039392706 | H14: =D14-($P$12+$O$12*$B14) -> -0.0025342843 | I14: =E14-($P$13+$O$13*$B14) -> 0.039322041 | J14: =F14-($P$14+$O$14*$B14) -> 0.049317539 | N14: CONOCOPHILLIPS | O14: =SLOPE(F$6:F$2502,$B$6:$B$2502) -> 1.0109646 | P14: =INTERCEPT(F$6:F$2502,$B$6:$B$2502) -> -2.9898753e-05 | Q14: =VARP(J$6:J$2502) -> 0.00047524091 | R14: =P14+O14*$N$4 -> 0.00051642258
A15: ='2_CVaR_t1'!A15 -> 42311 | B15: ='2_CVaR_t1'!D15-1 -> 0.023255236 | C15: ='Stocks Returns'!B11 -> 0.033932136 | D15: ='Stocks Returns'!C11 -> 0.035628822 | E15: ='Stocks Returns'!D11 -> -0.0014317856 | F15: ='Stocks Returns'!E11 -> 0.032580997 | G15: =C15-($P$11+$O$11*$B15) -> 0.013019087 | H15: =D15-($P$12+$O$12*$B15) -> 0.0020698197 | I15: =E15-($P$13+$O$13*$B15) -> -0.033758413 | J15: =F15-($P$14+$O$14*$B15) -> 0.0091006752
A16: ='2_CVaR_t1'!A16 -> 42312 | B16: ='2_CVaR_t1'!D16-1 -> 0.0039279582 | C16: ='Stocks Returns'!B12 -> -0.025096525 | D16: ='Stocks Returns'!C12 -> 0.0057766367 | E16: ='Stocks Returns'!D12 -> 0.0034821794 | F16: ='Stocks Returns'!E12 -> -0.0068746695 | G16: =C16-($P$11+$O$11*$B16) -> -0.028174 | H16: =D16-($P$12+$O$12*$B16) -> 0.00014166042 | I16: =E16-($P$13+$O$13*$B16) -> -0.0019298568 | J16: =F16-($P$14+$O$14*$B16) -> -0.010815797
A17: ='2_CVaR_t1'!A17 -> 42313 | B17: ='2_CVaR_t1'!D17-1 -> 0.0067136396 | C17: ='Stocks Returns'!B13 -> -0.026072607 | D17: ='Stocks Returns'!C13 -> 0.01161455 | E17: ='Stocks Returns'!D13 -> -0.022045315 | F17: ='Stocks Returns'!E13 -> -0.0010649627 | G17: =C17-($P$11+$O$11*$B17) -> -0.031720761 | H17: =D17-($P$12+$O$12*$B17) -> 0.0019548249 | I17: =E17-($P$13+$O$13*$B17) -> -0.031336608 | J17: =F17-($P$14+$O$14*$B17) -> -0.0078223161 | N17: Var-Cov | O17: WARNER BROS DISCOVERY | P17: VISA 'A' | Q17: MICROCHIP TECH. | R17: CONOCOPHILLIPS
A18: ='2_CVaR_t1'!A18 -> 42314 | B18: ='2_CVaR_t1'!D18-1 -> -0.0042313948 | C18: ='Stocks Returns'!B14 -> -0.016943409 | D18: ='Stocks Returns'!C14 -> -0.0064345193 | E18: ='Stocks Returns'!D14 -> -0.0012523482 | F18: ='Stocks Returns'!E14 -> -0.0090618337 | G18: =C18-($P$11+$O$11*$B18) -> -0.012491281 | H18: =D18-($P$12+$O$12*$B18) -> -0.00028087306 | I18: =E18-($P$13+$O$13*$B18) -> 0.0046980873 | J18: =F18-($P$14+$O$14*$B18) -> -0.0047541445 | N18: WARNER BROS DISCOVERY | O18: =$O$11*$O$11*$N$5+$Q$11 -> 0.00082297193 | P18: =$O$11*$O$12*$N$5 -> 0.00014789848 | Q18: =$O$11*$O$13*$N$5 -> 0.00014255205 | R18: =$O$11*$O$14*$N$5 -> 0.00010348855
A19: ='2_CVaR_t1'!A19 -> 42317 | B19: ='2_CVaR_t1'!D19-1 -> -0.0059092318 | C19: ='Stocks Returns'!B15 -> -0.00034470872 | D19: ='Stocks Returns'!C15 -> -0.009015873 | E19: ='Stocks Returns'!D15 -> -0.00073145246 | F19: ='Stocks Returns'!E15 -> -0.020261789 | G19: =C19-($P$11+$O$11*$B19) -> 0.0056557588 | H19: =D19-($P$12+$O$12*$B19) -> -0.00043809003 | I19: =E19-($P$13+$O$13*$B19) -> 0.0075554888 | J19: =F19-($P$14+$O$14*$B19) -> -0.014257866 | N19: VISA 'A' | O19: =$O$12*$O$11*$N$5 -> 0.00014789848 | P19: =$O$12*$O$12*$N$5+$Q$12 -> 0.00023318155 | Q19: =$O$12*$O$13*$N$5 -> 0.0002231847 | R19: =$O$12*$O$14*$N$5 -> 0.00016202547
A20: ='2_CVaR_t1'!A20 -> 42318 | B20: ='2_CVaR_t1'!D20-1 -> 0.011512281 | C20: ='Stocks Returns'!B16 -> 0.036551724 | D20: ='Stocks Returns'!C16 -> 0.018452076 | E20: ='Stocks Returns'!D16 -> -0.01369863 | F20: ='Stocks Returns'!E16 -> 0.00018301611 | G20: =C20-($P$11+$O$11*$B20) -> 0.026475294 | H20: =D20-($P$12+$O$12*$B20) -> 0.0018592798 | I20: =E20-($P$13+$O$13*$B20) -> -0.029672368 | J20: =F20-($P$14+$O$14*$B20) -> -0.011425594 | N20: MICROCHIP TECH. | O20: =$O$13*$O$11*$N$5 -> 0.00014255205 | P20: =$O$13*$O$12*$N$5 -> 0.0002231847 | Q20: =$O$13*$O$13*$N$5+$Q$13 -> 0.00063487343 | R20: =$O$13*$O$14*$N$5 -> 0.00015616835
A21: ='2_CVaR_t1'!A21 -> 42319 | B21: ='2_CVaR_t1'!D21-1 -> -0.0025146504 | C21: ='Stocks Returns'!B17 -> 0.01829674 | D21: ='Stocks Returns'!C17 -> -0.0037745345 | E21: ='Stocks Returns'!D17 -> -0.0012722646 | F21: ='Stocks Returns'!E17 -> -0.022140897 | G21: =C21-($P$11+$O$11*$B21) -> 0.021164624 | H21: =D21-($P$12+$O$12*$B21) -> -0.00010123823 | I21: =E21-($P$13+$O$13*$B21) -> 0.0022874838 | J21: =F21-($P$14+$O$14*$B21) -> -0.019568775 | N21: CONOCOPHILLIPS | O21: =$O$14*$O$11*$N$5 -> 0.00010348855 | P21: =$O$14*$O$12*$N$5 -> 0.00016202547 | Q21: =$O$14*$O$13*$N$5 -> 0.00015616835 | R21: =$O$14*$O$14*$N$5+$Q$14 -> 0.0005886145
A22: ='2_CVaR_t1'!A22 -> 42320 | B22: ='2_CVaR_t1'!D22-1 -> -0.007801097 | C22: ='Stocks Returns'!B18 -> -0.014701078 | D22: ='Stocks Returns'!C18 -> -0.010987623 | E22: ='Stocks Returns'!D18 -> -0.015498938 | F22: ='Stocks Returns'!E18 -> -0.027507485 | G22: =C22-($P$11+$O$11*$B22) -> -0.006954762 | H22: =D22-($P$12+$O$12*$B22) -> 0.00032352428 | I22: =E22-($P$13+$O$13*$B22) -> -0.0045774421 | J22: =F22-($P$14+$O$14*$B22) -> -0.019590953
A23: ='2_CVaR_t1'!A23 -> 42321 | B23: ='2_CVaR_t1'!D23-1 -> -0.0022763335 | C23: ='Stocks Returns'!B19 -> -0.0059681698 | D23: ='Stocks Returns'!C19 -> -0.0025539522 | E23: ='Stocks Returns'!D19 -> -0.015742937 | F23: ='Stocks Returns'!E19 -> -0.0026938618 | G23: =C23-($P$11+$O$11*$B23) -> -0.0033202086 | H23: =D23-($P$12+$O$12*$B23) -> 0.00077502408 | I23: =E23-($P$13+$O$13*$B23) -> -0.012515062 | J23: =F23-($P$14+$O$14*$B23) -> -0.00036267042 | M23: OPTIMAL MARKOWITZ PORTFOLIO (minimum variance for a fixed mean, no short selling)
A24: ='2_CVaR_t1'!A24 -> 42324 | B24: ='2_CVaR_t1'!D24-1 -> 0.0069658062 | C24: ='Stocks Returns'!B20 -> 0.020346898 | D24: ='Stocks Returns'!C20 -> 0.010113942 | E24: ='Stocks Returns'!D20 -> 0.0067922875 | F24: ='Stocks Returns'!E20 -> 0.049006367 | G24: =C24-($P$11+$O$11*$B24) -> 0.01446604 | H24: =D24-($P$12+$O$12*$B24) -> 8.9886729e-05 | I24: =E24-($P$13+$O$13*$B24) -> -0.0028501653 | J24: =F24-($P$14+$O$14*$B24) -> 0.041994082 | M24: Variable cells: weights in blue. Constraints: weights sum = 1; weights >= 0; expected return = N7. Objective: minimize O32.
A25: ='2_CVaR_t1'!A25 -> 42325 | B25: ='2_CVaR_t1'!D25-1 -> -0.00044759761 | C25: ='Stocks Returns'!B21 -> -0.016018307 | D25: ='Stocks Returns'!C21 -> -0.00088719899 | E25: ='Stocks Returns'!D21 -> 0.0028291621 | F25: ='Stocks Returns'!E21 -> -0.0086444731 | G25: =C25-($P$11+$O$11*$B25) -> -0.015057937 | H25: =D25-($P$12+$O$12*$B25) -> -0.00020037796 | I25: =E25-($P$13+$O$13*$B25) -> 0.0035103944 | J25: =F25-($P$14+$O$14*$B25) -> -0.008162069 | N25: Security | O25: Weight w | P25: E[R_i] | Q25: w x E[R_i] | R25: row i of Sigma %*% w
A26: ='2_CVaR_t1'!A26 -> 42326 | B26: ='2_CVaR_t1'!D26-1 -> 0.014319106 | C26: ='Stocks Returns'!B22 -> 0.022591362 | D26: ='Stocks Returns'!C22 -> 0.020677407 | E26: ='Stocks Returns'!D22 -> 0.01953125 | F26: ='Stocks Returns'!E22 -> 0.010760668 | G26: =C26-($P$11+$O$11*$B26) -> 0.0099247416 | H26: =D26-($P$12+$O$12*$B26) -> 2.9314047e-05 | I26: =E26-($P$13+$O$13*$B26) -> -0.00035118878 | J26: =F26-($P$14+$O$14*$B26) -> -0.0036855428 | N26: WARNER BROS DISCOVERY | O26: 0.74878258 | P26: =R11 -> -4.8630386e-05 | Q26: =O26*P26 -> -3.6413586e-05 | R26: =SUMPRODUCT($O$26:$O$29,O$18:O$21) -> 0.00064222517
A27: ='2_CVaR_t1'!A27 -> 42327 | B27: ='2_CVaR_t1'!D27-1 -> -0.0023355322 | C27: ='Stocks Returns'!B23 -> -0.0071474984 | D27: ='Stocks Returns'!C23 -> -0.0038528461 | E27: ='Stocks Returns'!D23 -> 0.0042571307 | F27: ='Stocks Returns'!E23 -> -0.016886931 | G27: =C27-($P$11+$O$11*$B27) -> -0.0044449076 | H27: =D27-($P$12+$O$12*$B27) -> -0.00043833971 | I27: =E27-($P$13+$O$13*$B27) -> 0.0075674444 | J27: =F27-($P$14+$O$14*$B27) -> -0.014495892 | N27: VISA 'A' | O27: 1.7952287e-18 | P27: =R12 -> 0.00074063099 | Q27: =O27*P27 -> 1.329602e-21 | R27: =SUMPRODUCT($O$26:$O$29,P$18:P$21) -> 0.00015144742
A28: ='2_CVaR_t1'!A28 -> 42328 | B28: ='2_CVaR_t1'!D28-1 -> 0.00050937556 | C28: ='Stocks Returns'!B24 -> 0.0068717277 | D28: ='Stocks Returns'!C24 -> 0.00049906425 | E28: ='Stocks Returns'!D24 -> 0.0042390844 | F28: ='Stocks Returns'!E24 -> -0.011762509 | G28: =C28-($P$11+$O$11*$B28) -> 0.0069489845 | H28: =D28-($P$12+$O$12*$B28) -> -0.00019674831 | I28: =E28-($P$13+$O$13*$B28) -> 0.0035876643 | J28: =F28-($P$14+$O$14*$B28) -> -0.012247571 | N28: MICROCHIP TECH. | O28: 0 | P28: =R13 -> 0.00069461828 | Q28: =O28*P28 -> 0 | R28: =SUMPRODUCT($O$26:$O$29,Q$18:Q$21) -> 0.0001459727
A29: ='2_CVaR_t1'!A29 -> 42331 | B29: ='2_CVaR_t1'!D29-1 -> -0.0012776918 | C29: ='Stocks Returns'!B25 -> -0.0019499513 | D29: ='Stocks Returns'!C25 -> -0.00099763063 | E29: ='Stocks Returns'!D25 -> -0.016462642 | F29: ='Stocks Returns'!E25 -> 0.0066125071 | G29: =C29-($P$11+$O$11*$B29) -> -0.00022355541 | H29: =D29-($P$12+$O$12*$B29) -> 0.00088850937 | I29: =E29-($P$13+$O$13*$B29) -> -0.014625446 | J29: =F29-($P$14+$O$14*$B29) -> 0.007934107 | N29: CONOCOPHILLIPS | O29: 0.25121742 | P29: =R14 -> 0.00051642258 | Q29: =O29*P29 -> 0.00012973435 | R29: =SUMPRODUCT($O$26:$O$29,R$18:R$21) -> 0.00022536064
A30: ='2_CVaR_t1'!A30 -> 42332 | B30: ='2_CVaR_t1'!D30-1 -> -0.0019800619 | C30: ='Stocks Returns'!B26 -> 0.007815044 | D30: ='Stocks Returns'!C26 -> -0.0039945076 | E30: ='Stocks Returns'!D26 -> 0.013519313 | F30: ='Stocks Returns'!E26 -> 0.038288288 | G30: =C30-($P$11+$O$11*$B30) -> 0.0101896 | H30: =D30-($P$12+$O$12*$B30) -> -0.001093584 | I30: =E30-($P$13+$O$13*$B30) -> 0.01633461 | J30: =F30-($P$14+$O$14*$B30) -> 0.04031996 | N30: Sum of weights | O30: =SUM(O26:O29) -> 1
A31: ='2_CVaR_t1'!A31 -> 42333 | B31: ='2_CVaR_t1'!D31-1 -> -0.0019429185 | C31: ='Stocks Returns'!B27 -> 0.0054927302 | D31: ='Stocks Returns'!C27 -> -0.0028825667 | E31: ='Stocks Returns'!D27 -> -0.0016938387 | F31: ='Stocks Returns'!E27 -> -0.016992046 | G31: =C31-($P$11+$O$11*$B31) -> 0.0078330097 | H31: =D31-($P$12+$O$12*$B31) -> -3.5308098e-05 | I31: =E31-($P$13+$O$13*$B31) -> 0.0010697329 | J31: =F31-($P$14+$O$14*$B31) -> -0.014997926 | N31: Expected portfolio return | O31: =SUM(Q26:Q29) -> 9.3320763e-05
A32: ='2_CVaR_t1'!A32 -> 42334 | B32: ='2_CVaR_t1'!D32-1 -> 2.8556153e-05 | C32: ='Stocks Returns'!B28 -> 0 | D32: ='Stocks Returns'!C28 -> 0 | E32: ='Stocks Returns'!D28 -> 0 | F32: ='Stocks Returns'!E28 -> 0 | G32: =C32-($P$11+$O$11*$B32) -> 0.00052096585 | H32: =D32-($P$12+$O$12*$B32) -> -1.1253115e-06 | I32: =E32-($P$13+$O$13*$B32) -> 1.8154757e-05 | J32: =F32-($P$14+$O$14*$B32) -> 1.0294918e-06 | N32: Portfolio variance w' Sigma w | O32: =SUMPRODUCT(O26:O29,R26:R29) -> 0.00053750154
A33: ='2_CVaR_t1'!A33 -> 42335 | B33: ='2_CVaR_t1'!D33-1 -> 0.0027642055 | C33: ='Stocks Returns'!B29 -> -0.001285347 | D33: ='Stocks Returns'!C29 -> 0.0035193565 | E33: ='Stocks Returns'!D29 -> 0.01145281 | F33: ='Stocks Returns'!E29 -> -0.016550202 | G33: =C33-($P$11+$O$11*$B33) -> -0.0032888895 | H33: =D33-($P$12+$O$12*$B33) -> -0.00043423144 | I33: =E33-($P$13+$O$13*$B33) -> 0.0076613812 | J33: =F33-($P$14+$O$14*$B33) -> -0.019314817 | N33: Daily standard deviation | O33: =SQRT(O32) -> 0.023184079
A34: ='2_CVaR_t1'!A34 -> 42338 | B34: ='2_CVaR_t1'!D34-1 -> -0.0062390453 | C34: ='Stocks Returns'!B30 -> 0.0019305019 | D34: ='Stocks Returns'!C30 -> -0.010395792 | E34: ='Stocks Returns'!D30 -> 0.012371566 | F34: ='Stocks Returns'!E30 -> 0.01065819 | G34: =C34-($P$11+$O$11*$B34) -> 0.0082353276 | H34: =D34-($P$12+$O$12*$B34) -> -0.0013414944 | I34: =E34-($P$13+$O$13*$B34) -> 0.021117796 | J34: =F34-($P$14+$O$14*$B34) -> 0.016995543 | N34: Annualized standard deviation | O34: =O33*SQRT(252) -> 0.36803585
A35: ='2_CVaR_t1'!A35 -> 42339 | B35: ='2_CVaR_t1'!D35-1 -> 0.0076483388 | C35: ='Stocks Returns'!B31 -> -0.0019267823 | D35: ='Stocks Returns'!C31 -> 0.011390963 | E35: ='Stocks Returns'!D31 -> 0.0043496272 | F35: ='Stocks Returns'!E31 -> 0.010360777 | G35: =C35-($P$11+$O$11*$B35) -> -0.0084374943 | H35: =D35-($P$12+$O$12*$B35) -> 0.00038078577 | I35: =E35-($P$13+$O$13*$B35) -> -0.0062433002 | J35: =F35-($P$14+$O$14*$B35) -> 0.0026584759 | N35: Mean constraint check (should be 0) | O35: =O31-N7 -> 5.2854856e-19
A36: ='2_CVaR_t1'!A36 -> 42340 | B36: ='2_CVaR_t1'!D36-1 -> -0.0086468953 | C36: ='Stocks Returns'!B32 -> -0.028957529 | D36: ='Stocks Returns'!C32 -> -0.010887248 | E36: ='Stocks Returns'!D32 -> -0.03773974 | F36: ='Stocks Returns'!E32 -> -0.037722029 | G36: =C36-($P$11+$O$11*$B36) -> -0.020430694 | H36: =D36-($P$12+$O$12*$B36) -> 0.0016459075 | I36: =E36-($P$13+$O$13*$B36) -> -0.02564041 | J36: =F36-($P$14+$O$14*$B36) -> -0.028950425
A37: ='2_CVaR_t1'!A37 -> 42341 | B37: ='2_CVaR_t1'!D37-1 -> -0.0063839867 | C37: ='Stocks Returns'!B33 -> -0.0019880716 | D37: ='Stocks Returns'!C33 -> -0.0094888664 | E37: ='Stocks Returns'!D33 -> -0.0049292756 | F37: ='Stocks Returns'!E33 -> -0.017887726 | G37: =C37-($P$11+$O$11*$B37) -> 0.0044505086 | H37: =D37-($P$12+$O$12*$B37) -> -0.0002251582 | I37: =E37-($P$13+$O$13*$B37) -> 0.0040187951 | J37: =F37-($P$14+$O$14*$B37) -> -0.011403843
A38: ='2_CVaR_t1'!A38 -> 42342 | B38: ='2_CVaR_t1'!D38-1 -> 0.018414877 | C38: ='Stocks Returns'!B34 -> 0.020252324 | D38: ='Stocks Returns'!C34 -> 0.026951079 | E38: ='Stocks Returns'!D34 -> 0.020245531 | F38: ='Stocks Returns'!E34 -> -0.0081379578 | G38: =C38-($P$11+$O$11*$B38) -> 0.0038060495 | H38: =D38-($P$12+$O$12*$B38) -> 0.00038542174 | I38: =E38-($P$13+$O$13*$B38) -> -0.0053405564 | J38: =F38-($P$14+$O$14*$B38) -> -0.026724848
A39: ='2_CVaR_t1'!A39 -> 42345 | B39: ='2_CVaR_t1'!D39-1 -> -0.0075132063 | C39: ='Stocks Returns'!B35 -> -0.00097624471 | D39: ='Stocks Returns'!C35 -> -0.010572139 | E39: ='Stocks Returns'!D35 -> -0.014566181 | F39: ='Stocks Returns'!E35 -> -0.042977144 | G39: =C39-($P$11+$O$11*$B39) -> 0.0065044005 | H39: =D39-($P$12+$O$12*$B39) -> 0.00032306398 | I39: =E39-($P$13+$O$13*$B39) -> -0.0040455928 | J39: =F39-($P$14+$O$14*$B39) -> -0.035351659
A40: ='2_CVaR_t1'!A40 -> 42346 | B40: ='2_CVaR_t1'!D40-1 -> -0.0043326311 | C40: ='Stocks Returns'!B36 -> -0.041368078 | D40: ='Stocks Returns'!C36 -> -0.0060339409 | E40: ='Stocks Returns'!D36 -> -0.010068552 | F40: ='Stocks Returns'!E36 -> -0.014084507 | G40: =C40-($P$11+$O$11*$B40) -> -0.036822527 | H40: =D40-($P$12+$O$12*$B40) -> 0.00026597142 | I40: =E40-($P$13+$O$13*$B40) -> -0.0039771378 | J40: =F40-($P$14+$O$14*$B40) -> -0.0096744715
A41: ='2_CVaR_t1'!A41 -> 42347 | B41: ='2_CVaR_t1'!D41-1 -> -0.010395144 | C41: ='Stocks Returns'!B37 -> -0.033299354 | D41: ='Stocks Returns'!C37 -> -0.015049956 | E41: ='Stocks Returns'!D37 -> -0.015148236 | F41: ='Stocks Returns'!E37 -> 0.0035196687 | G41: =C41-($P$11+$O$11*$B41) -> -0.023159203 | H41: =D41-($P$12+$O$12*$B41) -> 9.0678925e-06 | I41: =E41-($P$13+$O$13*$B41) -> -0.00061434701 | J41: =F41-($P$14+$O$14*$B41) -> 0.014058691
A42: ='2_CVaR_t1'!A42 -> 42348 | B42: ='2_CVaR_t1'!D42-1 -> 0.0019176248 | C42: ='Stocks Returns'!B38 -> -0.0021089631 | D42: ='Stocks Returns'!C38 -> 0.0030816641 | E42: ='Stocks Returns'!D38 -> -0.0035157108 | F42: ='Stocks Returns'!E38 -> 0.015473489 | G42: =C42-($P$11+$O$11*$B42) -> -0.0033312651 | H42: =D42-($P$12+$O$12*$B42) -> 0.00035121489 | I42: =E42-($P$13+$O$13*$B42) -> -0.0061282167 | J42: =F42-($P$14+$O$14*$B42) -> 0.013564737
A43: ='2_CVaR_t1'!A43 -> 42349 | B43: ='2_CVaR_t1'!D43-1 -> -0.017416471 | C43: ='Stocks Returns'!B39 -> -0.035928144 | D43: ='Stocks Returns'!C39 -> -0.025729647 | E43: ='Stocks Returns'!D39 -> -0.015656009 | F43: ='Stocks Returns'!E39 -> -0.022145469 | G43: =C43-($P$11+$O$11*$B43) -> -0.019308581 | H43: =D43-($P$12+$O$12*$B43) -> -0.00052621967 | I43: =E43-($P$13+$O$13*$B43) -> 0.0086555704 | J43: =F43-($P$14+$O$14*$B43) -> -0.0045081347
A44: ='2_CVaR_t1'!A44 -> 42352 | B44: ='2_CVaR_t1'!D44-1 -> 0.0065540751 | C44: ='Stocks Returns'!B40 -> -0.033613445 | D44: ='Stocks Returns'!C40 -> 0.0099855472 | E44: ='Stocks Returns'!D40 -> -0.00067204301 | F44: ='Stocks Returns'!E40 -> 0.029087887 | G44: =C44-($P$11+$O$11*$B44) -> -0.03911435 | H44: =D44-($P$12+$O$12*$B44) -> 0.00055636067 | I44: =E44-($P$13+$O$13*$B44) -> -0.0097411313 | J44: =F44-($P$14+$O$14*$B44) -> 0.022491848
A45: ='2_CVaR_t1'!A45 -> 42353 | B45: ='2_CVaR_t1'!D45-1 -> 0.016227357 | C45: ='Stocks Returns'!B41 -> 0.0026465028 | D45: ='Stocks Returns'!C41 -> 0.022765708 | E45: ='Stocks Returns'!D41 -> 0.032728088 | F45: ='Stocks Returns'!E41 -> 0.020795477 | G45: =C45-($P$11+$O$11*$B45) -> -0.011781088 | H45: =D45-($P$12+$O$12*$B45) -> -0.0006394236 | I45: =E45-($P$13+$O$13*$B45) -> 0.010188275 | J45: =F45-($P$14+$O$14*$B45) -> 0.0044200923
A46: ='2_CVaR_t1'!A46 -> 42354 | B46: ='2_CVaR_t1'!D46-1 -> 0.011195572 | C46: ='Stocks Returns'!B42 -> 0.024886878 | D46: ='Stocks Returns'!C42 -> 0.015772068 | E46: ='Stocks Returns'!D42 -> 0.022574343 | F46: ='Stocks Returns'!E42 -> -0.023931962 | G46: =C46-($P$11+$O$11*$B46) -> 0.015102712 | H46: =D46-($P$12+$O$12*$B46) -> -0.00036314758 | I46: =E46-($P$13+$O$13*$B46) -> 0.0070416444 | J46: =F46-($P$14+$O$14*$B46) -> -0.035220391
A47: ='2_CVaR_t1'!A47 -> 42355 | B47: ='2_CVaR_t1'!D47-1 -> -0.010158341 | C47: ='Stocks Returns'!B43 -> -0.025754231 | D47: ='Stocks Returns'!C43 -> -0.014650639 | E47: ='Stocks Returns'!D43 -> -0.014222034 | F47: ='Stocks Returns'!E43 -> -0.041945289 | G47: =C47-($P$11+$O$11*$B47) -> -0.015832606 | H47: =D47-($P$12+$O$12*$B47) -> 6.6251756e-05 | I47: =E47-($P$13+$O$13*$B47) -> -1.7909598e-05 | J47: =F47-($P$14+$O$14*$B47) -> -0.031645667
... A2502: ='2_CVaR_t1'!A2502 -> 45792 | B2502: ='2_CVaR_t1'!D2502-1 -> 0.01082088 | C2502: ='Stocks Returns'!B2498 -> -0.0076004343 | D2502: ='Stocks Returns'!C2498 -> 0.016383325 | E2502: ='Stocks Returns'!D2498 -> 0.0024732069 | F2502: ='Stocks Returns'!E2498 -> 0.004213028 | G2502: =C2502-($P$11+$O$11*$B2502) -> -0.017038827 | H2502: =D2502-($P$12+$O$12*$B2502) -> 0.00078946371 | I2502: =E2502-($P$13+$O$13*$B2502) -> -0.012537707 | J2502: =F2502-($P$14+$O$14*$B2502) -> -0.0066966004

Sheet 3_SIM_t2
A2: POINT 3 - Single Index Model and Markowitz portfolio - rebalancing 2 (16/06/2025)
M3: MARKET PARAMETERS
M4: E[Rm] daily | N4: =AVERAGE($B$6:$B$2524) -> 0.00052630147
A5: Date | B5: R index (market) | C5: WARNER BROS DISCOVERY | D5: VISA 'A' | E5: MICROCHIP TECH. | F5: CONOCOPHILLIPS | G5: residual 1 | H5: residual 2 | I5: residual 3 | J5: residual 4 | M5: Var(Rm) (population variance) | N5: =VARP($B$6:$B$2524) -> 0.00010618275
A6: ='2_CVaR_t2'!A6 -> 42298 | B6: ='2_CVaR_t2'!D6-1 -> -0.0069828675 | C6: ='Stocks Returns'!B2 -> -0.012679918 | D6: ='Stocks Returns'!C2 -> -0.010749869 | E6: ='Stocks Returns'!D2 -> -0.0050632911 | F6: ='Stocks Returns'!E2 -> -0.010646246 | G6: =C6-($P$11+$O$11*$B6) -> -0.0054818835 | H6: =D6-($P$12+$O$12*$B6) -> -0.00042580966 | I6: =E6-($P$13+$O$13*$B6) -> 0.0052823912 | J6: =F6-($P$14+$O$14*$B6) -> -0.0033730277 | M6: Daily risk-free rate rf | N6: ='2_CVaR_t2'!H13 -> 9.8731645e-05
A7: ='2_CVaR_t2'!A7 -> 42299 | B7: ='2_CVaR_t2'!D7-1 -> 0.0099341188 | C7: ='Stocks Returns'!B3 -> 0.022214509 | D7: ='Stocks Returns'!C3 -> 0.012721972 | E7: ='Stocks Returns'!D3 -> 0.036047498 | F7: ='Stocks Returns'!E3 -> 0.030394563 | G7: =C7-($P$11+$O$11*$B7) -> 0.013150023 | H7: =D7-($P$12+$O$12*$B7) -> -0.0018513316 | I7: =E7-($P$13+$O$13*$B7) -> 0.021425249 | J7: =F7-($P$14+$O$14*$B7) -> 0.020106777 | M7: Target return of the Markowitz portfolio (= daily rf) | N7: =N6 -> 9.8731645e-05
A8: ='2_CVaR_t2'!A8 -> 42300 | B8: ='2_CVaR_t2'!D8-1 -> 0.005621177 | C8: ='Stocks Returns'!B4 -> 0.010865874 | D8: ='Stocks Returns'!C4 -> 0.0085056268 | E8: ='Stocks Returns'!D4 -> 0.0051166598 | F8: ='Stocks Returns'!E4 -> 0.00054965189 | G8: =C8-($P$11+$O$11*$B8) -> 0.005947476 | H8: =D8-($P$12+$O$12*$B8) -> 0.00027984131 | I8: =E8-($P$13+$O$13*$B8) -> -0.0031400796 | J8: =F8-($P$14+$O$14*$B8) -> -0.0052610013
A9: ='2_CVaR_t2'!A9 -> 42303 | B9: ='2_CVaR_t2'!D9-1 -> 0.0083402478 | C9: ='Stocks Returns'!B5 -> -0.016123614 | D9: ='Stocks Returns'!C5 -> 0.014402491 | E9: ='Stocks Returns'!D5 -> -0.012217471 | F9: ='Stocks Returns'!E5 -> -0.030397363 | G9: =C9-($P$11+$O$11*$B9) -> -0.023655891 | H9: =D9-($P$12+$O$12*$B9) -> 0.0021749474 | I9: =E9-($P$13+$O$13*$B9) -> -0.024487311 | J9: =F9-($P$14+$O$14*$B9) -> -0.0390306 | M9: OLS ESTIMATES OF THE SINGLE INDEX MODEL: R_i = alpha_i + beta_i * R_m + eps_i
A10: ='2_CVaR_t2'!A10 -> 42304 | B10: ='2_CVaR_t2'!D10-1 -> -0.005926777 | C10: ='Stocks Returns'!B6 -> -0.017412086 | D10: ='Stocks Returns'!C6 -> -0.0084420568 | E10: ='Stocks Returns'!D6 -> -0.011956298 | F10: ='Stocks Returns'!E6 -> -0.023796034 | G10: =C10-($P$11+$O$11*$B10) -> -0.011229285 | H10: =D10-($P$12+$O$12*$B10) -> 0.00032771445 | I10: =E10-($P$13+$O$13*$B10) -> -0.0031693087 | J10: =F10-($P$14+$O$14*$B10) -> -0.017619111 | N10: Security | O10: beta | P10: alpha | Q10: var(eps_i) | R10: E[R_i] = alpha + beta*E[Rm]
A11: ='2_CVaR_t2'!A11 -> 42305 | B11: ='2_CVaR_t2'!D11-1 -> 0.011685377 | C11: ='Stocks Returns'!B7 -> 0.026059764 | D11: ='Stocks Returns'!C7 -> 0.017414861 | E11: ='Stocks Returns'!D7 -> 0.013144169 | F11: ='Stocks Returns'!E7 -> 0.031921068 | G11: =C11-($P$11+$O$11*$B11) -> 0.015311771 | H11: =D11-($P$12+$O$12*$B11) -> 0.00026416493 | I11: =E11-($P$13+$O$13*$B11) -> -0.0040627775 | J11: =F11-($P$14+$O$14*$B11) -> 0.019815355 | N11: WARNER BROS DISCOVERY | O11: =SLOPE(C$6:C$2524,$B$6:$B$2524) -> 0.96131306 | P11: =INTERCEPT(C$6:C$2524,$B$6:$B$2524) -> -0.0004853125 | Q11: =VARP(G$6:G$2524) -> 0.00072599773 | R11: =P11+O11*$N$4 -> 2.062798e-05
A12: ='2_CVaR_t2'!A12 -> 42306 | B12: ='2_CVaR_t2'!D12-1 -> -0.0040635053 | C12: ='Stocks Returns'!B8 -> -0.0054182188 | D12: ='Stocks Returns'!C8 -> -0.0045644732 | E12: ='Stocks Returns'!D8 -> -0.024093904 | F12: ='Stocks Returns'!E8 -> 0.0052493438 | G12: =C12-($P$11+$O$11*$B12) -> -0.0010266055 | H12: =D12-($P$12+$O$12*$B12) -> 0.0014630513 | I12: =E12-($P$13+$O$13*$B12) -> -0.018056935 | J12: =F12-($P$14+$O$14*$B12) -> 0.0094920618 | N12: VISA 'A' | O12: =SLOPE(D$6:D$2524,$B$6:$B$2524) -> 1.4717375 | P12: =INTERCEPT(D$6:D$2524,$B$6:$B$2524) -> -4.7111413e-05 | Q12: =VARP(H$6:H$2524) -> 2.8259141e-06 | R12: =P12+O12*$N$4 -> 0.00072746619
A13: ='2_CVaR_t2'!A13 -> 42307 | B13: ='2_CVaR_t2'!D13-1 -> -0.0064068994 | C13: ='Stocks Returns'!B9 -> 0.0023833844 | D13: ='Stocks Returns'!C9 -> -0.011845625 | E13: ='Stocks Returns'!D9 -> 0.018991348 | F13: ='Stocks Returns'!E9 -> -0.0050354345 | G13: =C13-($P$11+$O$11*$B13) -> 0.0090277329 | H13: =D13-($P$12+$O$12*$B13) -> -0.0023692394 | I13: =E13-($P$13+$O$13*$B13) -> 0.028486954 | J13: =F13-($P$14+$O$14*$B13) -> 0.0016398887 | N13: MICROCHIP TECH. | O13: =SLOPE(E$6:E$2524,$B$6:$B$2524) -> 1.4759089 | P13: =INTERCEPT(E$6:E$2524,$B$6:$B$2524) -> -3.9605915e-05 | Q13: =VARP(I$6:I$2524) -> 0.00040422695 | R13: =P13+O13*$N$4 -> 0.00073716713
A14: ='2_CVaR_t2'!A14 -> 42310 | B14: ='2_CVaR_t2'!D14-1 -> -0.018291306 | C14: ='Stocks Returns'!B10 -> 0.021059783 | D14: ='Stocks Returns'!C10 -> -0.030420211 | E14: ='Stocks Returns'!D10 -> 0.012424933 | F14: ='Stocks Returns'!E10 -> 0.029803187 | G14: =C14-($P$11+$O$11*$B14) -> 0.039128766 | H14: =D14-($P$12+$O$12*$B14) -> -0.0034530995 | I14: =E14-($P$13+$O$13*$B14) -> 0.03946084 | J14: =F14-($P$14+$O$14*$B14) -> 0.048815347 | N14: CONOCOPHILLIPS | O14: =SLOPE(F$6:F$2524,$B$6:$B$2524) -> 1.0380693 | P14: =INTERCEPT(F$6:F$2524,$B$6:$B$2524) -> -2.451791e-05 | Q14: =VARP(J$6:J$2524) -> 0.00047163293 | R14: =P14+O14*$N$4 -> 0.00052181948
A15: ='2_CVaR_t2'!A15 -> 42311 | B15: ='2_CVaR_t2'!D15-1 -> 0.022328229 | C15: ='Stocks Returns'!B11 -> 0.033932136 | D15: ='Stocks Returns'!C11 -> 0.035628822 | E15: ='Stocks Returns'!D11 -> -0.0014317856 | F15: ='Stocks Returns'!E11 -> 0.032580997 | G15: =C15-($P$11+$O$11*$B15) -> 0.01295303 | H15: =D15-($P$12+$O$12*$B15) -> 0.0028146417 | I15: =E15-($P$13+$O$13*$B15) -> -0.034346612 | J15: =F15-($P$14+$O$14*$B15) -> 0.0094272667
A16: ='2_CVaR_t2'!A16 -> 42312 | B16: ='2_CVaR_t2'!D16-1 -> 0.0038114779 | C16: ='Stocks Returns'!B12 -> -0.025096525 | D16: ='Stocks Returns'!C12 -> 0.0057766367 | E16: ='Stocks Returns'!D12 -> 0.0034821794 | F16: ='Stocks Returns'!E12 -> -0.0068746695 | G16: =C16-($P$11+$O$11*$B16) -> -0.028275236 | H16: =D16-($P$12+$O$12*$B16) -> 0.00021425327 | I16: =E16-($P$13+$O$13*$B16) -> -0.0021036089 | J16: =F16-($P$14+$O$14*$B16) -> -0.01080673
A17: ='2_CVaR_t2'!A17 -> 42313 | B17: ='2_CVaR_t2'!D17-1 -> 0.0061529027 | C17: ='Stocks Returns'!B13 -> -0.026072607 | D17: ='Stocks Returns'!C13 -> 0.01161455 | E17: ='Stocks Returns'!D13 -> -0.022045315 | F17: ='Stocks Returns'!E13 -> -0.0010649627 | G17: =C17-($P$11+$O$11*$B17) -> -0.03150216 | H17: =D17-($P$12+$O$12*$B17) -> 0.002606204 | I17: =E17-($P$13+$O$13*$B17) -> -0.031086833 | J17: =F17-($P$14+$O$14*$B17) -> -0.007427584 | N17: Var-Cov | O17: WARNER BROS DISCOVERY | P17: VISA 'A' | Q17: MICROCHIP TECH. | R17: CONOCOPHILLIPS
A18: ='2_CVaR_t2'!A18 -> 42314 | B18: ='2_CVaR_t2'!D18-1 -> -0.0040809003 | C18: ='Stocks Returns'!B14 -> -0.016943409 | D18: ='Stocks Returns'!C14 -> -0.0064345193 | E18: ='Stocks Returns'!D14 -> -0.0012523482 | F18: ='Stocks Returns'!E14 -> -0.0090618337 | G18: =C18-($P$11+$O$11*$B18) -> -0.012535074 | H18: =D18-($P$12+$O$12*$B18) -> -0.00038139395 | I18: =E18-($P$13+$O$13*$B18) -> 0.0048102949 | J18: =F18-($P$14+$O$14*$B18) -> -0.0048010586 | N18: WARNER BROS DISCOVERY | O18: =$O$11*$O$11*$N$5+$Q$11 -> 0.00082412363 | P18: =$O$11*$O$12*$N$5 -> 0.00015022741 | Q18: =$O$11*$O$13*$N$5 -> 0.0001506532 | R18: =$O$11*$O$14*$N$5 -> 0.00010596078
A19: ='2_CVaR_t2'!A19 -> 42317 | B19: ='2_CVaR_t2'!D19-1 -> -0.0056950067 | C19: ='Stocks Returns'!B15 -> -0.00034470872 | D19: ='Stocks Returns'!C15 -> -0.009015873 | E19: ='Stocks Returns'!D15 -> -0.00073145246 | F19: ='Stocks Returns'!E15 -> -0.020261789 | G19: =C19-($P$11+$O$11*$B19) -> 0.0056152881 | H19: =D19-($P$12+$O$12*$B19) -> -0.00058720679 | I19: =E19-($P$13+$O$13*$B19) -> 0.0077134647 | J19: =F19-($P$14+$O$14*$B19) -> -0.01432546 | N19: VISA 'A' | O19: =$O$12*$O$11*$N$5 -> 0.00015022741 | P19: =$O$12*$O$12*$N$5+$Q$12 -> 0.00023281894 | Q19: =$O$12*$O$13*$N$5 -> 0.00023064491 | R19: =$O$12*$O$14*$N$5 -> 0.00016222234
A20: ='2_CVaR_t2'!A20 -> 42318 | B20: ='2_CVaR_t2'!D20-1 -> 0.010867902 | C20: ='Stocks Returns'!B16 -> 0.036551724 | D20: ='Stocks Returns'!C16 -> 0.018452076 | E20: ='Stocks Returns'!D16 -> -0.01369863 | F20: ='Stocks Returns'!E16 -> 0.00018301611 | G20: =C20-($P$11+$O$11*$B20) -> 0.02658958 | H20: =D20-($P$12+$O$12*$B20) -> 0.002504488 | I20: =E20-($P$13+$O$13*$B20) -> -0.029699058 | J20: =F20-($P$14+$O$14*$B20) -> -0.011074101 | N20: MICROCHIP TECH. | O20: =$O$13*$O$11*$N$5 -> 0.0001506532 | P20: =$O$13*$O$12*$N$5 -> 0.00023064491 | Q20: =$O$13*$O$13*$N$5+$Q$13 -> 0.00063552559 | R20: =$O$13*$O$14*$N$5 -> 0.00016268214
A21: ='2_CVaR_t2'!A21 -> 42319 | B21: ='2_CVaR_t2'!D21-1 -> -0.0024474557 | C21: ='Stocks Returns'!B17 -> 0.01829674 | D21: ='Stocks Returns'!C17 -> -0.0037745345 | E21: ='Stocks Returns'!D17 -> -0.0012722646 | F21: ='Stocks Returns'!E17 -> -0.022140897 | G21: =C21-($P$11+$O$11*$B21) -> 0.021134824 | H21: =D21-($P$12+$O$12*$B21) -> -0.00012541072 | I21: =E21-($P$13+$O$13*$B21) -> 0.002379563 | J21: =F21-($P$14+$O$14*$B21) -> -0.01957575 | N21: CONOCOPHILLIPS | O21: =$O$14*$O$11*$N$5 -> 0.00010596078 | P21: =$O$14*$O$12*$N$5 -> 0.00016222234 | Q21: =$O$14*$O$13*$N$5 -> 0.00016268214 | R21: =$O$14*$O$14*$N$5+$Q$14 -> 0.00058605417
A22: ='2_CVaR_t2'!A22 -> 42320 | B22: ='2_CVaR_t2'!D22-1 -> -0.007712207 | C22: ='Stocks Returns'!B18 -> -0.014701078 | D22: ='Stocks Returns'!C18 -> -0.010987623 | E22: ='Stocks Returns'!D18 -> -0.015498938 | F22: ='Stocks Returns'!E18 -> -0.027507485 | G22: =C22-($P$11+$O$11*$B22) -> -0.0068019203 | H22: =D22-($P$12+$O$12*$B22) -> 0.00040983236 | I22: =E22-($P$13+$O$13*$B22) -> -0.0040768174 | J22: =F22-($P$14+$O$14*$B22) -> -0.019477162
A23: ='2_CVaR_t2'!A23 -> 42321 | B23: ='2_CVaR_t2'!D23-1 -> -0.0023901031 | C23: ='Stocks Returns'!B19 -> -0.0059681698 | D23: ='Stocks Returns'!C19 -> -0.0025539522 | E23: ='Stocks Returns'!D19 -> -0.015742937 | F23: ='Stocks Returns'!E19 -> -0.0026938618 | G23: =C23-($P$11+$O$11*$B23) -> -0.0031852199 | H23: =D23-($P$12+$O$12*$B23) -> 0.0010107635 | I23: =E23-($P$13+$O$13*$B23) -> -0.012175757 | J23: =F23-($P$14+$O$14*$B23) -> -0.00018825131 | M23: OPTIMAL MARKOWITZ PORTFOLIO (minimum variance for a fixed mean, no short selling)
A24: ='2_CVaR_t2'!A24 -> 42324 | B24: ='2_CVaR_t2'!D24-1 -> 0.0068261424 | C24: ='Stocks Returns'!B20 -> 0.020346898 | D24: ='Stocks Returns'!C20 -> 0.010113942 | E24: ='Stocks Returns'!D20 -> 0.0067922875 | F24: ='Stocks Returns'!E20 -> 0.049006367 | G24: =C24-($P$11+$O$11*$B24) -> 0.014270151 | H24: =D24-($P$12+$O$12*$B24) -> 0.00011476365 | I24: =E24-($P$13+$O$13*$B24) -> -0.0032428711 | J24: =F24-($P$14+$O$14*$B24) -> 0.041944876 | M24: Variable cells: weights in blue. Constraints: weights sum = 1; weights >= 0; expected return = N7. Objective: minimize O32.
A25: ='2_CVaR_t2'!A25 -> 42325 | B25: ='2_CVaR_t2'!D25-1 -> -0.00039662404 | C25: ='Stocks Returns'!B21 -> -0.016018307 | D25: ='Stocks Returns'!C21 -> -0.00088719899 | E25: ='Stocks Returns'!D21 -> 0.0028291621 | F25: ='Stocks Returns'!E21 -> -0.0086444731 | G25: =C25-($P$11+$O$11*$B25) -> -0.015151714 | H25: =D25-($P$12+$O$12*$B25) -> -0.00025636111 | I25: =E25-($P$13+$O$13*$B25) -> 0.003454149 | J25: =F25-($P$14+$O$14*$B25) -> -0.0082082319 | N25: Security | O25: Weight w | P25: E[R_i] | Q25: w x E[R_i] | R25: row i of Sigma %*% w
A26: ='2_CVaR_t2'!A26 -> 42326 | B26: ='2_CVaR_t2'!D26-1 -> 0.014009907 | C26: ='Stocks Returns'!B22 -> 0.022591362 | D26: ='Stocks Returns'!C22 -> 0.020677407 | E26: ='Stocks Returns'!D22 -> 0.01953125 | F26: ='Stocks Returns'!E22 -> 0.010760668 | G26: =C26-($P$11+$O$11*$B26) -> 0.0096087676 | H26: =D26-($P$12+$O$12*$B26) -> 0.00010561258 | I26: =E26-($P$13+$O$13*$B26) -> -0.0011064915 | J26: =F26-($P$14+$O$14*$B26) -> -0.0037580686 | N26: WARNER BROS DISCOVERY | O26: 0.84416403 | P26: =R11 -> 2.062798e-05 | Q26: =O26*P26 -> 1.7413399e-05 | R26: =SUMPRODUCT($O$26:$O$29,O$18:O$21) -> 0.00071220803
A27: ='2_CVaR_t2'!A27 -> 42327 | B27: ='2_CVaR_t2'!D27-1 -> -0.0021973197 | C27: ='Stocks Returns'!B23 -> -0.0071474984 | D27: ='Stocks Returns'!C23 -> -0.0038528461 | E27: ='Stocks Returns'!D23 -> 0.0042571307 | F27: ='Stocks Returns'!E23 -> -0.016886931 | G27: =C27-($P$11+$O$11*$B27) -> -0.0045498737 | H27: =D27-($P$12+$O$12*$B27) -> -0.00057185695 | I27: =E27-($P$13+$O$13*$B27) -> 0.0075397804 | J27: =F27-($P$14+$O$14*$B27) -> -0.014581443 | N27: VISA 'A' | O27: 0 | P27: =R12 -> 0.00072746619 | Q27: =O27*P27 -> 0 | R27: =SUMPRODUCT($O$26:$O$29,P$18:P$21) -> 0.00015209665
A28: ='2_CVaR_t2'!A28 -> 42328 | B28: ='2_CVaR_t2'!D28-1 -> 0.00053689701 | C28: ='Stocks Returns'!B24 -> 0.0068717277 | D28: ='Stocks Returns'!C24 -> 0.00049906425 | E28: ='Stocks Returns'!D24 -> 0.0042390844 | F28: ='Stocks Returns'!E24 -> -0.011762509 | G28: =C28-($P$11+$O$11*$B28) -> 0.0068409141 | H28: =D28-($P$12+$O$12*$B28) -> -0.00024399579 | I28: =E28-($P$13+$O$13*$B28) -> 0.0034862792 | J28: =F28-($P$14+$O$14*$B28) -> -0.012295328 | N28: MICROCHIP TECH. | O28: 1.5350728e-18 | P28: =R13 -> 0.00073716713 | Q28: =O28*P28 -> 1.1316052e-21 | R28: =SUMPRODUCT($O$26:$O$29,Q$18:Q$21) -> 0.00015252775
A29: ='2_CVaR_t2'!A29 -> 42331 | B29: ='2_CVaR_t2'!D29-1 -> -0.0014321253 | C29: ='Stocks Returns'!B25 -> -0.0019499513 | D29: ='Stocks Returns'!C25 -> -0.00099763063 | E29: ='Stocks Returns'!D25 -> -0.016462642 | F29: ='Stocks Returns'!E25 -> 0.0066125071 | G29: =C29-($P$11+$O$11*$B29) -> -8.7918029e-05 | H29: =D29-($P$12+$O$12*$B29) -> 0.0011571932 | I29: =E29-($P$13+$O$13*$B29) -> -0.01430935 | J29: =F29-($P$14+$O$14*$B29) -> 0.0081236702 | N29: CONOCOPHILLIPS | O29: 0.15583597 | P29: =R14 -> 0.00052181948 | Q29: =O29*P29 -> 8.1318246e-05 | R29: =SUMPRODUCT($O$26:$O$29,R$18:R$21) -> 0.0001807766
A30: ='2_CVaR_t2'!A30 -> 42332 | B30: ='2_CVaR_t2'!D30-1 -> -0.001678156 | C30: ='Stocks Returns'!B26 -> 0.007815044 | D30: ='Stocks Returns'!C26 -> -0.0039945076 | E30: ='Stocks Returns'!D26 -> 0.013519313 | F30: ='Stocks Returns'!E26 -> 0.038288288 | G30: =C30-($P$11+$O$11*$B30) -> 0.0099135897 | H30: =D30-($P$12+$O$12*$B30) -> -0.0014775911 | I30: =E30-($P$13+$O$13*$B30) -> 0.016035725 | J30: =F30-($P$14+$O$14*$B30) -> 0.040054848 | N30: Sum of weights | O30: =SUM(O26:O29) -> 1
A31: ='2_CVaR_t2'!A31 -> 42333 | B31: ='2_CVaR_t2'!D31-1 -> -0.0018993116 | C31: ='Stocks Returns'!B27 -> 0.0054927302 | D31: ='Stocks Returns'!C27 -> -0.0028825667 | E31: ='Stocks Returns'!D27 -> -0.0016938387 | F31: ='Stocks Returns'!E27 -> -0.016992046 | G31: =C31-($P$11+$O$11*$B31) -> 0.0078038758 | H31: =D31-($P$12+$O$12*$B31) -> -4.0167266e-05 | I31: =E31-($P$13+$O$13*$B31) -> 0.0011489782 | J31: =F31-($P$14+$O$14*$B31) -> -0.014995911 | N31: Expected portfolio return | O31: =SUM(Q26:Q29) -> 9.8731645e-05
A32: ='2_CVaR_t2'!A32 -> 42334 | B32: ='2_CVaR_t2'!D32-1 -> 3.1594126e-05 | C32: ='Stocks Returns'!B28 -> 0 | D32: ='Stocks Returns'!C28 -> 0 | E32: ='Stocks Returns'!D28 -> 0 | F32: ='Stocks Returns'!E28 -> 0 | G32: =C32-($P$11+$O$11*$B32) -> 0.00045494065 | H32: =D32-($P$12+$O$12*$B32) -> 6.1315237e-07 | I32: =E32-($P$13+$O$13*$B32) -> -7.0241384e-06 | J32: =F32-($P$14+$O$14*$B32) -> -8.2789822e-06 | N32: Portfolio variance w' Sigma w | O32: =SUMPRODUCT(O26:O29,R26:R29) -> 0.00062939189
A33: ='2_CVaR_t2'!A33 -> 42335 | B33: ='2_CVaR_t2'!D33-1 -> 0.0027904227 | C33: ='Stocks Returns'!B29 -> -0.001285347 | D33: ='Stocks Returns'!C29 -> 0.0035193565 | E33: ='Stocks Returns'!D29 -> 0.01145281 | F33: ='Stocks Returns'!E29 -> -0.016550202 | G33: =C33-($P$11+$O$11*$B33) -> -0.0034825043 | H33: =D33-($P$12+$O$12*$B33) -> -0.0005403018 | I33: =E33-($P$13+$O$13*$B33) -> 0.0073740063 | J33: =F33-($P$14+$O$14*$B33) -> -0.019422336 | N33: Daily standard deviation | O33: =SQRT(O32) -> 0.025087684
A34: ='2_CVaR_t2'!A34 -> 42338 | B34: ='2_CVaR_t2'!D34-1 -> -0.005807155 | C34: ='Stocks Returns'!B30 -> 0.0019305019 | D34: ='Stocks Returns'!C30 -> -0.010395792 | E34: ='Stocks Returns'!D30 -> 0.012371566 | F34: ='Stocks Returns'!E30 -> 0.01065819 | G34: =C34-($P$11+$O$11*$B34) -> 0.0079983084 | H34: =D34-($P$12+$O$12*$B34) -> -0.0018020725 | I34: =E34-($P$13+$O$13*$B34) -> 0.020982004 | J34: =F34-($P$14+$O$14*$B34) -> 0.016710937 | N34: Annualized standard deviation | O34: =O33*SQRT(252) -> 0.39825464
A35: ='2_CVaR_t2'!A35 -> 42339 | B35: ='2_CVaR_t2'!D35-1 -> 0.0074095371 | C35: ='Stocks Returns'!B31 -> -0.0019267823 | D35: ='Stocks Returns'!C31 -> 0.011390963 | E35: ='Stocks Returns'!D31 -> 0.0043496272 | F35: ='Stocks Returns'!E31 -> 0.010360777 | G35: =C35-($P$11+$O$11*$B35) -> -0.0085643545 | H35: =D35-($P$12+$O$12*$B35) -> 0.00053318113 | I35: =E35-($P$13+$O$13*$B35) -> -0.0065465688 | J35: =F35-($P$14+$O$14*$B35) -> 0.0026936822 | N35: Mean constraint check (should be 0) | O35: =O31-N7 -> 0
A36: ='2_CVaR_t2'!A36 -> 42340 | B36: ='2_CVaR_t2'!D36-1 -> -0.0088275017 | C36: ='Stocks Returns'!B32 -> -0.028957529 | D36: ='Stocks Returns'!C32 -> -0.010887248 | E36: ='Stocks Returns'!D32 -> -0.03773974 | F36: ='Stocks Returns'!E32 -> -0.037722029 | G36: =C36-($P$11+$O$11*$B36) -> -0.019986224 | H36: =D36-($P$12+$O$12*$B36) -> 0.0021516284 | I36: =E36-($P$13+$O$13*$B36) -> -0.024671546 | J36: =F36-($P$14+$O$14*$B36) -> -0.028533953
A37: ='2_CVaR_t2'!A37 -> 42341 | B37: ='2_CVaR_t2'!D37-1 -> -0.0062034593 | C37: ='Stocks Returns'!B33 -> -0.0019880716 | D37: ='Stocks Returns'!C33 -> -0.0094888664 | E37: ='Stocks Returns'!D33 -> -0.0049292756 | F37: ='Stocks Returns'!E33 -> -0.017887726 | G37: =C37-($P$11+$O$11*$B37) -> 0.0044607074 | H37: =D37-($P$12+$O$12*$B37) -> -0.00031189137 | I37: =E37-($P$13+$O$13*$B37) -> 0.0042660713 | J37: =F37-($P$14+$O$14*$B37) -> -0.011423588
A38: ='2_CVaR_t2'!A38 -> 42342 | B38: ='2_CVaR_t2'!D38-1 -> 0.017929465 | C38: ='Stocks Returns'!B34 -> 0.020252324 | D38: ='Stocks Returns'!C34 -> 0.026951079 | E38: ='Stocks Returns'!D34 -> 0.020245531 | F38: ='Stocks Returns'!E34 -> -0.0081379578 | G38: =C38-($P$11+$O$11*$B38) -> 0.0035018075 | H38: =D38-($P$12+$O$12*$B38) -> 0.00061072489 | I38: =E38-($P$13+$O$13*$B38) -> -0.0061771207 | J38: =F38-($P$14+$O$14*$B38) -> -0.026725467
A39: ='2_CVaR_t2'!A39 -> 42345 | B39: ='2_CVaR_t2'!D39-1 -> -0.0074393824 | C39: ='Stocks Returns'!B35 -> -0.00097624471 | D39: ='Stocks Returns'!C35 -> -0.010572139 | E39: ='Stocks Returns'!D35 -> -0.014566181 | F39: ='Stocks Returns'!E35 -> -0.042977144 | G39: =C39-($P$11+$O$11*$B39) -> 0.0066606433 | H39: =D39-($P$12+$O$12*$B39) -> 0.00042379009 | I39: =E39-($P$13+$O$13*$B39) -> -0.0035467243 | J39: =F39-($P$14+$O$14*$B39) -> -0.035230032
A40: ='2_CVaR_t2'!A40 -> 42346 | B40: ='2_CVaR_t2'!D40-1 -> -0.0042994644 | C40: ='Stocks Returns'!B36 -> -0.041368078 | D40: ='Stocks Returns'!C36 -> -0.0060339409 | E40: ='Stocks Returns'!D36 -> -0.010068552 | F40: ='Stocks Returns'!E36 -> -0.014084507 | G40: =C40-($P$11+$O$11*$B40) -> -0.036749634 | H40: =D40-($P$12+$O$12*$B40) -> 0.00034085345 | I40: =E40-($P$13+$O$13*$B40) -> -0.003683328 | J40: =F40-($P$14+$O$14*$B40) -> -0.0095968472
A41: ='2_CVaR_t2'!A41 -> 42347 | B41: ='2_CVaR_t2'!D41-1 -> -0.010164742 | C41: ='Stocks Returns'!B37 -> -0.033299354 | D41: ='Stocks Returns'!C37 -> -0.015049956 | E41: ='Stocks Returns'!D37 -> -0.015148236 | F41: ='Stocks Returns'!E37 -> 0.0035196687 | G41: =C41-($P$11+$O$11*$B41) -> -0.023042543 | H41: =D41-($P$12+$O$12*$B41) -> -4.3012797e-05 | I41: =E41-($P$13+$O$13*$B41) -> -0.00010639724 | J41: =F41-($P$14+$O$14*$B41) -> 0.014095893
A42: ='2_CVaR_t2'!A42 -> 42348 | B42: ='2_CVaR_t2'!D42-1 -> 0.0018131507 | C42: ='Stocks Returns'!B38 -> -0.0021089631 | D42: ='Stocks Returns'!C38 -> 0.0030816641 | E42: ='Stocks Returns'!D38 -> -0.0035157108 | F42: ='Stocks Returns'!E38 -> 0.015473489 | G42: =C42-($P$11+$O$11*$B42) -> -0.003366656 | H42: =D42-($P$12+$O$12*$B42) -> 0.00046029367 | I42: =E42-($P$13+$O$13*$B42) -> -0.0061521502 | J42: =F42-($P$14+$O$14*$B42) -> 0.013615831
A43: ='2_CVaR_t2'!A43 -> 42349 | B43: ='2_CVaR_t2'!D43-1 -> -0.016933358 | C43: ='Stocks Returns'!B39 -> -0.035928144 | D43: ='Stocks Returns'!C39 -> -0.025729647 | E43: ='Stocks Returns'!D39 -> -0.015656009 | F43: ='Stocks Returns'!E39 -> -0.022145469 | G43: =C43-($P$11+$O$11*$B43) -> -0.019164573 | H43: =D43-($P$12+$O$12*$B43) -> -0.00076107738 | I43: =E43-($P$13+$O$13*$B43) -> 0.0093756915 | J43: =F43-($P$14+$O$14*$B43) -> -0.0045429526
A44: ='2_CVaR_t2'!A44 -> 42352 | B44: ='2_CVaR_t2'!D44-1 -> 0.0063124544 | C44: ='Stocks Returns'!B40 -> -0.033613445 | D44: ='Stocks Returns'!C40 -> 0.0099855472 | E44: ='Stocks Returns'!D40 -> -0.00067204301 | F44: ='Stocks Returns'!E40 -> 0.029087887 | G44: =C44-($P$11+$O$11*$B44) -> -0.039196378 | H44: =D44-($P$12+$O$12*$B44) -> 0.00074238295 | I44: =E44-($P$13+$O$13*$B44) -> -0.0099490448 | J44: =F44-($P$14+$O$14*$B44) -> 0.02255964
A45: ='2_CVaR_t2'!A45 -> 42353 | B45: ='2_CVaR_t2'!D45-1 -> 0.016024925 | C45: ='Stocks Returns'!B41 -> 0.0026465028 | D45: ='Stocks Returns'!C41 -> 0.022765708 | E45: ='Stocks Returns'!D41 -> 0.032728088 | F45: ='Stocks Returns'!E41 -> 0.020795477 | G45: =C45-($P$11+$O$11*$B45) -> -0.012273154 | H45: =D45-($P$12+$O$12*$B45) -> -0.00077166234 | I45: =E45-($P$13+$O$13*$B45) -> 0.0091163647 | J45: =F45-($P$14+$O$14*$B45) -> 0.0041850136
A46: ='2_CVaR_t2'!A46 -> 42354 | B46: ='2_CVaR_t2'!D46-1 -> 0.011018356 | C46: ='Stocks Returns'!B42 -> 0.024886878 | D46: ='Stocks Returns'!C42 -> 0.015772068 | E46: ='Stocks Returns'!D42 -> 0.022574343 | F46: ='Stocks Returns'!E42 -> -0.023931962 | G46: =C46-($P$11+$O$11*$B46) -> 0.0147801 | H46: =D46-($P$12+$O$12*$B46) -> -0.00039694855 | I46: =E46-($P$13+$O$13*$B46) -> 0.0063518587 | J46: =F46-($P$14+$O$14*$B46) -> -0.035345261
A47: ='2_CVaR_t2'!A47 -> 42355 | B47: ='2_CVaR_t2'!D47-1 -> -0.0099714055 | C47: ='Stocks Returns'!B43 -> -0.025754231 | D47: ='Stocks Returns'!C43 -> -0.014650639 | E47: ='Stocks Returns'!D43 -> -0.014222034 | F47: ='Stocks Returns'!E43 -> -0.041945289 | G47: =C47-($P$11+$O$11*$B47) -> -0.015683276 | H47: =D47-($P$12+$O$12*$B47) -> 7.1764e-05 | I47: =E47-($P$13+$O$13*$B47) -> 0.00053445872 | J47: =F47-($P$14+$O$14*$B47) -> -0.031569761
... A2524: ='2_CVaR_t2'!A2524 -> 45824 | B2524: ='2_CVaR_t2'!D2524-1 -> 0.0065921499 | C2524: ='Stocks Returns'!B2520 -> 0.072781655 | D2524: ='Stocks Returns'!C2520 -> 0.0074533067 | E2524: ='Stocks Returns'!D2520 -> 0.037425833 | F2524: ='Stocks Returns'!E2520 -> -0.020214521 | G2524: =C2524-($P$11+$O$11*$B2524) -> 0.066929848 | H2524: =D2524-($P$12+$O$12*$B2524) -> -0.002201496 | I2524: =E2524-($P$13+$O$13*$B2524) -> 0.027736026 | J2524: =F2524-($P$14+$O$14*$B2524) -> -0.027033112

Sheet 3_SIM_t3
A2: POINT 3 - Single Index Model and Markowitz portfolio - rebalancing 3 (15/07/2025)
M3: MARKET PARAMETERS
M4: E[Rm] daily | N4: =AVERAGE($B$6:$B$2545) -> 0.00051246217
A5: Date | B5: R index (market) | C5: WARNER BROS DISCOVERY | D5: VISA 'A' | E5: MICROCHIP TECH. | F5: CONOCOPHILLIPS | G5: residual 1 | H5: residual 2 | I5: residual 3 | J5: residual 4 | M5: Var(Rm) (population variance) | N5: =VARP($B$6:$B$2545) -> 0.00010249058
A6: ='2_CVaR_t3'!A6 -> 42298 | B6: ='2_CVaR_t3'!D6-1 -> -0.0066350761 | C6: ='Stocks Returns'!B2 -> -0.012679918 | D6: ='Stocks Returns'!C2 -> -0.010749869 | E6: ='Stocks Returns'!D2 -> -0.0050632911 | F6: ='Stocks Returns'!E2 -> -0.010646246 | G6: =C6-($P$11+$O$11*$B6) -> -0.005537583 | H6: =D6-($P$12+$O$12*$B6) -> -0.00087408139 | I6: =E6-($P$13+$O$13*$B6) -> 0.0058719108 | J6: =F6-($P$14+$O$14*$B6) -> -0.0035910202 | M6: Daily risk-free rate rf | N6: ='2_CVaR_t3'!H13 -> 0.00010065704
A7: ='2_CVaR_t3'!A7 -> 42299 | B7: ='2_CVaR_t3'!D7-1 -> 0.010519304 | C7: ='Stocks Returns'!B3 -> 0.022214509 | D7: ='Stocks Returns'!C3 -> 0.012721972 | E7: ='Stocks Returns'!D3 -> 0.036047498 | F7: ='Stocks Returns'!E3 -> 0.030394563 | G7: =C7-($P$11+$O$11*$B7) -> 0.012057192 | H7: =D7-($P$12+$O$12*$B7) -> -0.0028156634 | I7: =E7-($P$13+$O$13*$B7) -> 0.018915086 | J7: =F7-($P$14+$O$14*$B7) -> 0.019296706 | M7: Target return of the Markowitz portfolio (= daily rf) | N7: =N6 -> 0.00010065704
A8: ='2_CVaR_t3'!A8 -> 42300 | B8: ='2_CVaR_t3'!D8-1 -> 0.0054059196 | C8: ='Stocks Returns'!B4 -> 0.010865874 | D8: ='Stocks Returns'!C4 -> 0.0085056268 | E8: ='Stocks Returns'!D4 -> 0.0051166598 | F8: ='Stocks Returns'!E4 -> 0.00054965189 | G8: =C8-($P$11+$O$11*$B8) -> 0.0058652445 | H8: =D8-($P$12+$O$12*$B8) -> 0.00054323475 | I8: =E8-($P$13+$O$13*$B8) -> -0.0036493466 | J8: =F8-($P$14+$O$14*$B8) -> -0.0051371273
A9: ='2_CVaR_t3'!A9 -> 42303 | B9: ='2_CVaR_t3'!D9-1 -> 0.0073285373 | C9: ='Stocks Returns'!B5 -> -0.016123614 | D9: ='Stocks Returns'!C5 -> 0.014402491 | E9: ='Stocks Returns'!D5 -> -0.012217471 | F9: ='Stocks Returns'!E5 -> -0.030397363 | G9: =C9-($P$11+$O$11*$B9) -> -0.023063144 | H9: =D9-($P$12+$O$12*$B9) -> 0.0035918297 | I9: =E9-($P$13+$O$13*$B9) -> -0.024129222 | J9: =F9-($P$14+$O$14*$B9) -> -0.038118692 | M9: OLS ESTIMATES OF THE SINGLE INDEX MODEL: R_i = alpha_i + beta_i * R_m + eps_i
A10: ='2_CVaR_t3'!A10 -> 42304 | B10: ='2_CVaR_t3'!D10-1 -> -0.005892048 | C10: ='Stocks Returns'!B6 -> -0.017412086 | D10: ='Stocks Returns'!C6 -> -0.0084420568 | E10: ='Stocks Returns'!D6 -> -0.011956298 | F10: ='Stocks Returns'!E6 -> -0.023796034 | G10: =C10-($P$11+$O$11*$B10) -> -0.011019072 | H10: =D10-($P$12+$O$12*$B10) -> 0.00033296898 | I10: =E10-($P$13+$O$13*$B10) -> -0.0022368216 | J10: =F10-($P$14+$O$14*$B10) -> -0.017527094 | N10: Security | O10: beta | P10: alpha | Q10: var(eps_i) | R10: E[R_i] = alpha + beta*E[Rm]
A11: ='2_CVaR_t3'!A11 -> 42305 | B11: ='2_CVaR_t3'!D11-1 -> 0.011263382 | C11: ='Stocks Returns'!B7 -> 0.026059764 | D11: ='Stocks Returns'!C7 -> 0.017414861 | E11: ='Stocks Returns'!D7 -> 0.013144169 | F11: ='Stocks Returns'!E7 -> 0.031921068 | G11: =C11-($P$11+$O$11*$B11) -> 0.015152068 | H11: =D11-($P$12+$O$12*$B11) -> 0.00077490858 | I11: =E11-($P$13+$O$13*$B11) -> -0.0052056869 | J11: =F11-($P$14+$O$14*$B11) -> 0.020035814 | N11: WARNER BROS DISCOVERY | O11: =SLOPE(C$6:C$2545,$B$6:$B$2545) -> 1.0084685 | P11: =INTERCEPT(C$6:C$2545,$B$6:$B$2545) -> -0.00045106965 | Q11: =VARP(G$6:G$2545) -> 0.00071577105 | R11: =P11+O11*$N$4 -> 6.5732292e-05
A12: ='2_CVaR_t3'!A12 -> 42306 | B12: ='2_CVaR_t3'!D12-1 -> -0.0046915911 | C12: ='Stocks Returns'!B8 -> -0.0054182188 | D12: ='Stocks Returns'!C8 -> -0.0045644732 | E12: ='Stocks Returns'!D8 -> -0.024093904 | F12: ='Stocks Returns'!E8 -> 0.0052493438 | G12: =C12-($P$11+$O$11*$B12) -> -0.00023582731 | H12: =D12-($P$12+$O$12*$B12) -> 0.0024321311 | I12: =E12-($P$13+$O$13*$B12) -> -0.016338589 | J12: =F12-($P$14+$O$14*$B12) -> 0.010247938 | N12: VISA 'A' | O12: =SLOPE(D$6:D$2545,$B$6:$B$2545) -> 1.4814539 | P12: =INTERCEPT(D$6:D$2545,$B$6:$B$2545) -> -4.6228437e-05 | Q12: =VARP(H$6:H$2545) -> 7.9276356e-06 | R12: =P12+O12*$N$4 -> 0.00071296062
A13: ='2_CVaR_t3'!A13 -> 42307 | B13: ='2_CVaR_t3'!D13-1 -> -0.0051945229 | C13: ='Stocks Returns'!B9 -> 0.0023833844 | D13: ='Stocks Returns'!C9 -> -0.011845625 | E13: ='Stocks Returns'!D9 -> 0.018991348 | F13: ='Stocks Returns'!E9 -> -0.0050354345 | G13: =C13-($P$11+$O$11*$B13) -> 0.0080729667 | H13: =D13-($P$12+$O$12*$B13) -> -0.0041039503 | I13: =E13-($P$13+$O$13*$B13) -> 0.027569549 | J13: =F13-($P$14+$O$14*$B13) -> 0.000495371 | N13: MICROCHIP TECH. | O13: =SLOPE(E$6:E$2545,$B$6:$B$2545) -> 1.6361777 | P13: =INTERCEPT(E$6:E$2545,$B$6:$B$2545) -> -7.9038543e-05 | Q13: =VARP(I$6:I$2545) -> 0.0003577658 | R13: =P13+O13*$N$4 -> 0.00075944062
A14: ='2_CVaR_t3'!A14 -> 42310 | B14: ='2_CVaR_t3'!D14-1 -> -0.016528965 | C14: ='Stocks Returns'!B10 -> 0.021059783 | D14: ='Stocks Returns'!C10 -> -0.030420211 | E14: ='Stocks Returns'!D10 -> 0.012424933 | F14: ='Stocks Returns'!E10 -> 0.029803187 | G14: =C14-($P$11+$O$11*$B14) -> 0.038179793 | H14: =D14-($P$12+$O$12*$B14) -> -0.0058870835 | I14: =E14-($P$13+$O$13*$B14) -> 0.039548295 | J14: =F14-($P$14+$O$14*$B14) -> 0.047328309 | N14: CONOCOPHILLIPS | O14: =SLOPE(F$6:F$2545,$B$6:$B$2545) -> 1.0582185 | P14: =INTERCEPT(F$6:F$2545,$B$6:$B$2545) -> -3.3865153e-05 | Q14: =VARP(J$6:J$2545) -> 0.00046887996 | R14: =P14+O14*$N$4 -> 0.00050843181
A15: ='2_CVaR_t3'!A15 -> 42311 | B15: ='2_CVaR_t3'!D15-1 -> 0.020564309 | C15: ='Stocks Returns'!B11 -> 0.033932136 | D15: ='Stocks Returns'!C11 -> 0.035628822 | E15: ='Stocks Returns'!D11 -> -0.0014317856 | F15: ='Stocks Returns'!E11 -> 0.032580997 | G15: =C15-($P$11+$O$11*$B15) -> 0.013644748 | H15: =D15-($P$12+$O$12*$B15) -> 0.0052099751 | I15: =E15-($P$13+$O$13*$B15) -> -0.034999611 | J15: =F15-($P$14+$O$14*$B15) -> 0.010853329
A16: ='2_CVaR_t3'!A16 -> 42312 | B16: ='2_CVaR_t3'!D16-1 -> 0.0036828618 | C16: ='Stocks Returns'!B12 -> -0.025096525 | D16: ='Stocks Returns'!C12 -> 0.0057766367 | E16: ='Stocks Returns'!D12 -> 0.0034821794 | F16: ='Stocks Returns'!E12 -> -0.0068746695 | G16: =C16-($P$11+$O$11*$B16) -> -0.028359505 | H16: =D16-($P$12+$O$12*$B16) -> 0.00036687537 | I16: =E16-($P$13+$O$13*$B16) -> -0.0024645982 | J16: =F16-($P$14+$O$14*$B16) -> -0.010738077
A17: ='2_CVaR_t3'!A17 -> 42313 | B17: ='2_CVaR_t3'!D17-1 -> 0.0048642676 | C17: ='Stocks Returns'!B13 -> -0.026072607 | D17: ='Stocks Returns'!C13 -> 0.01161455 | E17: ='Stocks Returns'!D13 -> -0.022045315 | F17: ='Stocks Returns'!E13 -> -0.0010649627 | G17: =C17-($P$11+$O$11*$B17) -> -0.030526998 | H17: =D17-($P$12+$O$12*$B17) -> 0.0044545905 | I17: =E17-($P$13+$O$13*$B17) -> -0.029925083 | J17: =F17-($P$14+$O$14*$B17) -> -0.0061785557 | N17: Var-Cov | O17: WARNER BROS DISCOVERY | P17: VISA 'A' | Q17: MICROCHIP TECH. | R17: CONOCOPHILLIPS
A18: ='2_CVaR_t3'!A18 -> 42314 | B18: ='2_CVaR_t3'!D18-1 -> -0.0038045805 | C18: ='Stocks Returns'!B14 -> -0.016943409 | D18: ='Stocks Returns'!C14 -> -0.0064345193 | E18: ='Stocks Returns'!D14 -> -0.0012523482 | F18: ='Stocks Returns'!E14 -> -0.0090618337 | G18: =C18-($P$11+$O$11*$B18) -> -0.01265554 | H18: =D18-($P$12+$O$12*$B18) -> -0.00075198044 | I18: =E18-($P$13+$O$13*$B18) -> 0.00505166 | J18: =F18-($P$14+$O$14*$B18) -> -0.005001891 | N18: WARNER BROS DISCOVERY | O18: =$O$11*$O$11*$N$5+$Q$11 -> 0.00082000486 | P18: =$O$11*$O$12*$N$5 -> 0.00015312088 | Q18: =$O$11*$O$13*$N$5 -> 0.00016911291 | R18: =$O$11*$O$14*$N$5 -> 0.0001093759
A19: ='2_CVaR_t3'!A19 -> 42317 | B19: ='2_CVaR_t3'!D19-1 -> -0.0052560567 | C19: ='Stocks Returns'!B15 -> -0.00034470872 | D19: ='Stocks Returns'!C15 -> -0.009015873 | E19: ='Stocks Returns'!D15 -> -0.00073145246 | F19: ='Stocks Returns'!E15 -> -0.020261789 | G19: =C19-($P$11+$O$11*$B19) -> 0.0054069285 | H19: =D19-($P$12+$O$12*$B19) -> -0.001183039 | I19: =E19-($P$13+$O$13*$B19) -> 0.0079474288 | J19: =F19-($P$14+$O$14*$B19) -> -0.014665868 | N19: VISA 'A' | O19: =$O$12*$O$11*$N$5 -> 0.00015312088 | P19: =$O$12*$O$12*$N$5+$Q$12 -> 0.00023286429 | Q19: =$O$12*$O$13*$N$5 -> 0.00024842916 | R19: =$O$12*$O$14*$N$5 -> 0.00016067469
A20: ='2_CVaR_t3'!A20 -> 42318 | B20: ='2_CVaR_t3'!D20-1 -> 0.0095482911 | C20: ='Stocks Returns'!B16 -> 0.036551724 | D20: ='Stocks Returns'!C16 -> 0.018452076 | E20: ='Stocks Returns'!D16 -> -0.01369863 | F20: ='Stocks Returns'!E16 -> 0.00018301611 | G20: =C20-($P$11+$O$11*$B20) -> 0.027373643 | H20: =D20-($P$12+$O$12*$B20) -> 0.0043529516 | I20: =E20-($P$13+$O$13*$B20) -> -0.029242292 | J20: =F20-($P$14+$O$14*$B20) -> -0.0098872973 | N20: MICROCHIP TECH. | O20: =$O$13*$O$11*$N$5 -> 0.00016911291 | P20: =$O$13*$O$12*$N$5 -> 0.00024842916 | Q20: =$O$13*$O$13*$N$5+$Q$13 -> 0.00063214103 | R20: =$O$13*$O$14*$N$5 -> 0.00017745563
A21: ='2_CVaR_t3'!A21 -> 42319 | B21: ='2_CVaR_t3'!D21-1 -> -0.0022642898 | C21: ='Stocks Returns'!B17 -> 0.01829674 | D21: ='Stocks Returns'!C17 -> -0.0037745345 | E21: ='Stocks Returns'!D17 -> -0.0012722646 | F21: ='Stocks Returns'!E17 -> -0.022140897 | G21: =C21-($P$11+$O$11*$B21) -> 0.021031274 | H21: =D21-($P$12+$O$12*$B21) -> -0.00037386517 | I21: =E21-($P$13+$O$13*$B21) -> 0.0025115543 | J21: =F21-($P$14+$O$14*$B21) -> -0.019710918 | N21: CONOCOPHILLIPS | O21: =$O$14*$O$11*$N$5 -> 0.0001093759 | P21: =$O$14*$O$12*$N$5 -> 0.00016067469 | Q21: =$O$14*$O$13*$N$5 -> 0.00017745563 | R21: =$O$14*$O$14*$N$5+$Q$14 -> 0.00058365163
A22: ='2_CVaR_t3'!A22 -> 42320 | B22: ='2_CVaR_t3'!D22-1 -> -0.0076734367 | C22: ='Stocks Returns'!B18 -> -0.014701078 | D22: ='Stocks Returns'!C18 -> -0.010987623 | E22: ='Stocks Returns'!D18 -> -0.015498938 | F22: ='Stocks Returns'!E18 -> -0.027507485 | G22: =C22-($P$11+$O$11*$B22) -> -0.0065115894 | H22: =D22-($P$12+$O$12*$B22) -> 0.00042644775 | I22: =E22-($P$13+$O$13*$B22) -> -0.002864794 | J22: =F22-($P$14+$O$14*$B22) -> -0.019353447
A23: ='2_CVaR_t3'!A23 -> 42321 | B23: ='2_CVaR_t3'!D23-1 -> -0.0028054421 | C23: ='Stocks Returns'!B19 -> -0.0059681698 | D23: ='Stocks Returns'!C19 -> -0.0025539522 | E23: ='Stocks Returns'!D19 -> -0.015742937 | F23: ='Stocks Returns'!E19 -> -0.0026938618 | G23: =C23-($P$11+$O$11*$B23) -> -0.0026879001 | H23: =D23-($P$12+$O$12*$B23) -> 0.0016484093 | I23: =E23-($P$13+$O$13*$B23) -> -0.011073697 | J23: =F23-($P$14+$O$14*$B23) -> 0.00030877417 | M23: OPTIMAL MARKOWITZ PORTFOLIO (minimum variance for a fixed mean, no short selling)
A24: ='2_CVaR_t3'!A24 -> 42324 | B24: ='2_CVaR_t3'!D24-1 -> 0.0064828661 | C24: ='Stocks Returns'!B20 -> 0.020346898 | D24: ='Stocks Returns'!C20 -> 0.010113942 | E24: ='Stocks Returns'!D20 -> 0.0067922875 | F24: ='Stocks Returns'!E20 -> 0.049006367 | G24: =C24-($P$11+$O$11*$B24) -> 0.014260201 | H24: =D24-($P$12+$O$12*$B24) -> 0.00055610327 | I24: =E24-($P$13+$O$13*$B24) -> -0.0037357949 | J24: =F24-($P$14+$O$14*$B24) -> 0.042179943 | M24: Variable cells: weights in blue. Constraints: weights sum = 1; weights >= 0; expected return = N7. Objective: minimize O32.
A25: ='2_CVaR_t3'!A25 -> 42325 | B25: ='2_CVaR_t3'!D25-1 -> -0.00023655565 | C25: ='Stocks Returns'!B21 -> -0.016018307 | D25: ='Stocks Returns'!C21 -> -0.00088719899 | E25: ='Stocks Returns'!D21 -> 0.0028291621 | F25: ='Stocks Returns'!E21 -> -0.0086444731 | G25: =C25-($P$11+$O$11*$B25) -> -0.015328678 | H25: =D25-($P$12+$O$12*$B25) -> -0.00049052427 | I25: =E25-($P$13+$O$13*$B25) -> 0.0032952478 | J25: =F25-($P$14+$O$14*$B25) -> -0.0083602803 | N25: Security | O25: Weight w | P25: E[R_i] | Q25: w x E[R_i] | R25: row i of Sigma %*% w
A26: ='2_CVaR_t3'!A26 -> 42326 | B26: ='2_CVaR_t3'!D26-1 -> 0.013705866 | C26: ='Stocks Returns'!B22 -> 0.022591362 | D26: ='Stocks Returns'!C22 -> 0.020677407 | E26: ='Stocks Returns'!D22 -> 0.01953125 | F26: ='Stocks Returns'!E22 -> 0.010760668 | G26: =C26-($P$11+$O$11*$B26) -> 0.0092204978 | H26: =D26-($P$12+$O$12*$B26) -> 0.00041902714 | I26: =E26-($P$13+$O$13*$B26) -> -0.0028149438 | J26: =F26-($P$14+$O$14*$B26) -> -0.0037092685 | N26: WARNER BROS DISCOVERY | O26: 0.92110958 | P26: =R11 -> 6.5732292e-05 | Q26: =O26*P26 -> 6.0546644e-05 | R26: =SUMPRODUCT($O$26:$O$29,O$18:O$21) -> 0.00076394305
A27: ='2_CVaR_t3'!A27 -> 42327 | B27: ='2_CVaR_t3'!D27-1 -> -0.0018325343 | C27: ='Stocks Returns'!B23 -> -0.0071474984 | D27: ='Stocks Returns'!C23 -> -0.0038528461 | E27: ='Stocks Returns'!D23 -> 0.0042571307 | F27: ='Stocks Returns'!E23 -> -0.016886931 | G27: =C27-($P$11+$O$11*$B27) -> -0.0048483757 | H27: =D27-($P$12+$O$12*$B27) -> -0.0010918027 | I27: =E27-($P$13+$O$13*$B27) -> 0.0073345209 | J27: =F27-($P$14+$O$14*$B27) -> -0.014913844 | N27: VISA 'A' | O27: 0 | P27: =R12 -> 0.00071296062 | Q27: =O27*P27 -> 0 | R27: =SUMPRODUCT($O$26:$O$29,P$18:P$21) -> 0.00015371681
A28: ='2_CVaR_t3'!A28 -> 42328 | B28: ='2_CVaR_t3'!D28-1 -> 0.0006887373 | C28: ='Stocks Returns'!B24 -> 0.0068717277 | D28: ='Stocks Returns'!C24 -> 0.00049906425 | E28: ='Stocks Returns'!D24 -> 0.0042390844 | F28: ='Stocks Returns'!E24 -> -0.011762509 | G28: =C28-($P$11+$O$11*$B28) -> 0.0066282275 | H28: =D28-($P$12+$O$12*$B28) -> -0.00047503984 | I28: =E28-($P$13+$O$13*$B28) -> 0.0031912263 | J28: =F28-($P$14+$O$14*$B28) -> -0.012457479 | N28: MICROCHIP TECH. | O28: 9.9609673e-19 | P28: =R13 -> 0.00075944062 | Q28: =O28*P28 -> 7.5647632e-22 | R28: =SUMPRODUCT($O$26:$O$29,Q$18:Q$21) -> 0.00016977107
A29: ='2_CVaR_t3'!A29 -> 42331 | B29: ='2_CVaR_t3'!D29-1 -> -0.0019653393 | C29: ='Stocks Returns'!B25 -> -0.0019499513 | D29: ='Stocks Returns'!C25 -> -0.00099763063 | E29: ='Stocks Returns'!D25 -> -0.016462642 | F29: ='Stocks Returns'!E25 -> 0.0066125071 | G29: =C29-($P$11+$O$11*$B29) -> 0.0004831011 | H29: =D29-($P$12+$O$12*$B29) -> 0.0019601573 | I29: =E29-($P$13+$O$13*$B29) -> -0.01316796 | J29: =F29-($P$14+$O$14*$B29) -> 0.0087261307 | N29: CONOCOPHILLIPS | O29: 0.078890419 | P29: =R14 -> 0.00050843181 | Q29: =O29*P29 -> 4.0110399e-05 | R29: =SUMPRODUCT($O$26:$O$29,R$18:R$21) -> 0.00014679172
A30: ='2_CVaR_t3'!A30 -> 42332 | B30: ='2_CVaR_t3'!D30-1 -> -0.0011153861 | C30: ='Stocks Returns'!B26 -> 0.007815044 | D30: ='Stocks Returns'!C26 -> -0.0039945076 | E30: ='Stocks Returns'!D26 -> 0.013519313 | F30: ='Stocks Returns'!E26 -> 0.038288288 | G30: =C30-($P$11+$O$11*$B30) -> 0.0093909453 | H30: =D30-($P$12+$O$12*$B30) -> -0.0022958861 | I30: =E30-($P$13+$O$13*$B30) -> 0.015423322 | J30: =F30-($P$14+$O$14*$B30) -> 0.039502476 | N30: Sum of weights | O30: =SUM(O26:O29) -> 1
A31: ='2_CVaR_t3'!A31 -> 42333 | B31: ='2_CVaR_t3'!D31-1 -> -0.00178359 | C31: ='Stocks Returns'!B27 -> 0.0054927302 | D31: ='Stocks Returns'!C27 -> -0.0028825667 | E31: ='Stocks Returns'!D27 -> -0.0016938387 | F31: ='Stocks Returns'!E27 -> -0.016992046 | G31: =C31-($P$11+$O$11*$B31) -> 0.0077424941 | H31: =D31-($P$12+$O$12*$B31) -> -0.00019403205 | I31: =E31-($P$13+$O$13*$B31) -> 0.00130347 | J31: =F31-($P$14+$O$14*$B31) -> -0.015070753 | N31: Expected portfolio return | O31: =SUM(Q26:Q29) -> 0.00010065704
A32: ='2_CVaR_t3'!A32 -> 42334 | B32: ='2_CVaR_t3'!D32-1 -> 3.3619452e-05 | C32: ='Stocks Returns'!B28 -> 0 | D32: ='Stocks Returns'!C28 -> 0 | E32: ='Stocks Returns'!D28 -> 0 | F32: ='Stocks Returns'!E28 -> 0 | G32: =C32-($P$11+$O$11*$B32) -> 0.0004171655 | H32: =D32-($P$12+$O$12*$B32) -> -3.5772303e-06 | I32: =E32-($P$13+$O$13*$B32) -> 2.4031145e-05 | J32: =F32-($P$14+$O$14*$B32) -> -1.7115738e-06 | N32: Portfolio variance w' Sigma w | O32: =SUMPRODUCT(O26:O29,R26:R29) -> 0.00071525572
A33: ='2_CVaR_t3'!A33 -> 42335 | B33: ='2_CVaR_t3'!D33-1 -> 0.0030621198 | C33: ='Stocks Returns'!B29 -> -0.001285347 | D33: ='Stocks Returns'!C29 -> 0.0035193565 | E33: ='Stocks Returns'!D29 -> 0.01145281 | F33: ='Stocks Returns'!E29 -> -0.016550202 | G33: =C33-($P$11+$O$11*$B33) -> -0.0039223287 | H33: =D33-($P$12+$O$12*$B33) -> -0.00097080429 | I33: =E33-($P$13+$O$13*$B33) -> 0.0065216767 | J33: =F33-($P$14+$O$14*$B33) -> -0.019756729 | N33: Daily standard deviation | O33: =SQRT(O32) -> 0.026744265
A34: ='2_CVaR_t3'!A34 -> 42338 | B34: ='2_CVaR_t3'!D34-1 -> -0.0049252928 | C34: ='Stocks Returns'!B30 -> 0.0019305019 | D34: ='Stocks Returns'!C30 -> -0.010395792 | E34: ='Stocks Returns'!D30 -> 0.012371566 | F34: ='Stocks Returns'!E30 -> 0.01065819 | G34: =C34-($P$11+$O$11*$B34) -> 0.0073485742 | H34: =D34-($P$12+$O$12*$B34) -> -0.003052969 | I34: =E34-($P$13+$O$13*$B34) -> 0.020509259 | J34: =F34-($P$14+$O$14*$B34) -> 0.015904091 | N34: Annualized standard deviation | O34: =O33*SQRT(252) -> 0.42455205
A35: ='2_CVaR_t3'!A35 -> 42339 | B35: ='2_CVaR_t3'!D35-1 -> 0.0070123763 | C35: ='Stocks Returns'!B31 -> -0.0019267823 | D35: ='Stocks Returns'!C31 -> 0.011390963 | E35: ='Stocks Returns'!D31 -> 0.0043496272 | F35: ='Stocks Returns'!E31 -> 0.010360777 | G35: =C35-($P$11+$O$11*$B35) -> -0.0085474731 | H35: =D35-($P$12+$O$12*$B35) -> 0.0010486796 | I35: =E35-($P$13+$O$13*$B35) -> -0.007044828 | J35: =F35-($P$14+$O$14*$B35) -> 0.0029740156 | N35: Mean constraint check (should be 0) | O35: =O31-N7 -> 1.6263033e-19
A36: ='2_CVaR_t3'!A36 -> 42340 | B36: ='2_CVaR_t3'!D36-1 -> -0.009534495 | C36: ='Stocks Returns'!B32 -> -0.028957529 | D36: ='Stocks Returns'!C32 -> -0.010887248 | E36: ='Stocks Returns'!D32 -> -0.03773974 | F36: ='Stocks Returns'!E32 -> -0.037722029 | G36: =C36-($P$11+$O$11*$B36) -> -0.018891222 | H36: =D36-($P$12+$O$12*$B36) -> 0.0032838947 | I36: =E36-($P$13+$O$13*$B36) -> -0.022060574 | J36: =F36-($P$14+$O$14*$B36) -> -0.027598585
A37: ='2_CVaR_t3'!A37 -> 42341 | B37: ='2_CVaR_t3'!D37-1 -> -0.0058925005 | C37: ='Stocks Returns'!B33 -> -0.0019880716 | D37: ='Stocks Returns'!C33 -> -0.0094888664 | E37: ='Stocks Returns'!D33 -> -0.0049292756 | F37: ='Stocks Returns'!E33 -> -0.017887726 | G37: =C37-($P$11+$O$11*$B37) -> 0.0044053991 | H37: =D37-($P$12+$O$12*$B37) -> -0.00071317027 | I37: =E37-($P$13+$O$13*$B37) -> 0.0047909408 | J37: =F37-($P$14+$O$14*$B37) -> -0.011618308
A38: ='2_CVaR_t3'!A38 -> 42342 | B38: ='2_CVaR_t3'!D38-1 -> 0.01740439 | C38: ='Stocks Returns'!B34 -> 0.020252324 | D38: ='Stocks Returns'!C34 -> 0.026951079 | E38: ='Stocks Returns'!D34 -> 0.020245531 | F38: ='Stocks Returns'!E34 -> -0.0081379578 | G38: =C38-($P$11+$O$11*$B38) -> 0.0031516148 | H38: =D38-($P$12+$O$12*$B38) -> 0.0012135068 | I38: =E38-($P$13+$O$13*$B38) -> -0.0081521053 | J38: =F38-($P$14+$O$14*$B38) -> -0.026521741
A39: ='2_CVaR_t3'!A39 -> 42345 | B39: ='2_CVaR_t3'!D39-1 -> -0.0073520869 | C39: ='Stocks Returns'!B35 -> -0.00097624471 | D39: ='Stocks Returns'!C35 -> -0.010572139 | E39: ='Stocks Returns'!D35 -> -0.014566181 | F39: ='Stocks Returns'!E35 -> -0.042977144 | G39: =C39-($P$11+$O$11*$B39) -> 0.0068891729 | H39: =D39-($P$12+$O$12*$B39) -> 0.00036586668 | I39: =E39-($P$13+$O$13*$B39) -> -0.0024578221 | J39: =F39-($P$14+$O$14*$B39) -> -0.035163164
A40: ='2_CVaR_t3'!A40 -> 42346 | B40: ='2_CVaR_t3'!D40-1 -> -0.0043331476 | C40: ='Stocks Returns'!B36 -> -0.041368078 | D40: ='Stocks Returns'!C36 -> -0.0060339409 | E40: ='Stocks Returns'!D36 -> -0.010068552 | F40: ='Stocks Returns'!E36 -> -0.014084507 | G40: =C40-($P$11+$O$11*$B40) -> -0.036547166 | H40: =D40-($P$12+$O$12*$B40) -> 0.00043164584 | I40: =E40-($P$13+$O$13*$B40) -> -0.0028997138 | J40: =F40-($P$14+$O$14*$B40) -> -0.0094652248
A41: ='2_CVaR_t3'!A41 -> 42347 | B41: ='2_CVaR_t3'!D41-1 -> -0.0099981321 | C41: ='Stocks Returns'!B37 -> -0.033299354 | D41: ='Stocks Returns'!C37 -> -0.015049956 | E41: ='Stocks Returns'!D37 -> -0.015148236 | F41: ='Stocks Returns'!E37 -> 0.0035196687 | G41: =C41-($P$11+$O$11*$B41) -> -0.022765484 | H41: =D41-($P$12+$O$12*$B41) -> -0.0001919559 | I41: =E41-($P$13+$O$13*$B41) -> 0.0012895228 | J41: =F41-($P$14+$O$14*$B41) -> 0.014133743
A42: ='2_CVaR_t3'!A42 -> 42348 | B42: ='2_CVaR_t3'!D42-1 -> 0.0015166943 | C42: ='Stocks Returns'!B38 -> -0.0021089631 | D42: ='Stocks Returns'!C38 -> 0.0030816641 | E42: ='Stocks Returns'!D38 -> -0.0035157108 | F42: ='Stocks Returns'!E38 -> 0.015473489 | G42: =C42-($P$11+$O$11*$B42) -> -0.0031874318 | H42: =D42-($P$12+$O$12*$B42) -> 0.0008809799 | I42: =E42-($P$13+$O$13*$B42) -> -0.0059182537 | J42: =F42-($P$14+$O$14*$B42) -> 0.01390236
A43: ='2_CVaR_t3'!A43 -> 42349 | B43: ='2_CVaR_t3'!D43-1 -> -0.016233031 | C43: ='Stocks Returns'!B39 -> -0.035928144 | D43: ='Stocks Returns'!C39 -> -0.025729647 | E43: ='Stocks Returns'!D39 -> -0.015656009 | F43: ='Stocks Returns'!E39 -> -0.022145469 | G43: =C43-($P$11+$O$11*$B43) -> -0.019106574 | H43: =D43-($P$12+$O$12*$B43) -> -0.0016349312 | I43: =E43-($P$13+$O$13*$B43) -> 0.010983153 | J43: =F43-($P$14+$O$14*$B43) -> -0.0049335096
A44: ='2_CVaR_t3'!A44 -> 42352 | B44: ='2_CVaR_t3'!D44-1 -> 0.0057643085 | C44: ='Stocks Returns'!B40 -> -0.033613445 | D44: ='Stocks Returns'!C40 -> 0.0099855472 | E44: ='Stocks Returns'!D40 -> -0.00067204301 | F44: ='Stocks Returns'!E40 -> 0.029087887 | G44: =C44-($P$11+$O$11*$B44) -> -0.038975499 | H44: =D44-($P$12+$O$12*$B44) -> 0.0014922186 | I44: =E44-($P$13+$O$13*$B44) -> -0.010024437 | J44: =F44-($P$14+$O$14*$B44) -> 0.023021854
A45: ='2_CVaR_t3'!A45 -> 42353 | B45: ='2_CVaR_t3'!D45-1 -> 0.016055274 | C45: ='Stocks Returns'!B41 -> 0.0026465028 | D45: ='Stocks Returns'!C41 -> 0.022765708 | E45: ='Stocks Returns'!D41 -> 0.032728088 | F45: ='Stocks Returns'!E41 -> 0.020795477 | G45: =C45-($P$11+$O$11*$B45) -> -0.013093665 | H45: =D45-($P$12+$O$12*$B45) -> -0.00097321111 | I45: =E45-($P$13+$O$13*$B45) -> 0.0065378452 | J45: =F45-($P$14+$O$14*$B45) -> 0.0038393541
A46: ='2_CVaR_t3'!A46 -> 42354 | B46: ='2_CVaR_t3'!D46-1 -> 0.011124812 | C46: ='Stocks Returns'!B42 -> 0.024886878 | D46: ='Stocks Returns'!C42 -> 0.015772068 | E46: ='Stocks Returns'!D42 -> 0.022574343 | F46: ='Stocks Returns'!E42 -> -0.023931962 | G46: =C46-($P$11+$O$11*$B46) -> 0.014118925 | H46: =D46-($P$12+$O$12*$B46) -> -0.00066259902 | I46: =E46-($P$13+$O$13*$B46) -> 0.0044512129 | J46: =F46-($P$14+$O$14*$B46) -> -0.035670579
A47: ='2_CVaR_t3'!A47 -> 42355 | B47: ='2_CVaR_t3'!D47-1 -> -0.0096867198 | C47: ='Stocks Returns'!B43 -> -0.025754231 | D47: ='Stocks Returns'!C43 -> -0.014650639 | E47: ='Stocks Returns'!D43 -> -0.014222034 | F47: ='Stocks Returns'!E43 -> -0.041945289 | G47: =C47-($P$11+$O$11*$B47) -> -0.01553441 | H47: =D47-($P$12+$O$12*$B47) -> -0.00025398164 | I47: =E47-($P$13+$O$13*$B47) -> 0.0017061999 | J47: =F47-($P$14+$O$14*$B47) -> -0.031660757
... A2545: ='2_CVaR_t3'!A2545 -> 45853 | B2545: ='2_CVaR_t3'!D2545-1 -> -0.0068175187 | C2545: ='Stocks Returns'!B2541 -> 0.0016652789 | D2545: ='Stocks Returns'!C2541 -> -0.0099286733 | E2545: ='Stocks Returns'!D2541 -> -0.012694126 | F2545: ='Stocks Returns'!E2541 -> -0.017202931 | G2545: =C2545-($P$11+$O$11*$B2545) -> 0.0089916014 | H2545: =D2545-($P$12+$O$12*$B2545) -> 0.00021739458 | I2545: =E2545-($P$13+$O$13*$B2545) -> -0.001460415 | J2545: =F2545-($P$14+$O$14*$B2545) -> -0.0099546411

Sheet 4_ExPost_Wealth
A2: POINT 4 - Ex-post wealth of the portfolios (initial capital EUR 100,000, 15/05/2025 - 15/08/2025)
A5: Date | B5: WARNER BROS DISCOVERY | C5: VISA 'A' | D5: MICROCHIP TECH. | E5: CONOCOPHILLIPS | F5: T-STRIP 15/05/38 (price) | G5: T-BOND 6% 15/02/26 (price) | H5: T-BOND 6 3/8% 15/08/27 (price) | I5: T-BOND 5 1/4% 15/11/28 (price) | J5: Mean-CVaR ptf wealth | K5: Markowitz ptf wealth | L5: Bond ptf wealth
A6: =Stocks!A2499 -> 45792 | B6: =Stocks!B2499 -> 9.14 | C6: =Stocks!C2499 -> 362.3 | D6: =Stocks!D2499 -> 60.8 | E6: =Stocks!E2499 -> 92.96 | F6: =INDEX(Bonds!J:J,2524) -> 52.088 | G6: =INDEX(Bonds!K:K,2524) -> 135.3281 | H6: =INDEX(Bonds!L:L,2524) -> 142.6875 | I6: =INDEX(Bonds!M:M,2524) -> 132.9219 | K6: =SUMPRODUCT(B6:E6,$S$11:$V$11)+$S$12*(1+$S$13)^0 -> 100000 | L6: =SUMPRODUCT(B6:E6,$S$15:$V$15) -> 100000 | M6: =SUMPRODUCT(F6:I6,$S$17:$V$17) -> 100000
A7: =Stocks!A2500 -> 45793 | B7: =Stocks!B2500 -> 9.16 | C7: =Stocks!C2500 -> 365.1201 | D7: =Stocks!D2500 -> 61.21 | E7: =Stocks!E2500 -> 92.43 | F7: =INDEX(Bonds!J:J,2525) -> 52.239 | G7: =INDEX(Bonds!K:K,2525) -> 135.3281 | H7: =INDEX(Bonds!L:L,2525) -> 142.7188 | I7: =INDEX(Bonds!M:M,2525) -> 132.9688 | K7: =SUMPRODUCT(B7:E7,$S$11:$V$11)+$S$12*(1+$S$13)^1 -> 100537.05 | L7: =SUMPRODUCT(B7:E7,$S$15:$V$15) -> 100020.62 | M7: =SUMPRODUCT(F7:I7,$S$17:$V$17) -> 100083.41
A8: =Stocks!A2501 -> 45796 | B8: =Stocks!B2501 -> 9.05 | C8: =Stocks!C2501 -> 367.8999 | D8: =Stocks!D2501 -> 60.57 | E8: =Stocks!E2501 -> 90.41 | F8: =INDEX(Bonds!J:J,2526) -> 52.16 | G8: =INDEX(Bonds!K:K,2526) -> 135.1875 | H8: =INDEX(Bonds!L:L,2526) -> 142.5313 | I8: =INDEX(Bonds!M:M,2526) -> 132.7969 | K8: =SUMPRODUCT(B8:E8,$S$11:$V$11)+$S$12*(1+$S$13)^2 -> 100994.99 | L8: =SUMPRODUCT(B8:E8,$S$15:$V$15) -> 98573.568 | M8: =SUMPRODUCT(F8:I8,$S$17:$V$17) -> 99948.564 | Q8: REBALANCING PARAMETERS (number of bonds purchased at each review date)
A9: =Stocks!A2502 -> 45797 | B9: =Stocks!B2502 -> 9.23 | C9: =Stocks!C2502 -> 366.8401 | D9: =Stocks!D2502 -> 60.8 | E9: =Stocks!E2502 -> 89.69 | F9: =INDEX(Bonds!J:J,2527) -> 51.043 | G9: =INDEX(Bonds!K:K,2527) -> 134.4375 | H9: =INDEX(Bonds!L:L,2527) -> 141.625 | I9: =INDEX(Bonds!M:M,2527) -> 131.7813 | K9: =SUMPRODUCT(B9:E9,$S$11:$V$11)+$S$12*(1+$S$13)^3 -> 100821.26 | L9: =SUMPRODUCT(B9:E9,$S$15:$V$15) -> 99853.62 | M9: =SUMPRODUCT(F9:I9,$S$17:$V$17) -> 98946.182 | Q9: Rebalancing 1 - 15/05/2025
A10: =Stocks!A2503 -> 45798 | B10: =Stocks!B2503 -> 8.95 | C10: =Stocks!C2503 -> 358.3 | D10: =Stocks!D2503 -> 59.25 | E10: =Stocks!E2503 -> 87.15 | F10: =INDEX(Bonds!J:J,2528) -> 51.683 | G10: =INDEX(Bonds!K:K,2528) -> 135.0625 | H10: =INDEX(Bonds!L:L,2528) -> 142.3281 | I10: =INDEX(Bonds!M:M,2528) -> 132.5 | K10: =SUMPRODUCT(B10:E10,$S$11:$V$11)+$S$12*(1+$S$13)^4 -> 99179.972 | L10: =SUMPRODUCT(B10:E10,$S$15:$V$15) -> 96873.341 | M10: =SUMPRODUCT(F10:I10,$S$17:$V$17) -> 99612.179 | Q10: Wealth available at rebalancing (CVaR / Markowitz / Bonds) | S10: 100000 | T10: 100000 | U10: 100000
A11: =Stocks!A2504 -> 45799 | B11: =Stocks!B2504 -> 9.02 | C11: =Stocks!C2504 -> 357.97 | D11: =Stocks!D2504 -> 58.05 | E11: =Stocks!E2504 -> 86.13 | F11: =INDEX(Bonds!J:J,2529) -> 51.443 | G11: =INDEX(Bonds!K:K,2529) -> 134.75 | H11: =INDEX(Bonds!L:L,2529) -> 141.9688 | I11: =INDEX(Bonds!M:M,2529) -> 132.1563 | K11: =SUMPRODUCT(B11:E11,$S$11:$V$11)+$S$12*(1+$S$13)^5 -> 99042.29 | L11: =SUMPRODUCT(B11:E11,$S$15:$V$15) -> 97171.159 | M11: =SUMPRODUCT(F11:I11,$S$17:$V$17) -> 99313.853 | Q11: Mean-CVaR ptf: no. of shares = lambda * w_i * W / P_i | S11: ='2_CVaR_t1'!$H$19*'2_CVaR_t1'!H$10*$S$10/B6 -> 0 | T11: ='2_CVaR_t1'!$H$19*'2_CVaR_t1'!I$10*$S$10/C6 -> 180.04441 | U11: ='2_CVaR_t1'!$H$19*'2_CVaR_t1'!J$10*$S$10/D6 -> 66.375535 | V11: ='2_CVaR_t1'!$H$19*'2_CVaR_t1'!K$10*$S$10/E6 -> 1.4444757
A12: =Stocks!A2505 -> 45800 | B12: =Stocks!B2505 -> 9 | C12: =Stocks!C2505 -> 353.54 | D12: =Stocks!D2505 -> 56.19 | E12: =Stocks!E2505 -> 85.19 | F12: =INDEX(Bonds!J:J,2530) -> 51.45 | G12: =INDEX(Bonds!K:K,2530) -> 134.5625 | H12: =INDEX(Bonds!L:L,2530) -> 141.6875 | I12: =INDEX(Bonds!M:M,2530) -> 131.8906 | K12: =SUMPRODUCT(B12:E12,$S$11:$V$11)+$S$12*(1+$S$13)^6 -> 98122.734 | L12: =SUMPRODUCT(B12:E12,$S$15:$V$15) -> 96753.284 | M12: =SUMPRODUCT(F12:I12,$S$17:$V$17) -> 99159.86 | Q12: Mean-CVaR ptf: cash invested at the risk-free rate | S12: =(1-'2_CVaR_t1'!$H$19)*$S$10 -> 30600
A13: =Stocks!A2506 -> 45803 | B13: =Stocks!B2506 -> 9 | C13: =Stocks!C2506 -> 353.54 | D13: =Stocks!D2506 -> 56.19 | E13: =Stocks!E2506 -> 85.19 | F13: =INDEX(Bonds!J:J,2531) -> 50.576 | G13: =INDEX(Bonds!K:K,2531) -> 133.8594 | H13: =INDEX(Bonds!L:L,2531) -> 140.8438 | I13: =INDEX(Bonds!M:M,2531) -> 130.9688 | K13: =SUMPRODUCT(B13:E13,$S$11:$V$11)+$S$12*(1+$S$13)^7 -> 98125.591 | L13: =SUMPRODUCT(B13:E13,$S$15:$V$15) -> 96753.284 | M13: =SUMPRODUCT(F13:I13,$S$17:$V$17) -> 98300.516 | Q13: Daily risk-free rate | S13: ='2_CVaR_t1'!$H$13 -> 9.3320763e-05
A14: =Stocks!A2507 -> 45804 | B14: =Stocks!B2507 -> 9.55 | C14: =Stocks!C2507 -> 359.3 | D14: =Stocks!D2507 -> 58.68 | E14: =Stocks!E2507 -> 85.55 | F14: =INDEX(Bonds!J:J,2532) -> 50.811 | G14: =INDEX(Bonds!K:K,2532) -> 133.8125 | H14: =INDEX(Bonds!L:L,2532) -> 140.8438 | I14: =INDEX(Bonds!M:M,2532) -> 131.0313 | K14: =SUMPRODUCT(B14:E14,$S$11:$V$11)+$S$12*(1+$S$13)^8 -> 99331.299 | L14: =SUMPRODUCT(B14:E14,$S$15:$V$15) -> 101356.37 | M14: =SUMPRODUCT(F14:I14,$S$17:$V$17) -> 98413.598 | Q14: Markowitz ptf: no. of shares
A15: =Stocks!A2508 -> 45805 | B15: =Stocks!B2508 -> 10.02 | C15: =Stocks!C2508 -> 359.73 | D15: =Stocks!D2508 -> 57.46 | E15: =Stocks!E2508 -> 84.58 | F15: =INDEX(Bonds!J:J,2533) -> 50.5 | G15: =INDEX(Bonds!K:K,2533) -> 133.5313 | H15: =INDEX(Bonds!L:L,2533) -> 140.5 | I15: =INDEX(Bonds!M:M,2533) -> 130.6563 | K15: =SUMPRODUCT(B15:E15,$S$11:$V$11)+$S$12*(1+$S$13)^9 -> 99329.197 | L15: =SUMPRODUCT(B15:E15,$S$15:$V$15) -> 104944.65 | M15: =SUMPRODUCT(F15:I15,$S$17:$V$17) -> 98081.808 | S15: ='3_SIM_t1'!$O$26*$T$10/B6 -> 8192.3696 | T15: ='3_SIM_t1'!$O$27*$T$10/C6 -> 4.9550888e-16 | U15: ='3_SIM_t1'!$O$28*$T$10/D6 -> 0 | V15: ='3_SIM_t1'!$O$29*$T$10/E6 -> 270.24249
A16: =Stocks!A2509 -> 45806 | B16: =Stocks!B2509 -> 10.04 | C16: =Stocks!C2509 -> 362.3999 | D16: =Stocks!D2509 -> 58.11 | E16: =Stocks!E2509 -> 85.6 | F16: =INDEX(Bonds!J:J,2534) -> 50.5 | G16: =INDEX(Bonds!K:K,2534) -> 133.5313 | H16: =INDEX(Bonds!L:L,2534) -> 140.5 | I16: =INDEX(Bonds!M:M,2534) -> 130.6563 | K16: =SUMPRODUCT(B16:E16,$S$11:$V$11)+$S$12*(1+$S$13)^10 -> 99857.373 | L16: =SUMPRODUCT(B16:E16,$S$15:$V$15) -> 105384.15 | M16: =SUMPRODUCT(F16:I16,$S$17:$V$17) -> 98081.808 | Q16: Bond ptf: no. of bonds
A17: =Stocks!A2510 -> 45807 | B17: =Stocks!B2510 -> 9.97 | C17: =Stocks!C2510 -> 365.1899 | D17: =Stocks!D2510 -> 58.04 | E17: =Stocks!E2510 -> 85.35 | F17: =INDEX(Bonds!J:J,2535) -> 50.273 | G17: =INDEX(Bonds!K:K,2535) -> 133.2813 | H17: =INDEX(Bonds!L:L,2535) -> 140.2188 | I17: =INDEX(Bonds!M:M,2535) -> 130.375 | K17: =SUMPRODUCT(B17:E17,$S$11:$V$11)+$S$12*(1+$S$13)^11 -> 100357.55 | L17: =SUMPRODUCT(B17:E17,$S$15:$V$15) -> 104743.12 | M17: =SUMPRODUCT(F17:I17,$S$17:$V$17) -> 97828.926 | S17: ='1_Bonds'!$H$8*$U$10/F6 -> 403.16388 | T17: ='1_Bonds'!$H$9*$U$10/G6 -> 0 | U17: ='1_Bonds'!$H$10*$U$10/H6 -> 280.3329 | V17: ='1_Bonds'!$H$11*$U$10/I6 -> 293.40538
A18: =Stocks!A2511 -> 45810 | B18: =Stocks!B2511 -> 10 | C18: =Stocks!C2511 -> 365.3201 | D18: =Stocks!D2511 -> 60 | E18: =Stocks!E2511 -> 86.72 | F18: =INDEX(Bonds!J:J,2536) -> 50.263 | G18: =INDEX(Bonds!K:K,2536) -> 133.125 | H18: =INDEX(Bonds!L:L,2536) -> 140.0625 | I18: =INDEX(Bonds!M:M,2536) -> 130.25 | K18: =SUMPRODUCT(B18:E18,$S$11:$V$11)+$S$12*(1+$S$13)^12 -> 100515.92 | L18: =SUMPRODUCT(B18:E18,$S$15:$V$15) -> 105359.12 | M18: =SUMPRODUCT(F18:I18,$S$17:$V$17) -> 97744.402 | Q18: Rebalancing 2 - 16/06/2025
A19: =Stocks!A2512 -> 45811 | B19: =Stocks!B2512 -> 9.94 | C19: =Stocks!C2512 -> 365.8601 | D19: =Stocks!D2512 -> 63.84 | E19: =Stocks!E2512 -> 87.91 | F19: =INDEX(Bonds!J:J,2537) -> 51.486 | G19: =INDEX(Bonds!K:K,2537) -> 133.9531 | H19: =INDEX(Bonds!L:L,2537) -> 141.0781 | I19: =INDEX(Bonds!M:M,2537) -> 131.3125 | K19: =SUMPRODUCT(B19:E19,$S$11:$V$11)+$S$12*(1+$S$13)^13 -> 100872.61 | L19: =SUMPRODUCT(B19:E19,$S$15:$V$15) -> 105189.17 | M19: =SUMPRODUCT(F19:I19,$S$17:$V$17) -> 98833.921 | Q19: Wealth available at rebalancing (CVaR / Markowitz / Bonds) | S19: =K27 -> 98691.632 | T19: =L27 -> 108372.18 | U19: =M27 -> 98240.583
A20: =Stocks!A2513 -> 45812 | B20: =Stocks!B2513 -> 9.79 | C20: =Stocks!C2513 -> 368 | D20: =Stocks!D2513 -> 64.67 | E20: =Stocks!E2513 -> 85.95 | F20: =INDEX(Bonds!J:J,2538) -> 51.177 | G20: =INDEX(Bonds!K:K,2538) -> 133.8438 | H20: =INDEX(Bonds!L:L,2538) -> 140.9375 | I20: =INDEX(Bonds!M:M,2538) -> 131.1406 | K20: =SUMPRODUCT(B20:E20,$S$11:$V$11)+$S$12*(1+$S$13)^14 -> 101313 | L20: =SUMPRODUCT(B20:E20,$S$15:$V$15) -> 103430.64 | M20: =SUMPRODUCT(F20:I20,$S$17:$V$17) -> 98619.492 | Q20: Mean-CVaR ptf: no. of shares = lambda * w_i * W / P_i | S20: ='2_CVaR_t2'!$H$19*'2_CVaR_t2'!H$10*$S$19/B28 -> 0 | T20: ='2_CVaR_t2'!$H$19*'2_CVaR_t2'!I$10*$S$19/C28 -> 173.7362 | U20: ='2_CVaR_t2'!$H$19*'2_CVaR_t2'!J$10*$S$19/D28 -> 75.134746 | V20: ='2_CVaR_t2'!$H$19*'2_CVaR_t2'!K$10*$S$19/E28 -> 2.3908263
A21: =Stocks!A2514 -> 45813 | B21: =Stocks!B2514 -> 9.65 | C21: =Stocks!C2514 -> 366.77 | D21: =Stocks!D2514 -> 64.37 | E21: =Stocks!E2514 -> 85.35 | F21: =INDEX(Bonds!J:J,2539) -> 51.177 | G21: =INDEX(Bonds!K:K,2539) -> 133.8438 | H21: =INDEX(Bonds!L:L,2539) -> 140.9375 | I21: =INDEX(Bonds!M:M,2539) -> 131.1406 | K21: =SUMPRODUCT(B21:E21,$S$11:$V$11)+$S$12*(1+$S$13)^15 -> 101073.63 | L21: =SUMPRODUCT(B21:E21,$S$15:$V$15) -> 102121.56 | M21: =SUMPRODUCT(F21:I21,$S$17:$V$17) -> 98619.492 | Q21: Mean-CVaR ptf: cash invested at the risk-free rate | S21: =(1-'2_CVaR_t2'!$H$19)*$S$19 -> 31581.322
A22: =Stocks!A2515 -> 45814 | B22: =Stocks!B2515 -> 9.82 | C22: =Stocks!C2515 -> 370.22 | D22: =Stocks!D2515 -> 65.25 | E22: =Stocks!E2515 -> 87.22 | F22: =INDEX(Bonds!J:J,2540) -> 50.85 | G22: =INDEX(Bonds!K:K,2540) -> 133.7031 | H22: =INDEX(Bonds!L:L,2540) -> 140.75 | I22: =INDEX(Bonds!M:M,2540) -> 130.8906 | K22: =SUMPRODUCT(B22:E22,$S$11:$V$11)+$S$12*(1+$S$13)^16 -> 101758.75 | L22: =SUMPRODUCT(B22:E22,$S$15:$V$15) -> 104019.62 | M22: =SUMPRODUCT(F22:I22,$S$17:$V$17) -> 98361.744 | Q22: Daily risk-free rate | S22: ='2_CVaR_t2'!$H$13 -> 9.8731645e-05
A23: =Stocks!A2516 -> 45817 | B23: =Stocks!B2516 -> 9.53 | C23: =Stocks!C2516 -> 366.6599 | D23: =Stocks!D2516 -> 68.05 | E23: =Stocks!E2516 -> 88.04 | F23: =INDEX(Bonds!J:J,2541) -> 51.382 | G23: =INDEX(Bonds!K:K,2541) -> 133.9844 | H23: =INDEX(Bonds!L:L,2541) -> 141.1094 | I23: =INDEX(Bonds!M:M,2541) -> 131.2813 | K23: =SUMPRODUCT(B23:E23,$S$11:$V$11)+$S$12*(1+$S$13)^17 -> 101307.67 | L23: =SUMPRODUCT(B23:E23,$S$15:$V$15) -> 101865.43 | M23: =SUMPRODUCT(F23:I23,$S$17:$V$17) -> 98791.612 | Q23: Markowitz ptf: no. of shares
A24: =Stocks!A2517 -> 45818 | B24: =Stocks!B2517 -> 10.01 | C24: =Stocks!C2517 -> 370.7 | D24: =Stocks!D2517 -> 69.59 | E24: =Stocks!E2517 -> 91.18 | F24: =INDEX(Bonds!J:J,2542) -> 52.011 | G24: =INDEX(Bonds!K:K,2542) -> 134.4375 | H24: =INDEX(Bonds!L:L,2542) -> 141.6875 | I24: =INDEX(Bonds!M:M,2542) -> 131.875 | K24: =SUMPRODUCT(B24:E24,$S$11:$V$11)+$S$12*(1+$S$13)^18 -> 102144.68 | L24: =SUMPRODUCT(B24:E24,$S$15:$V$15) -> 106646.33 | M24: =SUMPRODUCT(F24:I24,$S$17:$V$17) -> 99381.457 | S24: ='3_SIM_t2'!$O$26*$T$19/B28 -> 8502.2207 | T24: ='3_SIM_t2'!$O$27*$T$19/C28 -> 0 | U24: ='3_SIM_t2'!$O$28*$T$19/D28 -> 2.4396419e-15 | V24: ='3_SIM_t2'!$O$29*$T$19/E28 -> 177.77141
A25: =Stocks!A2518 -> 45819 | B25: =Stocks!B2518 -> 10.51 | C25: =Stocks!C2518 -> 373.3101 | D25: =Stocks!D2518 -> 69.6 | E25: =Stocks!E2518 -> 93.35 | F25: =INDEX(Bonds!J:J,2543) -> 51.961 | G25: =INDEX(Bonds!K:K,2543) -> 134.375 | H25: =INDEX(Bonds!L:L,2543) -> 141.6094 | I25: =INDEX(Bonds!M:M,2543) -> 131.8125 | K25: =SUMPRODUCT(B25:E25,$S$11:$V$11)+$S$12*(1+$S$13)^19 -> 102621.28 | L25: =SUMPRODUCT(B25:E25,$S$15:$V$15) -> 111328.94 | M25: =SUMPRODUCT(F25:I25,$S$17:$V$17) -> 99321.067 | Q25: Bond ptf: no. of bonds
A26: =Stocks!A2519 -> 45820 | B26: =Stocks!B2519 -> 10.16 | C26: =Stocks!C2519 -> 371.3999 | D26: =Stocks!D2519 -> 67.93 | E26: =Stocks!E2519 -> 94.69 | F26: =INDEX(Bonds!J:J,2544) -> 51.897 | G26: =INDEX(Bonds!K:K,2544) -> 134.1719 | H26: =INDEX(Bonds!L:L,2544) -> 141.4063 | I26: =INDEX(Bonds!M:M,2544) -> 131.625 | K26: =SUMPRODUCT(B26:E26,$S$11:$V$11)+$S$12*(1+$S$13)^20 -> 102171.31 | L26: =SUMPRODUCT(B26:E26,$S$15:$V$15) -> 108823.74 | M26: =SUMPRODUCT(F26:I26,$S$17:$V$17) -> 99183.316 | S26: ='1_Bonds'!$H$33*$U$19/F28 -> 481.02338 | T26: ='1_Bonds'!$H$34*$U$19/G28 -> 121.21798 | U26: ='1_Bonds'!$H$35*$U$19/H28 -> 278.97487 | V26: ='1_Bonds'!$H$36*$U$19/I28 -> 138.49591
A27: =Stocks!A2520 -> 45821 | B27: =Stocks!B2520 -> 10.03 | C27: =Stocks!C2520 -> 352.8501 | D27: =Stocks!D2520 -> 65.73 | E27: =Stocks!E2520 -> 96.96 | F27: =INDEX(Bonds!J:J,2545) -> 50.961 | G27: =INDEX(Bonds!K:K,2545) -> 133.3906 | H27: =INDEX(Bonds!L:L,2545) -> 140.4688 | I27: =INDEX(Bonds!M:M,2545) -> 130.5938 | K27: =SUMPRODUCT(B27:E27,$S$11:$V$11)+$S$12*(1+$S$13)^21 -> 98691.632 | L27: =SUMPRODUCT(B27:E27,$S$15:$V$15) -> 108372.18 | M27: =SUMPRODUCT(F27:I27,$S$17:$V$17) -> 98240.583 | Q27: Rebalancing 3 - 15/07/2025
A28: =Stocks!A2521 -> 45824 | B28: =Stocks!B2521 -> 10.76 | C28: =Stocks!C2521 -> 355.48 | D28: =Stocks!D2521 -> 68.19 | E28: =Stocks!E2521 -> 95 | F28: =INDEX(Bonds!J:J,2546) -> 51.126 | G28: =INDEX(Bonds!K:K,2546) -> 133.75 | H28: =INDEX(Bonds!L:L,2546) -> 140.8594 | I28: =INDEX(Bonds!M:M,2546) -> 130.9688 | K28: =SUMPRODUCT(B28:E28,$S$20:$V$20)+$S$21*(1+$S$22)^0 -> 98691.632 | L28: =SUMPRODUCT(B28:E28,$S$24:$V$24) -> 108372.18 | M28: =SUMPRODUCT(F28:I28,$S$26:$V$26) -> 98240.583 | Q28: Wealth available at rebalancing (CVaR / Markowitz / Bonds) | S28: =K48 -> 98327.151 | T28: =L48 -> 118852.4 | U28: =M48 -> 97663.032
A29: =Stocks!A2522 -> 45825 | B29: =Stocks!B2522 -> 10.58 | C29: =Stocks!C2522 -> 357.8401 | D29: =Stocks!D2522 -> 67.69 | E29: =Stocks!E2522 -> 95.5 | F29: =INDEX(Bonds!J:J,2547) -> 51.53 | G29: =INDEX(Bonds!K:K,2547) -> 134.2188 | H29: =INDEX(Bonds!L:L,2547) -> 141.4063 | I29: =INDEX(Bonds!M:M,2547) -> 131.5469 | K29: =SUMPRODUCT(B29:E29,$S$20:$V$20)+$S$21*(1+$S$22)^1 -> 99068.412 | L29: =SUMPRODUCT(B29:E29,$S$24:$V$24) -> 106930.66 | M29: =SUMPRODUCT(F29:I29,$S$26:$V$26) -> 98724.379 | Q29: Mean-CVaR ptf: no. of shares = lambda * w_i * W / P_i | S29: ='2_CVaR_t3'!$H$19*'2_CVaR_t3'!H$10*$S$28/B49 -> 0 | T29: ='2_CVaR_t3'!$H$19*'2_CVaR_t3'!I$10*$S$28/C49 -> 164.2581 | U29: ='2_CVaR_t3'!$H$19*'2_CVaR_t3'!J$10*$S$28/D49 -> 116.0585 | V29: ='2_CVaR_t3'!$H$19*'2_CVaR_t3'!K$10*$S$28/E49 -> 0
A30: =Stocks!A2523 -> 45826 | B30: =Stocks!B2523 -> 10.57 | C30: =Stocks!C2523 -> 340.3799 | D30: =Stocks!D2523 -> 68.02 | E30: =Stocks!E2523 -> 93.8 | F30: =INDEX(Bonds!J:J,2548) -> 52.398 | G30: =INDEX(Bonds!K:K,2548) -> 135.2344 | H30: =INDEX(Bonds!L:L,2548) -> 142.5469 | I30: =INDEX(Bonds!M:M,2548) -> 132.6875 | K30: =SUMPRODUCT(B30:E30,$S$20:$V$20)+$S$21*(1+$S$22)^2 -> 96058.792 | L30: =SUMPRODUCT(B30:E30,$S$24:$V$24) -> 106543.43 | M30: =SUMPRODUCT(F30:I30,$S$26:$V$26) -> 99741.183 | Q30: Mean-CVaR ptf: cash invested at the risk-free rate | S30: =(1-'2_CVaR_t3'!$H$19)*$S$28 -> 32841.268
A31: =Stocks!A2524 -> 45827 | B31: =Stocks!B2524 -> 10.57 | C31: =Stocks!C2524 -> 340.3799 | D31: =Stocks!D2524 -> 68.02 | E31: =Stocks!E2524 -> 93.8 | F31: =INDEX(Bonds!J:J,2549) -> 51.241 | G31: =INDEX(Bonds!K:K,2549) -> 134.1563 | H31: =INDEX(Bonds!L:L,2549) -> 141.2969 | I31: =INDEX(Bonds!M:M,2549) -> 131.3906 | K31: =SUMPRODUCT(B31:E31,$S$20:$V$20)+$S$21*(1+$S$22)^3 -> 96061.911 | L31: =SUMPRODUCT(B31:E31,$S$24:$V$24) -> 106543.43 | M31: =SUMPRODUCT(F31:I31,$S$26:$V$26) -> 98525.62 | Q31: Daily risk-free rate | S31: ='2_CVaR_t3'!$H$13 -> 0.00010065704
A32: =Stocks!A2525 -> 45828 | B32: =Stocks!B2525 -> 10.52 | C32: =Stocks!C2525 -> 338.5701 | D32: =Stocks!D2525 -> 68.97 | E32: =Stocks!E2525 -> 94.69 | F32: =INDEX(Bonds!J:J,2550) -> 51.282 | G32: =INDEX(Bonds!K:K,2550) -> 134.3906 | H32: =INDEX(Bonds!L:L,2550) -> 141.5469 | I32: =INDEX(Bonds!M:M,2550) -> 131.6094 | K32: =SUMPRODUCT(B32:E32,$S$20:$V$20)+$S$21*(1+$S$22)^4 -> 95824.108 | L32: =SUMPRODUCT(B32:E32,$S$24:$V$24) -> 106276.54 | M32: =SUMPRODUCT(F32:I32,$S$26:$V$26) -> 98673.79 | Q32: Markowitz ptf: no. of shares = w_i * W / P_i
A33: =Stocks!A2526 -> 45831 | B33: =Stocks!B2526 -> 10.68 | C33: =Stocks!C2526 -> 343.75 | D33: =Stocks!D2526 -> 68.58 | E33: =Stocks!E2526 -> 91.71 | F33: =INDEX(Bonds!J:J,2551) -> 51.3 | G33: =INDEX(Bonds!K:K,2551) -> 134.2813 | H33: =INDEX(Bonds!L:L,2551) -> 141.4375 | I33: =INDEX(Bonds!M:M,2551) -> 131.5 | K33: =SUMPRODUCT(B33:E33,$S$20:$V$20)+$S$21*(1+$S$22)^5 -> 96690.736 | L33: =SUMPRODUCT(B33:E33,$S$24:$V$24) -> 107107.13 | M33: =SUMPRODUCT(F33:I33,$S$26:$V$26) -> 98623.528 | S33: ='3_SIM_t3'!$O$26*$T$28/B49 -> 9100.2567 | T33: ='3_SIM_t3'!$O$27*$T$28/C49 -> 0 | U33: ='3_SIM_t3'!$O$28*$T$28/D49 -> 1.6193201e-15 | V33: ='3_SIM_t3'!$O$29*$T$28/E49 -> 101.31082
A34: =Stocks!A2527 -> 45832 | B34: =Stocks!B2527 -> 10.9 | C34: =Stocks!C2527 -> 351.6299 | D34: =Stocks!D2527 -> 70.43 | E34: =Stocks!E2527 -> 89.39 | F34: =INDEX(Bonds!J:J,2552) -> 51.262 | G34: =INDEX(Bonds!K:K,2552) -> 134.1563 | H34: =INDEX(Bonds!L:L,2552) -> 141.2813 | I34: =INDEX(Bonds!M:M,2552) -> 131.3125 | K34: =SUMPRODUCT(B34:E34,$S$20:$V$20)+$S$21*(1+$S$22)^6 -> 98196.332 | L34: =SUMPRODUCT(B34:E34,$S$24:$V$24) -> 108565.19 | M34: =SUMPRODUCT(F34:I34,$S$26:$V$26) -> 98520.553 | Q34: Bond ptf: no. of bonds = w_i * W / P_i
A35: =Stocks!A2528 -> 45833 | B35: =Stocks!B2528 -> 10.87 | C35: =Stocks!C2528 -> 345.26 | D35: =Stocks!D2528 -> 71.6 | E35: =Stocks!E2528 -> 89 | F35: =INDEX(Bonds!J:J,2553) -> 50.577 | G35: =INDEX(Bonds!K:K,2553) -> 133.75 | H35: =INDEX(Bonds!L:L,2553) -> 140.7813 | I35: =INDEX(Bonds!M:M,2553) -> 130.7813 | K35: =SUMPRODUCT(B35:E35,$S$20:$V$20)+$S$21*(1+$S$22)^7 -> 97179.745 | L35: =SUMPRODUCT(B35:E35,$S$24:$V$24) -> 108240.79 | M35: =SUMPRODUCT(F35:I35,$S$26:$V$26) -> 97928.745 | S35: ='1_Bonds'!$H$58*$U$28/F49 -> 489.4211 | T35: ='1_Bonds'!$H$59*$U$28/G49 -> 117.7288 | U35: ='1_Bonds'!$H$60*$U$28/H49 -> 277.58112 | V35: ='1_Bonds'!$H$61*$U$28/I49 -> 141.42628
A36: =Stocks!A2529 -> 45834 | B36: =Stocks!B2529 -> 11.15 | C36: =Stocks!C2529 -> 346.03 | D36: =Stocks!D2529 -> 70.78 | E36: =Stocks!E2529 -> 90.89 | F36: =INDEX(Bonds!J:J,2554) -> 49.915 | G36: =INDEX(Bonds!K:K,2554) -> 133.2813 | H36: =INDEX(Bonds!L:L,2554) -> 140.1875 | I36: =INDEX(Bonds!M:M,2554) -> 130.0938 | K36: =SUMPRODUCT(B36:E36,$S$20:$V$20)+$S$21*(1+$S$22)^8 -> 97259.55 | L36: =SUMPRODUCT(B36:E36,$S$24:$V$24) -> 110957.4 | M36: =SUMPRODUCT(F36:I36,$S$26:$V$26) -> 97292.621
A37: =Stocks!A2530 -> 45835 | B37: =Stocks!B2530 -> 11.3 | C37: =Stocks!C2530 -> 348.6101 | D37: =Stocks!D2530 -> 70.49 | E37: =Stocks!E2530 -> 90.17 | F37: =INDEX(Bonds!J:J,2555) -> 52.047 | G37: =INDEX(Bonds!K:K,2555) -> 134.8125 | H37: =INDEX(Bonds!L:L,2555) -> 142.0469 | I37: =INDEX(Bonds!M:M,2555) -> 132.0469 | K37: =SUMPRODUCT(B37:E37,$S$20:$V$20)+$S$21*(1+$S$22)^9 -> 97687.417 | L37: =SUMPRODUCT(B37:E37,$S$24:$V$24) -> 112104.74 | M37: =SUMPRODUCT(F37:I37,$S$26:$V$26) -> 99292.994
A38: =Stocks!A2531 -> 45838 | B38: =Stocks!B2531 -> 11.46 | C38: =Stocks!C2531 -> 355.05 | D38: =Stocks!D2531 -> 70.37 | E38: =Stocks!E2531 -> 89.74 | F38: =INDEX(Bonds!J:J,2556) -> 51.876 | G38: =INDEX(Bonds!K:K,2556) -> 135.1563 | H38: =INDEX(Bonds!L:L,2556) -> 142.375 | I38: =INDEX(Bonds!M:M,2556) -> 132.3125 | K38: =SUMPRODUCT(B38:E38,$S$20:$V$20)+$S$21*(1+$S$22)^10 -> 98799.338 | L38: =SUMPRODUCT(B38:E38,$S$24:$V$24) -> 113388.66 | M38: =SUMPRODUCT(F38:I38,$S$26:$V$26) -> 99380.73
A39: =Stocks!A2532 -> 45839 | B39: =Stocks!B2532 -> 10.94 | C39: =Stocks!C2532 -> 355.47 | D39: =Stocks!D2532 -> 71.68 | E39: =Stocks!E2532 -> 91.99 | F39: =INDEX(Bonds!J:J,2557) -> 51.012 | G39: =INDEX(Bonds!K:K,2557) -> 134.4844 | H39: =INDEX(Bonds!L:L,2557) -> 141.5313 | I39: =INDEX(Bonds!M:M,2557) -> 131.4063 | K39: =SUMPRODUCT(B39:E39,$S$20:$V$20)+$S$21*(1+$S$22)^11 -> 98979.234 | L39: =SUMPRODUCT(B39:E39,$S$24:$V$24) -> 109367.49 | M39: =SUMPRODUCT(F39:I39,$S$26:$V$26) -> 98522.804
A40: =Stocks!A2533 -> 45840 | B40: =Stocks!B2533 -> 11.12 | C40: =Stocks!C2533 -> 354.22 | D40: =Stocks!D2533 -> 73.16 | E40: =Stocks!E2533 -> 94.44 | F40: =INDEX(Bonds!J:J,2558) -> 50.648 | G40: =INDEX(Bonds!K:K,2558) -> 134.3594 | H40: =INDEX(Bonds!L:L,2558) -> 141.3594 | I40: =INDEX(Bonds!M:M,2558) -> 131.2188 | K40: =SUMPRODUCT(B40:E40,$S$20:$V$20)+$S$21*(1+$S$22)^12 -> 98882.242 | L40: =SUMPRODUCT(B40:E40,$S$24:$V$24) -> 111333.43 | M40: =SUMPRODUCT(F40:I40,$S$26:$V$26) -> 98258.635
A41: =Stocks!A2534 -> 45841 | B41: =Stocks!B2534 -> 11.22 | C41: =Stocks!C2534 -> 358.8601 | D41: =Stocks!D2534 -> 73.06 | E41: =Stocks!E2534 -> 93.68 | F41: =INDEX(Bonds!J:J,2559) -> 50.804 | G41: =INDEX(Bonds!K:K,2559) -> 134.25 | H41: =INDEX(Bonds!L:L,2559) -> 141.2813 | I41: =INDEX(Bonds!M:M,2559) -> 131.1563 | K41: =SUMPRODUCT(B41:E41,$S$20:$V$20)+$S$21*(1+$S$22)^13 -> 99682.187 | L41: =SUMPRODUCT(B41:E41,$S$24:$V$24) -> 112048.54 | M41: =SUMPRODUCT(F41:I41,$S$26:$V$26) -> 98289.97
A42: =Stocks!A2535 -> 45842 | B42: =Stocks!B2535 -> 11.22 | C42: =Stocks!C2535 -> 358.8601 | D42: =Stocks!D2535 -> 73.06 | E42: =Stocks!E2535 -> 93.68 | F42: =INDEX(Bonds!J:J,2560) -> 50.804 | G42: =INDEX(Bonds!K:K,2560) -> 134.25 | H42: =INDEX(Bonds!L:L,2560) -> 141.2813 | I42: =INDEX(Bonds!M:M,2560) -> 131.1563 | K42: =SUMPRODUCT(B42:E42,$S$20:$V$20)+$S$21*(1+$S$22)^14 -> 99685.309 | L42: =SUMPRODUCT(B42:E42,$S$24:$V$24) -> 112048.54 | M42: =SUMPRODUCT(F42:I42,$S$26:$V$26) -> 98289.97
A43: =Stocks!A2536 -> 45845 | B43: =Stocks!B2536 -> 11.02 | C43: =Stocks!C2536 -> 356.6399 | D43: =Stocks!D2536 -> 71.48 | E43: =Stocks!E2536 -> 92.55 | F43: =INDEX(Bonds!J:J,2561) -> 50.672 | G43: =INDEX(Bonds!K:K,2561) -> 134.2188 | H43: =INDEX(Bonds!L:L,2561) -> 141.2031 | I43: =INDEX(Bonds!M:M,2561) -> 131.0625 | K43: =SUMPRODUCT(B43:E43,$S$20:$V$20)+$S$21*(1+$S$22)^15 -> 99181.287 | L43: =SUMPRODUCT(B43:E43,$S$24:$V$24) -> 110147.22 | M43: =SUMPRODUCT(F43:I43,$S$26:$V$26) -> 98187.886
A44: =Stocks!A2537 -> 45846 | B44: =Stocks!B2537 -> 11.41 | C44: =Stocks!C2537 -> 354.55 | D44: =Stocks!D2537 -> 74.56 | E44: =Stocks!E2537 -> 95.79 | F44: =INDEX(Bonds!J:J,2562) -> 50.814 | G44: =INDEX(Bonds!K:K,2562) -> 134.1406 | H44: =INDEX(Bonds!L:L,2562) -> 141.1719 | I44: =INDEX(Bonds!M:M,2562) -> 131.0313 | K44: =SUMPRODUCT(B44:E44,$S$20:$V$20)+$S$21*(1+$S$22)^16 -> 99060.48 | L44: =SUMPRODUCT(B44:E44,$S$24:$V$24) -> 114039.06 | M44: =SUMPRODUCT(F44:I44,$S$26:$V$26) -> 98233.687
A45: =Stocks!A2538 -> 45847 | B45: =Stocks!B2538 -> 11.49 | C45: =Stocks!C2538 -> 357.76 | D45: =Stocks!D2538 -> 74.68 | E45: =Stocks!E2538 -> 94.53 | F45: =INDEX(Bonds!J:J,2563) -> 50.44 | G45: =INDEX(Bonds!K:K,2563) -> 133.9375 | H45: =INDEX(Bonds!L:L,2563) -> 140.875 | I45: =INDEX(Bonds!M:M,2563) -> 130.7188 | K45: =SUMPRODUCT(B45:E45,$S$20:$V$20)+$S$21*(1+$S$22)^17 -> 99627.3 | L45: =SUMPRODUCT(B45:E45,$S$24:$V$24) -> 114495.25 | M45: =SUMPRODUCT(F45:I45,$S$26:$V$26) -> 97903.057
A46: =Stocks!A2539 -> 45848 | B46: =Stocks!B2539 -> 11.65 | C46: =Stocks!C2539 -> 355.8799 | D46: =Stocks!D2539 -> 75.08 | E46: =Stocks!E2539 -> 95.37 | F46: =INDEX(Bonds!J:J,2564) -> 50.657 | G46: =INDEX(Bonds!K:K,2564) -> 134.1563 | H46: =INDEX(Bonds!L:L,2564) -> 141.125 | I46: =INDEX(Bonds!M:M,2564) -> 130.9688 | K46: =SUMPRODUCT(B46:E46,$S$20:$V$20)+$S$21*(1+$S$22)^18 -> 99335.844 | L46: =SUMPRODUCT(B46:E46,$S$24:$V$24) -> 116004.93 | M46: =SUMPRODUCT(F46:I46,$S$26:$V$26) -> 98138.329
A47: =Stocks!A2540 -> 45849 | B47: =Stocks!B2540 -> 11.73 | C47: =Stocks!C2540 -> 347.9299 | D47: =Stocks!D2540 -> 74.56 | E47: =Stocks!E2540 -> 95.61 | F47: =INDEX(Bonds!J:J,2565) -> 50.261 | G47: =INDEX(Bonds!K:K,2565) -> 133.8281 | H47: =INDEX(Bonds!L:L,2565) -> 140.7344 | I47: =INDEX(Bonds!M:M,2565) -> 130.5313 | K47: =SUMPRODUCT(B47:E47,$S$20:$V$20)+$S$21*(1+$S$22)^19 -> 97919.269 | L47: =SUMPRODUCT(B47:E47,$S$24:$V$24) -> 116727.77 | M47: =SUMPRODUCT(F47:I47,$S$26:$V$26) -> 97738.501
A48: =Stocks!A2541 -> 45852 | B48: =Stocks!B2541 -> 12.01 | C48: =Stocks!C2541 -> 350.5 | D48: =Stocks!D2541 -> 74.05 | E48: =Stocks!E2541 -> 94.17 | F48: =INDEX(Bonds!J:J,2566) -> 50.029 | G48: =INDEX(Bonds!K:K,2566) -> 133.875 | H48: =INDEX(Bonds!L:L,2566) -> 140.8125 | I48: =INDEX(Bonds!M:M,2566) -> 130.5938 | K48: =SUMPRODUCT(B48:E48,$S$20:$V$20)+$S$21*(1+$S$22)^20 -> 98327.151 | L48: =SUMPRODUCT(B48:E48,$S$24:$V$24) -> 118852.4 | M48: =SUMPRODUCT(F48:I48,$S$26:$V$26) -> 97663.032
A49: =Stocks!A2542 -> 45853 | B49: =Stocks!B2542 -> 12.03 | C49: =Stocks!C2542 -> 347.02 | D49: =Stocks!D2542 -> 73.11 | E49: =Stocks!E2542 -> 92.55 | F49: =INDEX(Bonds!J:J,2567) -> 49.832 | G49: =INDEX(Bonds!K:K,2567) -> 133.8438 | H49: =INDEX(Bonds!L:L,2567) -> 140.7344 | I49: =INDEX(Bonds!M:M,2567) -> 130.4688 | K49: =SUMPRODUCT(B49:E49,$S$29:$V$29)+$S$30*(1+$S$31)^0 -> 98327.151 | L49: =SUMPRODUCT(B49:E49,$S$33:$V$33) -> 118852.4 | M49: =SUMPRODUCT(F49:I49,$S$35:$V$35) -> 97663.032
A50: =Stocks!A2543 -> 45854 | B50: =Stocks!B2543 -> 12.58 | C50: =Stocks!C2543 -> 349.8999 | D50: =Stocks!D2543 -> 74.43 | E50: =Stocks!E2543 -> 91.51 | F50: =INDEX(Bonds!J:J,2568) -> 49.899 | G50: =INDEX(Bonds!K:K,2568) -> 133.8125 | H50: =INDEX(Bonds!L:L,2568) -> 140.7188 | I50: =INDEX(Bonds!M:M,2568) -> 130.4688 | K50: =SUMPRODUCT(B50:E50,$S$29:$V$29)+$S$30*(1+$S$31)^1 -> 98956.7 | L50: =SUMPRODUCT(B50:E50,$S$33:$V$33) -> 123752.18 | M50: =SUMPRODUCT(F50:I50,$S$35:$V$35) -> 97687.808
A51: =Stocks!A2544 -> 45855 | B51: =Stocks!B2544 -> 12.84 | C51: =Stocks!C2544 -> 349.8101 | D51: =Stocks!D2544 -> 74.3 | E51: =Stocks!E2544 -> 92.81 | F51: =INDEX(Bonds!J:J,2569) -> 49.655 | G51: =INDEX(Bonds!K:K,2569) -> 133.4063 | H51: =INDEX(Bonds!L:L,2569) -> 140.2813 | I51: =INDEX(Bonds!M:M,2569) -> 130.0156 | K51: =SUMPRODUCT(B51:E51,$S$29:$V$29)+$S$30*(1+$S$31)^2 -> 98930.168 | L51: =SUMPRODUCT(B51:E51,$S$33:$V$33) -> 126249.95 | M51: =SUMPRODUCT(F51:I51,$S$35:$V$35) -> 97335.032
A52: =Stocks!A2545 -> 45856 | B52: =Stocks!B2545 -> 12.75 | C52: =Stocks!C2545 -> 349.05 | D52: =Stocks!D2545 -> 74.78 | E52: =Stocks!E2545 -> 91.64 | F52: =INDEX(Bonds!J:J,2570) -> 49.404 | G52: =INDEX(Bonds!K:K,2570) -> 133.3125 | H52: =INDEX(Bonds!L:L,2570) -> 140.1094 | I52: =INDEX(Bonds!M:M,2570) -> 129.8125 | K52: =SUMPRODUCT(B52:E52,$S$29:$V$29)+$S$30*(1+$S$31)^3 -> 98864.33 | L52: =SUMPRODUCT(B52:E52,$S$33:$V$33) -> 125312.4 | M52: =SUMPRODUCT(F52:I52,$S$35:$V$35) -> 97124.705
A53: =Stocks!A2546 -> 45859 | B53: =Stocks!B2546 -> 12.8 | C53: =Stocks!C2546 -> 350.9399 | D53: =Stocks!D2546 -> 73.85 | E53: =Stocks!E2546 -> 91 | F53: =INDEX(Bonds!J:J,2571) -> 49.404 | G53: =INDEX(Bonds!K:K,2571) -> 133.3125 | H53: =INDEX(Bonds!L:L,2571) -> 140.1094 | I53: =INDEX(Bonds!M:M,2571) -> 129.8125 | K53: =SUMPRODUCT(B53:E53,$S$29:$V$29)+$S$30*(1+$S$31)^4 -> 99070.134 | L53: =SUMPRODUCT(B53:E53,$S$33:$V$33) -> 125702.57 | M53: =SUMPRODUCT(F53:I53,$S$35:$V$35) -> 97124.705
A54: =Stocks!A2547 -> 45860 | B54: =Stocks!B2547 -> 12.85 | C54: =Stocks!C2547 -> 351.8601 | D54: =Stocks!D2547 -> 75.26 | E54: =Stocks!E2547 -> 92.98 | F54: =INDEX(Bonds!J:J,2572) -> 49.297 | G54: =INDEX(Bonds!K:K,2572) -> 133.1719 | H54: =INDEX(Bonds!L:L,2572) -> 139.9688 | I54: =INDEX(Bonds!M:M,2572) -> 129.6406 | K54: =SUMPRODUCT(B54:E54,$S$29:$V$29)+$S$30*(1+$S$31)^5 -> 99388.234 | L54: =SUMPRODUCT(B54:E54,$S$33:$V$33) -> 126358.18 | M54: =SUMPRODUCT(F54:I54,$S$35:$V$35) -> 96992.445
A55: =Stocks!A2548 -> 45861 | B55: =Stocks!B2548 -> 13.31 | C55: =Stocks!C2548 -> 355.29 | D55: =Stocks!D2548 -> 70.25 | E55: =Stocks!E2548 -> 95.04 | F55: =INDEX(Bonds!J:J,2573) -> 49.572 | G55: =INDEX(Bonds!K:K,2573) -> 133.4375 | H55: =INDEX(Bonds!L:L,2573) -> 140.25 | I55: =INDEX(Bonds!M:M,2573) -> 129.9375 | K55: =SUMPRODUCT(B55:E55,$S$29:$V$29)+$S$30*(1+$S$31)^6 -> 99373.477 | L55: =SUMPRODUCT(B55:E55,$S$33:$V$33) -> 130753 | M55: =SUMPRODUCT(F55:I55,$S$35:$V$35) -> 97278.35
A56: =Stocks!A2549 -> 45862 | B56: =Stocks!B2549 -> 13.5 | C56: =Stocks!C2549 -> 353.97 | D56: =Stocks!D2549 -> 67.81 | E56: =Stocks!E2549 -> 95.62 | F56: =INDEX(Bonds!J:J,2574) -> 50.666 | G56: =INDEX(Bonds!K:K,2574) -> 134.4375 | H56: =INDEX(Bonds!L:L,2574) -> 141.375 | I56: =INDEX(Bonds!M:M,2574) -> 131.0938 | K56: =SUMPRODUCT(B56:E56,$S$29:$V$29)+$S$30*(1+$S$31)^7 -> 98876.781 | L56: =SUMPRODUCT(B56:E56,$S$33:$V$33) -> 132540.81 | M56: =SUMPRODUCT(F56:I56,$S$35:$V$35) -> 98407.315
A57: =Stocks!A2550 -> 45863 | B57: =Stocks!B2550 -> 13.49 | C57: =Stocks!C2550 -> 357.04 | D57: =Stocks!D2550 -> 69.21 | E57: =Stocks!E2550 -> 94.95 | F57: =INDEX(Bonds!J:J,2575) -> 50.943 | G57: =INDEX(Bonds!K:K,2575) -> 134.5625 | H57: =INDEX(Bonds!L:L,2575) -> 141.5625 | I57: =INDEX(Bonds!M:M,2575) -> 131.2813 | K57: =SUMPRODUCT(B57:E57,$S$29:$V$29)+$S$30*(1+$S$31)^8 -> 99546.844 | L57: =SUMPRODUCT(B57:E57,$S$33:$V$33) -> 132381.93 | M57: =SUMPRODUCT(F57:I57,$S$35:$V$35) -> 98636.165
A58: =Stocks!A2551 -> 45866 | B58: =Stocks!B2551 -> 13.7 | C58: =Stocks!C2551 -> 355.47 | D58: =Stocks!D2551 -> 70.53 | E58: =Stocks!E2551 -> 97.02 | F58: =INDEX(Bonds!J:J,2576) -> 50.86 | G58: =INDEX(Bonds!K:K,2576) -> 134.6563 | H58: =INDEX(Bonds!L:L,2576) -> 141.625 | I58: =INDEX(Bonds!M:M,2576) -> 131.3438 | K58: =SUMPRODUCT(B58:E58,$S$29:$V$29)+$S$30*(1+$S$31)^9 -> 99445.464 | L58: =SUMPRODUCT(B58:E58,$S$33:$V$33) -> 134502.69 | M58: =SUMPRODUCT(F58:I58,$S$35:$V$35) -> 98632.774
A59: =Stocks!A2552 -> 45867 | B59: =Stocks!B2552 -> 13.12 | C59: =Stocks!C2552 -> 351.29 | D59: =Stocks!D2552 -> 70.68 | E59: =Stocks!E2552 -> 97.99 | F59: =INDEX(Bonds!J:J,2577) -> 51.681 | G59: =INDEX(Bonds!K:K,2577) -> 135.0938 | H59: =INDEX(Bonds!L:L,2577) -> 142.2031 | I59: =INDEX(Bonds!M:M,2577) -> 131.9531 | K59: =SUMPRODUCT(B59:E59,$S$29:$V$29)+$S$30*(1+$S$31)^10 -> 98779.583 | L59: =SUMPRODUCT(B59:E59,$S$33:$V$33) -> 129322.82 | M59: =SUMPRODUCT(F59:I59,$S$35:$V$35) -> 99332.735
A60: =Stocks!A2553 -> 45868 | B60: =Stocks!B2553 -> 13.26 | C60: =Stocks!C2553 -> 350.9099 | D60: =Stocks!D2553 -> 70.29 | E60: =Stocks!E2553 -> 96.67 | F60: =INDEX(Bonds!J:J,2578) -> 51.993 | G60: =INDEX(Bonds!K:K,2578) -> 135.4531 | H60: =INDEX(Bonds!L:L,2578) -> 142.6094 | I60: =INDEX(Bonds!M:M,2578) -> 132.3594 | K60: =SUMPRODUCT(B60:E60,$S$29:$V$29)+$S$30*(1+$S$31)^11 -> 98675.194 | L60: =SUMPRODUCT(B60:E60,$S$33:$V$33) -> 130463.12 | M60: =SUMPRODUCT(F60:I60,$S$35:$V$35) -> 99697.977
A61: =Stocks!A2554 -> 45869 | B61: =Stocks!B2554 -> 13.17 | C61: =Stocks!C2554 -> 345.47 | D61: =Stocks!D2554 -> 67.59 | E61: =Stocks!E2554 -> 95.34 | F61: =INDEX(Bonds!J:J,2579) -> 51.339 | G61: =INDEX(Bonds!K:K,2579) -> 135.1875 | H61: =INDEX(Bonds!L:L,2579) -> 142.2813 | I61: =INDEX(Bonds!M:M,2579) -> 132 | K61: =SUMPRODUCT(B61:E61,$S$29:$V$29)+$S$30*(1+$S$31)^12 -> 97471.598 | L61: =SUMPRODUCT(B61:E61,$S$33:$V$33) -> 129509.35 | M61: =SUMPRODUCT(F61:I61,$S$35:$V$35) -> 99204.724
A62: =Stocks!A2555 -> 45870 | B62: =Stocks!B2555 -> 12.87 | C62: =Stocks!C2555 -> 339.3501 | D62: =Stocks!D2555 -> 66.36 | E62: =Stocks!E2555 -> 92.76 | F62: =INDEX(Bonds!J:J,2580) -> 52.441 | G62: =INDEX(Bonds!K:K,2580) -> 135.9844 | H62: =INDEX(Bonds!L:L,2580) -> 143.25 | I62: =INDEX(Bonds!M:M,2580) -> 133.0156 | K62: =SUMPRODUCT(B62:E62,$S$29:$V$29)+$S$30*(1+$S$31)^13 -> 96326.913 | L62: =SUMPRODUCT(B62:E62,$S$33:$V$33) -> 126517.9 | M62: =SUMPRODUCT(F62:I62,$S$35:$V$35) -> 100250.41
A63: =Stocks!A2556 -> 45873 | B63: =Stocks!B2556 -> 12.8 | C63: =Stocks!C2556 -> 342.1499 | D63: =Stocks!D2556 -> 66.59 | E63: =Stocks!E2556 -> 92.85 | F63: =INDEX(Bonds!J:J,2581) -> 52.589 | G63: =INDEX(Bonds!K:K,2581) -> 136.6719 | H63: =INDEX(Bonds!L:L,2581) -> 143.9531 | I63: =INDEX(Bonds!M:M,2581) -> 133.6719 | K63: =SUMPRODUCT(B63:E63,$S$29:$V$29)+$S$30*(1+$S$31)^14 -> 96816.806 | L63: =SUMPRODUCT(B63:E63,$S$33:$V$33) -> 125890 | M63: =SUMPRODUCT(F63:I63,$S$35:$V$35) -> 100691.77
A64: =Stocks!A2557 -> 45874 | B64: =Stocks!B2557 -> 12.72 | C64: =Stocks!C2557 -> 337.4299 | D64: =Stocks!D2557 -> 67.13 | E64: =Stocks!E2557 -> 93.2 | F64: =INDEX(Bonds!J:J,2582) -> 52.474 | G64: =INDEX(Bonds!K:K,2582) -> 136.4375 | H64: =INDEX(Bonds!L:L,2582) -> 143.7031 | I64: =INDEX(Bonds!M:M,2582) -> 133.4531 | K64: =SUMPRODUCT(B64:E64,$S$29:$V$29)+$S$30*(1+$S$31)^15 -> 96107.49 | L64: =SUMPRODUCT(B64:E64,$S$33:$V$33) -> 125197.43 | M64: =SUMPRODUCT(F64:I64,$S$35:$V$35) -> 100507.55
A65: =Stocks!A2558 -> 45875 | B65: =Stocks!B2558 -> 12.79 | C65: =Stocks!C2558 -> 339.74 | D65: =Stocks!D2558 -> 66.17 | E65: =Stocks!E2558 -> 93.11 | F65: =INDEX(Bonds!J:J,2583) -> 51.994 | G65: =INDEX(Bonds!K:K,2583) -> 136.125 | H65: =INDEX(Bonds!L:L,2583) -> 143.3438 | I65: =INDEX(Bonds!M:M,2583) -> 133.0469 | K65: =SUMPRODUCT(B65:E65,$S$29:$V$29)+$S$30*(1+$S$31)^16 -> 96378.837 | L65: =SUMPRODUCT(B65:E65,$S$33:$V$33) -> 125825.33 | M65: =SUMPRODUCT(F65:I65,$S$35:$V$35) -> 100078.66
A66: =Stocks!A2559 -> 45876 | B66: =Stocks!B2559 -> 11.86 | C66: =Stocks!C2559 -> 332.0901 | D66: =Stocks!D2559 -> 66.22 | E66: =Stocks!E2559 -> 92.6 | F66: =INDEX(Bonds!J:J,2584) -> 52.498 | G66: =INDEX(Bonds!K:K,2584) -> 136.8125 | H66: =INDEX(Bonds!L:L,2584) -> 144.1406 | I66: =INDEX(Bonds!M:M,2584) -> 133.8438 | K66: =SUMPRODUCT(B66:E66,$S$29:$V$29)+$S$30*(1+$S$31)^17 -> 95131.393 | L66: =SUMPRODUCT(B66:E66,$S$33:$V$33) -> 117310.43 | M66: =SUMPRODUCT(F66:I66,$S$35:$V$35) -> 100740.14
A67: =Stocks!A2560 -> 45877 | B67: =Stocks!B2560 -> 10.91 | C67: =Stocks!C2560 -> 336.78 | D67: =Stocks!D2560 -> 61.87 | E67: =Stocks!E2560 -> 93.91 | F67: =INDEX(Bonds!J:J,2585) -> 52.524 | G67: =INDEX(Bonds!K:K,2585) -> 136.8438 | H67: =INDEX(Bonds!L:L,2585) -> 144.1563 | I67: =INDEX(Bonds!M:M,2585) -> 133.9219 | K67: =SUMPRODUCT(B67:E67,$S$29:$V$29)+$S$30*(1+$S$31)^18 -> 95400.204 | L67: =SUMPRODUCT(B67:E67,$S$33:$V$33) -> 108797.9 | M67: =SUMPRODUCT(F67:I67,$S$35:$V$35) -> 100771.95
A68: =Stocks!A2561 -> 45880 | B68: =Stocks!B2561 -> 10.78 | C68: =Stocks!C2561 -> 335.8999 | D68: =Stocks!D2561 -> 60.95 | E68: =Stocks!E2561 -> 93.53 | F68: =INDEX(Bonds!J:J,2586) -> 51.869 | G68: =INDEX(Bonds!K:K,2586) -> 136.375 | H68: =INDEX(Bonds!L:L,2586) -> 143.625 | I68: =INDEX(Bonds!M:M,2586) -> 133.3438 | K68: =SUMPRODUCT(B68:E68,$S$29:$V$29)+$S$30*(1+$S$31)^19 -> 95152.178 | L68: =SUMPRODUCT(B68:E68,$S$33:$V$33) -> 107576.37 | M68: =SUMPRODUCT(F68:I68,$S$35:$V$35) -> 100166.95
A69: =Stocks!A2562 -> 45881 | B69: =Stocks!B2562 -> 11.22 | C69: =Stocks!C2562 -> 336.74 | D69: =Stocks!D2562 -> 64.5 | E69: =Stocks!E2562 -> 94.59 | F69: =INDEX(Bonds!J:J,2587) -> 52.422 | G69: =INDEX(Bonds!K:K,2587) -> 136.9219 | H69: =INDEX(Bonds!L:L,2587) -> 144.25 | I69: =INDEX(Bonds!M:M,2587) -> 134 | K69: =SUMPRODUCT(B69:E69,$S$29:$V$29)+$S$30*(1+$S$31)^20 -> 95705.491 | L69: =SUMPRODUCT(B69:E69,$S$33:$V$33) -> 111687.87 | M69: =SUMPRODUCT(F69:I69,$S$35:$V$35) -> 100768.28
A70: =Stocks!A2563 -> 45882 | B70: =Stocks!B2563 -> 12.05 | C70: =Stocks!C2563 -> 342.55 | D70: =Stocks!D2563 -> 65.75 | E70: =Stocks!E2563 -> 95.88 | F70: =INDEX(Bonds!J:J,2588) -> 52.441 | G70: =INDEX(Bonds!K:K,2588) -> 136.8125 | H70: =INDEX(Bonds!L:L,2588) -> 144.1719 | I70: =INDEX(Bonds!M:M,2588) -> 133.9375 | K70: =SUMPRODUCT(B70:E70,$S$29:$V$29)+$S$30*(1+$S$31)^21 -> 96808.216 | L70: =SUMPRODUCT(B70:E70,$S$33:$V$33) -> 119371.77 | M70: =SUMPRODUCT(F70:I70,$S$35:$V$35) -> 100734.18
A71: =Stocks!A2564 -> 45883 | B71: =Stocks!B2564 -> 11.78 | C71: =Stocks!C2564 -> 345.49 | D71: =Stocks!D2564 -> 65.99 | E71: =Stocks!E2564 -> 95.65 | F71: =INDEX(Bonds!J:J,2589) -> 52.604 | G71: =INDEX(Bonds!K:K,2589) -> 137.0313 | H71: =INDEX(Bonds!L:L,2589) -> 144.4063 | I71: =INDEX(Bonds!M:M,2589) -> 134.1719 | K71: =SUMPRODUCT(B71:E71,$S$29:$V$29)+$S$30*(1+$S$31)^22 -> 97322.302 | L71: =SUMPRODUCT(B71:E71,$S$33:$V$33) -> 116891.4 | M71: =SUMPRODUCT(F71:I71,$S$35:$V$35) -> 100937.93
A72: =Stocks!A2565 -> 45884 | B72: =Stocks!B2565 -> 11.85 | C72: =Stocks!C2565 -> 344.47 | D72: =Stocks!D2565 -> 65.71 | E72: =Stocks!E2565 -> 95.33 | F72: =INDEX(Bonds!J:J,2590) -> 52.888 | G72: =INDEX(Bonds!K:K,2590) -> 137.5313 | H72: =INDEX(Bonds!L:L,2590) -> 144.9844 | I72: =INDEX(Bonds!M:M,2590) -> 134.7656 | K72: =SUMPRODUCT(B72:E72,$S$29:$V$29)+$S$30*(1+$S$31)^23 -> 97125.575 | L72: =SUMPRODUCT(B72:E72,$S$33:$V$33) -> 117496 | M72: =SUMPRODUCT(F72:I72,$S$35:$V$35) -> 101380.23

Sheet 5_Summary_CE_RiskPremium
A2: SUMMARY OF RESULTS - certainty equivalent, risk premium, ex-post performance
A4: Quantity | B4: Rebalancing 1 | C4: Rebalancing 2 | D4: Rebalancing 3
A5: Valuation date | B5: ='2_CVaR_t1'!H3 -> 45792 | C5: ='2_CVaR_t2'!H3 -> 45824 | D5: ='2_CVaR_t3'!H3 -> 45853
A6: Observations used for estimation (T) | B6: ='2_CVaR_t1'!H5 -> 2497 | C6: ='2_CVaR_t2'!H5 -> 2519 | D6: ='2_CVaR_t3'!H5 -> 2540
A7: Annual IRR of the bond portfolio (risk free) | B7: ='2_CVaR_t1'!H12 -> 0.02379441 | C7: ='2_CVaR_t2'!H12 -> 0.025191215 | D7: ='2_CVaR_t3'!H12 -> 0.025688709
A8: Daily risk-free rate | B8: ='2_CVaR_t1'!H13 -> 9.3320763e-05 | C8: ='2_CVaR_t2'!H13 -> 9.8731645e-05 | D8: ='2_CVaR_t3'!H13 -> 0.00010065704
A9: Bond portfolio duration | B9: ='1_Bonds'!K12 -> 11.864152 | C9: ='1_Bonds'!K37 -> 12.07185 | D9: ='1_Bonds'!K62 -> 12.139775
A10: Average daily return of the risky portfolio | B10: ='2_CVaR_t1'!H14 -> 0.00073752153 | C10: ='2_CVaR_t2'!H14 -> 0.0007275108 | D10: ='2_CVaR_t3'!H14 -> 0.00071898306
A11: VaR 3% daily (loss) | B11: ='2_CVaR_t1'!H15 -> 0.028802031 | C11: ='2_CVaR_t2'!H15 -> 0.029215281 | D11: ='2_CVaR_t3'!H15 -> 0.029377076
A12: CVaR 3% daily (loss) | B12: ='2_CVaR_t1'!H16 -> 0.042674545 | C12: ='2_CVaR_t2'!H16 -> 0.042734434 | D12: ='2_CVaR_t3'!H16 -> 0.042857275
A13: STARR = (mu - rf)/CVaR | B13: ='2_CVaR_t1'!H17 -> 0.015095668 | C13: ='2_CVaR_t2'!H17 -> 0.014713642 | D13: ='2_CVaR_t3'!H17 -> 0.014427562
A14: lambda: share invested in the risky portfolio | B14: ='2_CVaR_t1'!H19 -> 0.694 | C14: ='2_CVaR_t2'!H19 -> 0.68 | D14: ='2_CVaR_t3'!H19 -> 0.666
A15: E[X] (expected wealth, base 1) | B15: ='2_CVaR_t1'!H28 -> 1.0005404 | C15: ='2_CVaR_t2'!H28 -> 1.0005263 | D15: ='2_CVaR_t3'!H28 -> 1.0005125
A16: Certainty equivalent CE | B16: ='2_CVaR_t1'!H29 -> 1.0003176 | C16: ='2_CVaR_t2'!H29 -> 1.0003131 | D16: ='2_CVaR_t3'!H29 -> 1.0003067
A17: Daily risk premium E[X] - CE | B17: ='2_CVaR_t1'!H31 -> 0.00022282459 | C17: ='2_CVaR_t2'!H31 -> 0.00021324739 | D17: ='2_CVaR_t3'!H31 -> 0.00020579541
A18: Annualized risk premium | B18: ='2_CVaR_t1'!H32 -> 0.056151796 | C18: ='2_CVaR_t2'!H32 -> 0.053738342 | D18: ='2_CVaR_t3'!H32 -> 0.051860443
A19: Absolute risk aversion ARA at CE | B19: ='2_CVaR_t1'!H33 -> 4.007633 | C19: ='2_CVaR_t2'!H33 -> 4.0075271 | D19: ='2_CVaR_t3'!H33 -> 4.0073734
A20: Daily variance of the Markowitz portfolio (SIM) | B20: ='3_SIM_t1'!O32 -> 0.00053750154 | C20: ='3_SIM_t2'!O32 -> 0.00062939189 | D20: ='3_SIM_t3'!O32 -> 0.00071525572
A21: Annualized volatility of the Markowitz portfolio | B21: ='3_SIM_t1'!O34 -> 0.36803585 | C21: ='3_SIM_t2'!O34 -> 0.39825464 | D21: ='3_SIM_t3'!O34 -> 0.42455205
A23: EX-POST WEALTH AT 15/08/2025 (initial capital EUR 100,000)
A24: Optimal mean-CVaR 3% portfolio (point 2) | B24: ='4_ExPost_Wealth'!K72 -> 97125.575 | C24: ='4_ExPost_Wealth'!K72/100000-1 -> -0.02874425
A25: Markowitz portfolio under the SIM (point 3) | B25: ='4_ExPost_Wealth'!L72 -> 117496 | C25: ='4_ExPost_Wealth'!L72/100000-1 -> 0.17496002
A26: Immunized bond portfolio (point 1) | B26: ='4_ExPost_Wealth'!M72 -> 101380.23 | C26: ='4_ExPost_Wealth'!M72/100000-1 -> 0.013802284
A28: COMMENT ON RISK AVERSION / RISK TOLERANCE
A30: The utility function u(x) = a*x - b*x^2 - ln(1 + c*e^(1-x^3)) was calibrated with a=4, b=2, c=0.5. With these
A31: parameters u'(x) > 0 and u''(x) < 0 over the whole relevant wealth range (about 0.85 - 1.15): the investor is
A32: hence non-satiated and risk-averse, with absolute risk aversion ARA = -u''/u' of about 4 at x = 1.
A34: WARNING: with the parameters used in the original version (a=2, b=1, c=3) the same function has u''(x) > 0 for
A35: x < 1.077, i.e. it is CONVEX exactly in the range where final wealth falls. With that calibration the
A36: the investor would be risk-loving, the certainty equivalent would exceed expected wealth, and the premium
A37: risk premium would be negative: the entire discussion of risk aversion and risk premium would lose its meaning.
A39: With the correct calibration the risk premium is positive, at about 5% annualized: it is the amount that
A40: the investor would be willing to pay to exchange the risky portfolio for its certain expected wealth.
A41: The premium decreases slightly from one rebalancing to the next because both lambda and the mean return decline
A42: estimated, while the CVaR stays nearly unchanged.
... A53: confirmation that the criterion is sound.
